Workbook

Sheet Sheet1
A1: in | B1: TIME | C1: DATE | D1: NAME | E1: DESCRIPTION | F1: IMEI | G1: PHONE NUMBER | H1: PRICE | I1: Amount paid | J1: STATUS | K1: IMEI FOR SWAPPED DEAL | L1: RECORD_ID | M1: DEAL LOCATION | N1: INTERNAL NOTE | O1: PAID DATE | P1: EXPENSE AMOUNT | Q1: EXPENSE DESCRIPTION | R1: CALCULATED PROFIT
A2: 1 | B2: 1 | C2: 46070 | D2: DEMEX | E2: IPHONE 16 BLACK UPDATE | G2: 2347067462101 | H2: 2500 | I2: 2500 | J2: paid | L2: 9dcfec929c764ae7a52bfd4caf78d6c5
A3: 2 | B3: 2 | C3: 46070 | D3: DAH UNIQUE | E3: GOLD IPHONE 14 PRO | G3: 2349070536253 | H3: 2500 | I3: 2500 | J3: PAID | L3: e1e76866b2b44537a367a48baed4cbb7
A4: 3 | B4: 3 | C4: 46070 | D4: HUNTER LIFE | E4: SWAPPED IPHONE 13 TO 11 PRO SILVER | G4: =IF(LEN(TRIM(D4))=0,"",IFNA(VLOOKUP(UPPER(TRIM(D4)),'CLIENT DIRECTORY'!A:B,2,FALSE),"")) | H4: 185000 | I4: 185000 | J4: PAID | L4: 252820e05f6641b4aec1103a18424f72
A5: 4 | B5: 4 | C5: 46070 | D5: RICKY | E5: IPHONE 16 PRO GOLD 100% SWAPPED WITH IPHONE 15 PRO 512GB | G5: =IF(LEN(TRIM(D5))=0,"",IFNA(VLOOKUP(UPPER(TRIM(D5)),'CLIENT DIRECTORY'!A:B,2,FALSE),"")) | H5: 280000 | I5: 280000 | J5: PAID | L5: 13b8f92dda7b4ff7825daa1e2676f734
A6: 5 | B6: 5 | C6: 46070 | D6: OSES | E6: IPHONE 14 PLUS UPDATE MIDNIGHT COLOR | G6: =IF(LEN(TRIM(D6))=0,"",IFNA(VLOOKUP(UPPER(TRIM(D6)),'CLIENT DIRECTORY'!A:B,2,FALSE),"")) | H6: 2500 | I6: 2500 | J6: PAID | L6: c2a8339184ce430f975db6123c51a7fb
A7: 6 | B7: 6 | C7: 46070 | D7: KEMI FROM SEUN | E7: IPHONE 15 PRO MAX 512GB TO IPHONE | G7: =IF(LEN(TRIM(D7))=0,"",IFNA(VLOOKUP(UPPER(TRIM(D7)),'CLIENT DIRECTORY'!A:B,2,FALSE),"")) | H7: 1500000 | I7: 1500000 | J7: PAID | L7: 3debc2aabaa842ce9d440b9b84980f2d
A8: 7 | B8: 7 | C8: 46070 | D8: IBIRONKE FAVOUR | E8: APPLE ID CREATE & SIGN IN | G8: =IF(LEN(TRIM(D8))=0,"",IFNA(VLOOKUP(UPPER(TRIM(D8)),'CLIENT DIRECTORY'!A:B,2,FALSE),"")) | H8: 10000 | I8: 10000 | J8: PAID | L8: ad63bb932f7e47abb64bae4d1546a4d8
A9: 8 | B9: 8 | C9: 46070 | D9: CLINTON GADGET | E9: IPHONE 16 256GB 354178509660284 | G9: =IF(LEN(TRIM(D9))=0,"",IFNA(VLOOKUP(UPPER(TRIM(D9)),'CLIENT DIRECTORY'!A:B,2,FALSE),"")) | H9: 800000 | I9: 800000 | J9: PAID | L9: ff964ae5a2f2444187915c0d21934773
A10: 9 | B10: 9 | C10: 46070 | D10: NURUDEEN | E10: CHIP FOR IPHONE 12 PRO PACIFIC BLUE | G10: 09122727950 | H10: 25000 | I10: 25000 | J10: PAID | L10: fb2d541894b74a0a9fcffa10378d8580
A11: 10 | B11: 10 | C11: 46070 | D11: WIZZY | E11: NATURAL TITANIUM IPHONE 15 PRO MAX IOS UPDATE | G11: 2348108686713 | H11: 2500 | I11: 2500 | J11: PAID | L11: 38425b848c1e4f8195ec6df4938be5ca
A12: 11 | B12: 11 | C12: 46068 | D12: ZEE TECH | E12: IPHONE 13 IOS UPDATE | G12: 2349033724061 | H12: 2500 | I12: 2500 | J12: PAID | L12: 7f9250f3a89542a69db22bdb2807f36b
A13: 12 | B13: 12 | C13: 46069 | D13: ZEE TECH | E13: IPHONE 13 PRO MAX IOS UPDATE | G13: 2349033724061 | H13: 2500 | I13: 2500 | J13: PAID | L13: c8dc8dfa28c343c484a7f2ba7fbf5b3f
A14: 13 | B14: 13 | C14: 46070 | D14: TUNDE BABZ | E14: CHIP FIX | G14: 2348130793960 | H14: 10000 | I14: 10000 | J14: PAID | L14: 8d69b845461f43ccad08fac46ac2348c
A15: 14 | B15: 14 | C15: 46070 | D15: KAYWISE | E15: IPHONE 15 PRO MAX P + E 512GB | G15: 2349032614464 | H15: 1000000 | I15: 1000000 | J15: PAID | L15: 81a4d573dc4a4afeab545d034c19ae52
A16: 15 | B16: 15 | C16: 46070 | D16: IAMFODIL | E16: CHIP FIX | G16: =IF(LEN(TRIM(D16))=0,"",IFNA(VLOOKUP(UPPER(TRIM(D16)),'CLIENT DIRECTORY'!A:B,2,FALSE),"")) | H16: 10000 | I16: 10000 | J16: PAID | L16: 1957f2a4eeea493ea424761b0b10eb60
A17: 16 | C17: 46070 | D17: DON | E17: IMESSAGE FIX | G17: 2348137676322 | H17: 5000 | J17: PAID | L17: 61b620789dbe4227a38d21fd9329b837
A18: 17 | B18: 1 | C18: 46064 | D18: TECH JAR | E18: GREEN IPHONE 11 FLASH | G18: 2347047512596 | H18: 3000 | I18: 3000 | J18: PAID | L18: 65b3dd616fef46bab83f7647525708c3
A19: 18 | B19: 2 | C19: 46065 | D19: DAPPER | E19: BLACK IPHONE 15 UPDATE | G19: 2349166394378 | H19: 3000 | I19: 3000 | J19: paid | L19: 3ec23fa2218f4c98b42e52e295adcada
A20: 19 | B20: 3 | C20: 46066 | D20: DEMEX | E20: IPHONE 12 PRO UPDATE | G20: 2347067462101 | H20: 2000 | I20: 2000 | J20: paid | L20: 4676473684ca4ecd9d5345b5515d9aa0
A21: 20 | B21: 4 | C21: 46063 | D21: NUMBER TELLOS | E21: NEW JERSEY USA NUMBER AND ULTRAMOBILE NUMBER REFILL | G21: 2348066173750 | H21: 90000 | J21: PAID | K21: PAID 90K OUT OF 180K | L21: 6d92fa4e661549589e511ea2c1109f42
A22: 21 | B22: 5 | C22: 46063 | D22: DAMBOX | E22: GOLD IPHONE 11 PRO MAX IOS UPDATE | G22: 09040943517 | H22: 2500 | J22: PAID | L22: 08b7c305cd444e0fb756a6a1b4fed2c7
A23: 22 | B23: 6 | C23: 46071 | D23: CH4 | E23: OUTSTANDING | G23: 2348131941406 | H23: 12500 | J23: PAID | L23: f396e68ad7e844268c3cd2c338cb4ec9
A24: 23 | B24: 7 | C24: 46060 | D24: VERTEX | E24: PINK IPHONE 15 PLUS UPDATE | G24: 2348103663581 | H24: 2500 | J24: PAID | L24: 4590d23eb8fa43579501fbc6bd071bd1
A25: 24 | B25: 8 | C25: 46060 | D25: MIKKY | E25: IPHONE 13 PRO MAX CHIP | G25: =IF(LEN(TRIM(D25))=0,"",IFNA(VLOOKUP(UPPER(TRIM(D25)),'CLIENT DIRECTORY'!A:B,2,FALSE),"")) | H25: 20000 | J25: RETURNED | L25: 9bbbf52992df41bca266eeb13d53ad91
A26: 25 | B26: 9 | C26: 46060 | D26: PRINZE GADGET | E26: IPHONE 13 UPDATE | G26: =IF(LEN(TRIM(D26))=0,"",IFNA(VLOOKUP(UPPER(TRIM(D26)),'CLIENT DIRECTORY'!A:B,2,FALSE),"")) | H26: 2500 | J26: PAID | L26: f902b4c8ea8c49a2bdb4466ed2b99884
A27: 26 | B27: 10 | C27: 46058 | D27: DENIS4WARD | E27: PS4 SLIM AND ONE GAMEPAD | G27: 2348038551439 | H27: 225000 | J27: PAID | L27: c6f548765acd4277a3081301ea7558e0
A28: 27 | B28: 11 | C28: 46057 | D28: MIDE GADGET | E28: BLUE IPHONE 16 UPDATE | G28: =IF(LEN(TRIM(D28))=0,"",IFNA(VLOOKUP(UPPER(TRIM(D28)),'CLIENT DIRECTORY'!A:B,2,FALSE),"")) | H28: 2500 | J28: PAID | L28: 1a175228683e4c7f83fa4ff7d78edd6c
A29: 28 | B29: 12 | C29: 46056 | D29: ZADDY ROLLAND | E29: TEAL 16 P+E BALANCE | G29: 2348050554029 | H29: 450000 | J29: PENDING | L29: cfb45f1f05604357b7eca2af401cc1b6
A30: 29 | B30: 13 | C30: 46056 | D30: ZADDY ROLLAND | E30: TEAL 16 P+E UPDATE | G30: 2348050554029 | H30: 2500 | J30: UNPAID | L30: 08f797e6e883406aafbd18de33d0fe07
A31: 30 | B31: 14 | C31: 46071 | D31: JAMEX | E31: OUTSTANDING BALANCE | G31: 2347033260364 | H31: 395000 | J31: PENDING | L31: 19d21d47029d41d0af0fc380928ba2cb
A32: 31 | B32: 15 | C32: 46050 | D32: AYANFE | E32: APPLE ID RECOVERY | G32: 2348138108648 | H32: 10000 | J32: PAID | L32: ee70de5352b248dda16ed018caac6dab
A33: 32 | B33: 16 | C33: 46049 | D33: DENIS4WARD | E33: ILESHA DRIVER | G33: 2348038551439 | H33: 5000 | J33: PAID | L33: 1e7c1962321a484b82cda53c4bbc338e
B34: 17 | C34: 46049 | D34: PRINZE GADGETS | E34: MIDNIGET LOCKED 14 PLUS. 81% | F34: 356295374969208 | G34: 2348073229131 | H34: 280000 | J34: PAID | L34: 523b7a62015f4f16aaa6fdcfe135e889
A35: 33 | B35: 18 | C35: 46049 | D35: DENIS4WARD | E35: GAS FILL | G35: 2348038551439 | H35: 16250 | J35: PAID | L35: 69bdbb71ddb34659b3c51ffc3f27914b
A36: 34 | B36: .. | C36: .. | D36: .. | E36: .. | F36: .. | G36: =IF(LEN(TRIM(D36))=0,"",IFNA(VLOOKUP(UPPER(TRIM(D36)),'CLIENT DIRECTORY'!A:B,2,FALSE),"")) | H36: .. | L36: 259c651fb2fc45bea1649447a37d344c
A37: 35 | B37: 1 | C37: 46071 | D37: NURUDEEN | E37: NATURAL TITANIUM 15 PRO UPDATE | G37: 09122727950 | H37: 2500 | J37: PAID | L37: 3a3ee298459f443e97ad50509eb0e3dd
A38: 36 | B38: 2 | C38: 46071 | D38: DAMBOX | E38: ORANGE IPHONE 17 PRO IOS UPDATE | G38: 09040943517 | H38: 2500 | J38: PAID | L38: 860f6063e1f64ed69181fea34c1331b6
A39: 37 | B39: 3 | C39: 46071 | D39: KAYWISE | E39: ULTRAMARINE IPHONE 16 PLUS UPDATE | G39: 2349032614464 | H39: 2000 | I39: 2000 | J39: PAID | L39: b263752956ea49d493083d288125523d
A40: 38 | B40: 4 | C40: 46071 | D40: PANKEY | E40: WHITE IPHONE 15 FIX BATTERY FLASH | G40: =IF(LEN(TRIM(D40))=0,"",IFNA(VLOOKUP(UPPER(TRIM(D40)),'CLIENT DIRECTORY'!A:B,2,FALSE),"")) | H40: 2500 | J40: PAID | L40: 1cbe6952e28545e786673dbdbb797adf
A41: 39 | B41: 5 | C41: 46071 | D41: THANKGOD | E41: IPHONE 16 ROUGH BODY SWAPPED WITH IPHONE 15 PTO MAX LOCKED NATURAL TITANIUM | G41: =IF(LEN(TRIM(D41))=0,"",IFNA(VLOOKUP(UPPER(TRIM(D41)),'CLIENT DIRECTORY'!A:B,2,FALSE),"")) | H41: 380000 | J41: PAID | L41: bf9eb880a87d40c59d132b0de1fa1c21
A42: 40 | B42: 6 | C42: 46071 | D42: JAYJOSH | E42: CHIP FIX IPHONE 13 | G42: =IF(LEN(TRIM(D42))=0,"",IFNA(VLOOKUP(UPPER(TRIM(D42)),'CLIENT DIRECTORY'!A:B,2,FALSE),"")) | H42: 10000 | J42: PAID | L42: 1fb7ef6836d24151a7f090a42d18e786
A43: 41 | B43: 7 | C43: 46071 | D43: BIGGIE - MELTRONICS | E43: HP PAVILION 1TB HDD | G43: =IF(LEN(TRIM(D43))=0,"",IFNA(VLOOKUP(UPPER(TRIM(D43)),'CLIENT DIRECTORY'!A:B,2,FALSE),"")) | H43: 290000 | J43: PAID | L43: 303affb6d32d4981b8b8fedc73b99291
A44: 42 | B44: 8 | C44: 46071 | D44: EMPEROR CORPER | E44: SUPERBIKE MAN DISPATCH TO ENGINEER ISAAC | G44: =IF(LEN(TRIM(D44))=0,"",IFNA(VLOOKUP(UPPER(TRIM(D44)),'CLIENT DIRECTORY'!A:B,2,FALSE),"")) | H44: 3000 | J44: PAID | L44: 659a57f80bc94538946b864ec33870e7
A45: 43 | B45: 9 | C45: 46071 | D45: OLLY | E45: ESIM 1 MONTH | G45: =IF(LEN(TRIM(D45))=0,"",IFNA(VLOOKUP(UPPER(TRIM(D45)),'CLIENT DIRECTORY'!A:B,2,FALSE),"")) | H45: 35000 | J45: PAID | L45: b1f5c60eb3504112b40d0c61a6075916
A46: 44 | B46: 10 | C46: 45975 | D46: DENIS4WARD | E46: CONVOCATION DRINK | G46: 2348038551439 | H46: 40000 | J46: PAID | L46: 11f19a7f43ff44c189d963304bd3b32c
B47: 11 | C47: 46035 | D47: DENIS4WARD | E47: GAS FILL | G47: 2348038551439 | H47: 16250 | J47: PAID | L47: b5279189300d42909bff74710f3f263a
A48: 45 | C48: .. | D48: .. | E48: .. | F48: .. | G48: =IF(LEN(TRIM(D48))=0,"",IFNA(VLOOKUP(UPPER(TRIM(D48)),'CLIENT DIRECTORY'!A:B,2,FALSE),"")) | H48: .. | J48: .. | L48: 99aa324644f94ceea7045ff30a389a90
A49: 46 | B49: 1 | C49: 46072 | D49: MOBILETRENDS | E49: IPHONE 11 APPLE ID INACTIVE FIX | G49: =IF(LEN(TRIM(D49))=0,"",IFNA(VLOOKUP(UPPER(TRIM(D49)),'CLIENT DIRECTORY'!A:B,2,FALSE),"")) | H49: 12000 | J49: RETURNED | L49: 77b5d09c077f4d6bb71031d0575f0baa
A50: 47 | B50: 2 | C50: 46072 | D50: BARRY | E50: PURPLE 14 PRO MAX IOS UPDATE TO 26.3 | G50: 2347031524935 | H50: 2500 | J50: UNPAID | L50: cb1db8e857d84f30a5621e87a66cf2fd
A51: 48 | B51: 3 | C51: 46072 | D51: DEMEX | E51: BLACK 15 PRO IOS UPDATE TO IOS 26.3 | G51: 2347067462101 | H51: 2500 | I51: 2500 | J51: paid | L51: 011c609d98814386ad639710a2987b95
A52: 49 | B52: 4 | C52: 46072 | D52: DAMBOX | E52: BLACK 16 PLUS IOS UPDATE | G52: 09040943517 | H52: 2500 | J52: PAID | L52: 7f9d7500f604451d8bb942ea99fdbd24
A53: 50 | B53: 5 | C53: 46072 | D53: TUNDE BABZ | E53: NIGERIA APPLE ID | G53: 2348130793960 | H53: 5000 | J53: PAID | L53: 28546211501b4ccd86b71da450e83548
A54: 51 | B54: 6 | C54: 46072 | D54: IBRAHIM GADGS | E54: HP ELITEBOOK 1030G2 16GB + 256GB SSD | G54: =IF(LEN(TRIM(D54))=0,"",IFNA(VLOOKUP(UPPER(TRIM(D54)),'CLIENT DIRECTORY'!A:B,2,FALSE),"")) | H54: 360000 | J54: PAID | L54: 23c2b2928df544d29c8108a50e93ab07
A55: 52 | B55: 7 | C55: 46072 | D55: PHILIPS OLUWAFEMI | E55: LOCATION ON IPHONE AIR IOS 26 | G55: =IF(LEN(TRIM(D55))=0,"",IFNA(VLOOKUP(UPPER(TRIM(D55)),'CLIENT DIRECTORY'!A:B,2,FALSE),"")) | H55: 5000 | J55: PAID | L55: d7f133b8cd1e4dd1ad64d817b1d16d34
A56: 53 | B56: 8 | C56: 46072 | D56: RAYMOND FLASH | E56: IPHONE 15 PRO BLUE TITANIUM P + E 87% | G56: =IF(LEN(TRIM(D56))=0,"",IFNA(VLOOKUP(UPPER(TRIM(D56)),'CLIENT DIRECTORY'!A:B,2,FALSE),"")) | H56: 830000 | J56: PAID | L56: 307d09a37adb4a178a0f674eafd48d11
A57: 54 | B57: 9 | C57: 46072 | D57: JENNIFER | E57: IPHOPNE 16 E BLACK 354741550229463 | G57: =IF(LEN(TRIM(D57))=0,"",IFNA(VLOOKUP(UPPER(TRIM(D57)),'CLIENT DIRECTORY'!A:B,2,FALSE),"")) | H57: 400000 | J57: PAID | L57: d23616dfdf79461f8541f9ead5c0ce85
A58: 55 | B58: .. | C58: .. | D58: .. | E58: .. | F58: ... | G58: =IF(LEN(TRIM(D58))=0,"",IFNA(VLOOKUP(UPPER(TRIM(D58)),'CLIENT DIRECTORY'!A:B,2,FALSE),"")) | H58: ... | J58: .. | L58: b6692a162ae94d16960dfcdd3c59e242
A59: 56 | B59: .. | C59: .. | D59: .. | E59: .. | F59: ... | G59: =IF(LEN(TRIM(D59))=0,"",IFNA(VLOOKUP(UPPER(TRIM(D59)),'CLIENT DIRECTORY'!A:B,2,FALSE),"")) | H59: ... | J59: .. | L59: 82ff85b965ef4000b65f89e3d3a96c2a
A60: 57 | B60: 1 | C60: 46073 | D60: BAYESH | E60: GOLD IPHONE XS IOS UPDATE | G60: 2348136276066 | H60: 2500 | J60: PAID | L60: 97b672e02eca43ca8ee818a9261eea9e
A61: 58 | B61: 2 | C61: 46073 | D61: FEMZ GADGET | E61: IPHONE 12 128GB WHITE 359035292273391 91% | G61: =IF(LEN(TRIM(D61))=0,"",IFNA(VLOOKUP(UPPER(TRIM(D61)),'CLIENT DIRECTORY'!A:B,2,FALSE),"")) | H61: 265000 | J61: PAID | L61: 20810a056f264a6d8dad7b02782070fb
A62: 59 | B62: 3 | C62: 46073 | D62: FM LORD | E62: NIGERIA APPLE ID CREATE | G62: =IF(LEN(TRIM(D62))=0,"",IFNA(VLOOKUP(UPPER(TRIM(D62)),'CLIENT DIRECTORY'!A:B,2,FALSE),"")) | H62: 5000 | J62: PAID | L62: 8b827bfe21c94d37b87a9c19e6cd1540
A63: 60 | B63: 4 | C63: 46073 | D63: FORMULA | E63: BLUE IPHONE 13 IOS UPDATE | G63: 2347067612418 | H63: 2500 | J63: PAID | L63: ccedac4140b9443684d14cf83f03a2ec
A64: 61 | B64: 5 | C64: 46073 | D64: FOLAKEMI | E64: PURPLE IPHONE 14 PRO MAX IOS UPDATE | G64: 2349075624207 | H64: 2500 | J64: PAID | L64: f47836ca49134dfd903ed1d3f420dbaa
A65: 62 | B65: 6 | C65: 46073 | D65: BIMKEM | E65: IPHONE 13 128GB 100% | G65: =IF(LEN(TRIM(D65))=0,"",IFNA(VLOOKUP(UPPER(TRIM(D65)),'CLIENT DIRECTORY'!A:B,2,FALSE),"")) | H65: 368000 | J65: PAID | L65: 95319025ec8b4cd5a83f755bde556535
A66: 63 | B66: 7 | C66: 46073 | D66: FORMULA | E66: IPHONE 16 TEAL | G66: 2347067612418 | H66: 2500 | J66: PAID | L66: c2c427764c2a4778990c3b8c76c360b8
A67: 64 | B67: 8 | C67: 46073 | D67: ANOINTED WEALTH | E67: IPHONE 15 UPDATE | G67: 2348137226383 | H67: 2500 | J67: PAID | L67: 85e27ef19a9f4982952a54eaf24ca700
A68: 65 | B68: 9 | C68: 46058 | D68: ANOINTED WEALTH | E68: IPHONE 16 PRO MAX UPDATE | G68: 2348137226383 | H68: 2500 | J68: PAID | L68: 9da89966b8024927962ca916a386bf9c
A69: 66 | B69: 10 | C69: 46073 | D69: POPOOLA MATTHEW | E69: 2 LOCATION CHANGE FOR IOS 18+ | G69: =IF(LEN(TRIM(D69))=0,"",IFNA(VLOOKUP(UPPER(TRIM(D69)),'CLIENT DIRECTORY'!A:B,2,FALSE),"")) | H69: 10000 | J69: PAID | L69: a38eafede69a423e9af8336b7c02c409
A70: 67 | B70: 11 | C70: 46073 | D70: GOLD GADGET | E70: IPHONE 12 LOCATION CHANGE | G70: =IF(LEN(TRIM(D70))=0,"",IFNA(VLOOKUP(UPPER(TRIM(D70)),'CLIENT DIRECTORY'!A:B,2,FALSE),"")) | H70: 5000 | J70: PAID | L70: da4ee50a72ba4777942c220a4b94198e
A71: 68 | B71: 12 | C71: 46073 | D71: OLAFISOYE OLUWATOSIN | E71: CHIP FOR PURPLE IPHONE 11 | G71: =IF(LEN(TRIM(D71))=0,"",IFNA(VLOOKUP(UPPER(TRIM(D71)),'CLIENT DIRECTORY'!A:B,2,FALSE),"")) | H71: 15000 | J71: PAID | L71: 9d987e002bde459998b1af78298c570e
A72: 69 | B72: 13 | C72: 46073 | D72: STAR BUSSY | E72: GOLD IPHONE 11 PRO MAX IOS UPDATE | G72: 2348127738411 | H72: 2500 | J72: PAID | L72: d665cc1e0b7e4679a421a4aad3e680f0
A73: 70 | B73: 14 | C73: 46073 | D73: GADGET AND EXCHANGE | E73: BLACK IPHONE 11 IOS BYPASS | G73: =IF(LEN(TRIM(D73))=0,"",IFNA(VLOOKUP(UPPER(TRIM(D73)),'CLIENT DIRECTORY'!A:B,2,FALSE),"")) | H73: 25000 | J73: PAID | L73: 287e9de21e9d44c7a77fb9560c846a87
A74: 71 | B74: 15 | C74: 46073 | D74: HOLLAH | E74: IPHONE AIR IOS UPDATE BLACK | G74: =IF(LEN(TRIM(D74))=0,"",IFNA(VLOOKUP(UPPER(TRIM(D74)),'CLIENT DIRECTORY'!A:B,2,FALSE),"")) | H74: 2500 | J74: PAID | L74: dc95f285f2f948e28865082ab931b555
A75: 72 | B75: 16 | C75: 46073 | D75: THANKGOD CUSTOMER | E75: S24 ULTRA OS UPDATE | G75: =IF(LEN(TRIM(D75))=0,"",IFNA(VLOOKUP(UPPER(TRIM(D75)),'CLIENT DIRECTORY'!A:B,2,FALSE),"")) | H75: 5000 | J75: PAID | L75: 44dab883c86b4c6e9a43d997109a6667
A76: 73 | B76: 17 | C76: 46073 | D76: CUSTOMER | E76: PERMANENT CHIP FOR IPHONE 13 | G76: 2341234567890 | H76: 25000 | J76: PAID | L76: c1036001dc9c4dd9b5cc2af6253b4012
A77: 74 | B77: 18 | C77: 46073 | D77: DEMEX | E77: SKY BLUE IPHONE 15 IOS UPDATE | G77: 2347067462101 | H77: 2500 | I77: 2500 | J77: paid | L77: af82da8a2df94a09a187baf4c5d98699
A78: 76 | B78: 19 | C78: 46073 | D78: OZ GADGET | E78: SCREEN TIME PASSWORD REMOVAL | G78: 2348106293924 | H78: 5000 | J78: PAID | L78: d6c383b4b3b044749c7d5c541d20ed91
A79: 77 | B79: 20 | C79: 46073 | D79: TOBI DAVID | E79: 11 PRO MAX CHIP | G79: =IF(LEN(TRIM(D79))=0,"",IFNA(VLOOKUP(UPPER(TRIM(D79)),'CLIENT DIRECTORY'!A:B,2,FALSE),"")) | H79: 15000 | J79: PAID | L79: b493d019bdab44d99219bbfe48f534aa
A80: 78 | B80: .. | C80: .. | D80: .. | E80: .. | F80: .. | G80: =IF(LEN(TRIM(D80))=0,"",IFNA(VLOOKUP(UPPER(TRIM(D80)),'CLIENT DIRECTORY'!A:B,2,FALSE),"")) | H80: .. | J80: .. | L80: 2bae46277e624bb497f4ea485378b54e
A81: 79 | C81: .. | D81: .. | E81: .. | F81: .. | G81: =IF(LEN(TRIM(D81))=0,"",IFNA(VLOOKUP(UPPER(TRIM(D81)),'CLIENT DIRECTORY'!A:B,2,FALSE),"")) | H81: .. | J81: .. | L81: 8034b9cfc29146a7b02f995313a82b96
A82: 80 | B82: 1 | C82: 46074 | D82: DAMBOX | E82: IPHONE AIR IOS UPDATE | G82: 09040943517 | H82: 2500 | J82: PAID | L82: c694551436c641b2905b330e7ffde5d9
A83: 81 | B83: 2 | C83: 46074 | D83: DAH UNIQUE | E83: BLACK 14 PRO MAX IOS UPDATE | G83: 2349070536253 | H83: 2500 | J83: PAID | L83: 4d85b5525de34cb0b3cd164ba76d018f
A84: 82 | B84: 3 | C84: 46074 | D84: LIZZIE TECHBOX | E84: APPLE ID PASSWORD RECOVERY | G84: =IF(LEN(TRIM(D84))=0,"",IFNA(VLOOKUP(UPPER(TRIM(D84)),'CLIENT DIRECTORY'!A:B,2,FALSE),"")) | H84: 15000 | J84: PAID | L84: 52e1028a443d421a8f616965d43f7198
A85: 83 | B85: 4 | C85: 46074 | D85: RAYMOND FLASH | E85: IPHONE 16 PRO BLACK 352657194592433 95% | G85: =IF(LEN(TRIM(D85))=0,"",IFNA(VLOOKUP(UPPER(TRIM(D85)),'CLIENT DIRECTORY'!A:B,2,FALSE),"")) | H85: 9300000 | J85: PAID | L85: c4718bc3cc4d40d7b902fb22cc4140c1
A86: 84 | B86: 5 | C86: 46074 | D86: PABLO | E86: GOLD IPHONE 16 PRO MAX IOS UPDATE | G86: =IF(LEN(TRIM(D86))=0,"",IFNA(VLOOKUP(UPPER(TRIM(D86)),'CLIENT DIRECTORY'!A:B,2,FALSE),"")) | H86: 2500 | J86: PAID | L86: 3708bbba431146d7a8ce439730664e4d
A87: 85 | B87: 6 | C87: 46075 | D87: PABLO | E87: CHIP ONLY FOR IPHONE 16 PRO MAX WITHOUT ESIM | G87: =IF(LEN(TRIM(D87))=0,"",IFNA(VLOOKUP(UPPER(TRIM(D87)),'CLIENT DIRECTORY'!A:B,2,FALSE),"")) | H87: 15000 | J87: PAID | L87: ebf56a10fdf24b9f86c1b7f2d24127e4
A88: 86 | B88: 7 | C88: 46074 | D88: PANKEY | E88: SILVER IPHONE 17 PRO MAX IOS UPDATE | G88: =IF(LEN(TRIM(D88))=0,"",IFNA(VLOOKUP(UPPER(TRIM(D88)),'CLIENT DIRECTORY'!A:B,2,FALSE),"")) | H88: 2500 | J88: PAID | L88: 84b08607f0144d3d9159c52f38331244
A89: 87 | B89: 8 | C89: 46074 | D89: MR AYODELE | E89: SAMSUNG A17 FRP FIX | G89: =IF(LEN(TRIM(D89))=0,"",IFNA(VLOOKUP(UPPER(TRIM(D89)),'CLIENT DIRECTORY'!A:B,2,FALSE),"")) | H89: 15000 | J89: PAID | L89: cbf8150f13c64c69bf9f24433737d50f
A90: 88 | B90: 9 | C90: 46074 | D90: TOP MAN | E90: IPHONE 13 WHITE IOS UPDATE | G90: =IF(LEN(TRIM(D90))=0,"",IFNA(VLOOKUP(UPPER(TRIM(D90)),'CLIENT DIRECTORY'!A:B,2,FALSE),"")) | H90: 2500 | J90: PAID | L90: 01e26a8d2b654b60a6a3d0bfd4232177
A91: 89 | B91: . | C91: .. | D91: .. | E91: .. | F91: ... | G91: =IF(LEN(TRIM(D91))=0,"",IFNA(VLOOKUP(UPPER(TRIM(D91)),'CLIENT DIRECTORY'!A:B,2,FALSE),"")) | H91: .. | J91: .. | L91: c6bfd29e311547ecbda0a4d8f5e08821
A92: 90 | C92: .. | D92: .. | E92: .. | F92: .. | G92: =IF(LEN(TRIM(D92))=0,"",IFNA(VLOOKUP(UPPER(TRIM(D92)),'CLIENT DIRECTORY'!A:B,2,FALSE),"")) | H92: .. | J92: .. | L92: 6bb782d201984c2999cf627a821b01fe
A93: 91 | B93: 1 | C93: 46076 | D93: CHUSTER | E93: NIGERIA APPLE ID | G93: =IF(LEN(TRIM(D93))=0,"",IFNA(VLOOKUP(UPPER(TRIM(D93)),'CLIENT DIRECTORY'!A:B,2,FALSE),"")) | H93: 4000 | J93: PAID | L93: 761d456d208b4da796a02b920dbd55c5
A94: 92 | B94: 2 | C94: 46076 | D94: AWILO | E94: APPLE WATCH SERIES 9 | G94: =IF(LEN(TRIM(D94))=0,"",IFNA(VLOOKUP(UPPER(TRIM(D94)),'CLIENT DIRECTORY'!A:B,2,FALSE),"")) | H94: 250000 | J94: PAID | L94: 0d28acc2d09f4982a4e8313c2fb14917
A95: 93 | B95: 3 | C95: 46076 | D95: DAMBOX | E95: IPHONE 17 AIR IOS UPDATE | G95: 09040943517 | H95: 2500 | J95: PAID | L95: d983d9aa162748069b6402ab482f72ff
A96: 94 | B96: 4 | C96: 46076 | D96: ZEE TECH | E96: IPHONE 11 PRO PASSWORD FLASH | G96: 2349033724061 | H96: 2500 | J96: PAID | L96: 5abfcab43e33484e8348fbebb46dd850
A97: 95 | B97: 5 | C97: 46076 | D97: OSAMA CUSTOMER | E97: NIGERIA APPLE ID CREATE | G97: =IF(LEN(TRIM(D97))=0,"",IFNA(VLOOKUP(UPPER(TRIM(D97)),'CLIENT DIRECTORY'!A:B,2,FALSE),"")) | H97: 5000 | J97: PAID | L97: d08f3e69b6f74269a268ddd490ebf54b
A98: 96 | B98: 6 | C98: 46076 | D98: OSAMA | E98: IPHONE 12 PRO SDP FLASH | G98: 2348140672915 | H98: 3000 | J98: PAID | L98: c134793da67c4565aa3aeb4f41d85c6b
A99: 97 | B99: 7 | C99: 46076 | D99: DENIS4WARD | E99: 3K CASH FOR DISPATCH | G99: 2348038551439 | H99: 3000 | J99: PAID | L99: 94357384bea040b9861cca9151d11585
A100: 98 | B100: 8 | C100: 46076 | D100: STARBOX | E100: IPHONE 17 AIR IOS UPDATE | G100: 2349063620334 | H100: 2500 | J100: PAID | L100: 40edcb7b32b04aa8b425278bbdb1eae4
...

Sheet Debtors Summary
A1: Name | B1: Outstanding Amount
A2: BIGMO | B2: NGN 1,150,000
A3: MBENZ | B3: NGN 875,000
A4: DAMBOX | B4: NGN 825,000
A5: AFRIKA | B5: NGN 580,000
A6: MD GADGS | B6: NGN 475,000
A7: ZADDY ROLLAND | B7: NGN 452,500
A8: JAMEX | B8: NGN 395,000
A9: SAMMY CONCEPT | B9: NGN 392,500
A10: PHLEMZY | B10: NGN 305,000
A11: DREY | B11: NGN 300,000
A12: ZEE | B12: NGN 37,500
... A52: ISAIAH BIKEMAN | B52: NGN 2,000

Sheet CLIENT DIRECTORY
A1: NAME | B1: PHONE NUMBER
A2: ACTIVE | B2: 2348145310779
A3: ADEBAYO ROKEEB | B3: 2348073670589
A4: ADESOLA AYODELE | B4: 2349166314423
A5: ADEX GADGETS | B5: 2347067852062
A6: ADEYEYE | B6: 2347069117214
A7: AFRIKA | B7: 2349032711183
A8: AHB | B8: 2349136777731
A9: AKINPELUMI MEE | B9: 2349039596257
A10: ANNIE | B10: 2348141375361
A11: ANOINTED WEALTH | B11: 2348137226383
A12: AREMO | B12: 2349037888923
... A176: ZINTO | B176: 2349068103734

Sheet CASH FLOW
A1: DATE | B1: CATEGORY | C1: AMOUNT | D1: DESCRIPTION | E1: CREATED BY | F1: SOURCE | G1: PAYMENT_STATUS | H1: TYPE | I1: COST_PRICE | J1: PAYMENT_DATE | K1: Column 11 | L1: Column 12 | M1: Column 13 | N1: Column 14 | O1: Column 15 | P1: Column 16 | Q1: Column 17 | R1: Column 18 | S1: Column 19 | T1: Column 20 | U1: Column 21 | V1: Column 22 | W1: Column 23 | X1: Column 24 | Y1: Column 25 | Z1: Column 26 | AA1: Column 27 | AB1: Column 28 | AC1: Column 29 | AD1: Column 30 | AE1: Column 31 | AF1: Column 32 | AG1: Column 33 | AH1: Column 34 | AI1: Column 35
A2: 46146 | B2: SERVICE PROFIT | C2: 5000 | D2: ICLOUD OPENING: NIGERIA | NOTE: Blessing oluwaseun, blessingoluwaseunogunleye@gmail.com, 07035919593 , Password provided: AppleID2026# adjusted date to 2004 from 2006 | E2: SAM EXCHANGE | F2: income | G2: PAID | H2: service | J2: 46146
A3: 46146 | B3: SERVICE PROFIT | C3: 2500 | D3: IPHONE 12 PRO MAX GOLD IOS UPDATE | E3: GLORY HOLLAH GADGETS | F3: income | G3: PAID | H3: service | J3: 46146
A4: 46146 | B4: SERVICE PROFIT | C4: 3000 | D4: IPHONE 14 PRO IOS UPDATE: SPACE BLACK | E4: DELIGHT | F4: income | G4: PAID | H4: service | J4: 46146
A5: 46146 | B5: SERVICE PROFIT | C5: 2500 | D5: IPHONE 15 PLUS IOS UPDATE: sky blue | E5: WIZZY | F5: income | G5: PAID | H5: service | J5: 46146
A6: 46146 | B6: SERVICE PROFIT | C6: 5000 | D6: IPHONE XSMAX SYSTEM DATA SPACE FIX | E6: IJEOMA | F6: income | G6: PAID | H6: service | J6: 46146
A7: 46146 | B7: SERVICE PROFIT | C7: 25000 | D7: STABLE CHIP FOR IPHONE 12 | E7: DAMOLA FCG | F7: income | G7: PAID | H7: service | J7: 46146
A8: 46147 | B8: PHONE PROFIT | C8: 80000 | D8: IPHONE 17 PRO MAX | E8: ANOINTED WEALTH | F8: income | G8: PAID | H8: phone | I8: 1180000 | J8: 46147
A9: 46147 | B9: SERVICE PROFIT | C9: 3000 | D9: CHIP FIX | E9: EMMANUEL OLAMILEKAN | F9: income | G9: PAID | H9: service | J9: 46147
A10: 46147 | B10: SERVICE PROFIT | C10: 2000 | D10: CUSTOMER FILE TRANSFER | E10: ANOINTED WEALTH | F10: income | G10: PAID | H10: service | J10: 46147
A11: 46147 | B11: SERVICE PROFIT | C11: 3000 | D11: ICLOUD OPENING: NIGERIA | E11: AHB | F11: income | G11: PAID | H11: service | J11: 46147
A12: 46147 | B12: SERVICE PROFIT | C12: 10000 | D12: ICLOUD OPENING: USA | E12: OLUFAD TELECOMMUNICATION | F12: income | G12: PAID | H12: service | J12: 46147
A13: 46147 | B13: SERVICE PROFIT | C13: 2500 | D13: IPHONE 12 IOS UPDATE: Blue | E13: BIG INVESTOR | F13: income | G13: PAID | H13: service | J13: 46147
A14: 46147 | B14: SERVICE PROFIT | C14: 3000 | D14: IPHONE 17 PRO MAX IOS UPDATE: silver | E14: ADEX GADGETS | F14: income | G14: PAID | H14: service | J14: 46147
A15: 46147 | B15: SERVICE PROFIT | C15: 5000 | D15: LOCATION SPOOFING | E15: TIMILEYIN | F15: income | G15: PAID | H15: service | J15: 46147
A16: 46147 | B16: SERVICE PROFIT | C16: 2500 | D16: iPhone 11 Red 64GB IOS UPDATE | E16: SMART | F16: income | G16: PAID | H16: service | J16: 46147
A17: 46148 | B17: SERVICE PROFIT | C17: 75000 | D17: 3 MONTHS ESIM | E17: TUNA MONEY | F17: income | G17: PAID | H17: service | J17: 46148
A18: 46148 | B18: SERVICE PROFIT | C18: 5000 | D18: ICLOUD FIXING | E18: FOLAKEMI | F18: income | G18: PAID | H18: service | J18: 46148
A19: 46148 | B19: SERVICE PROFIT | C19: 3000 | D19: ICLOUD SIGN IN FIX | E19: PRINCE MOSES | F19: income | G19: PAID | H19: service | J19: 46148
A20: 46148 | B20: SERVICE PROFIT | C20: 3000 | D20: iPhone 17 Pro Max Cosmic Orange 256GB IOS UPDATE | E20: TONYTRENDS | F20: income | G20: PAID | H20: service | J20: 46148
A21: 46148 | B21: SERVICE PROFIT | C21: 5000 | D21: iPhone XR Black 64GB LOCATIN SPOOFING | E21: CUSTOMER | F21: income | G21: PAID | H21: service | J21: 46148
A28: 46148 | B28: USA NUMBER | C28: 29000 | D28: FOR TUNA MONEY USE NUMBER 3 MONTHS | E28: admin | F28: expense | H28: expense
H29: 46149 | I29: PHONE PROFIT | J29: 90000 | K29: Item record_id: 7974dce216f545ce9d88bcc7a36d480b, sale: 820000.00, cost: 730000.00 | L29: admin | M29: income | N29: PAID | O29: phone | P29: 730000 | Q29: 46149
H30: 46149 | I30: PHONE SALE EXPENSE | J30: 2300 | K30: IPHONE 16 P + E | L30: KABEX KAYWISE | M30: expense | O30: expense
H31: 46147 | I31: USA ESIM | J31: 29090 | K31: USA 3 MONTHS ESIM FOR TUNA MONEY | L31: admin | M31: expense | O31: expense
H32: 46149 | I32: SERVICE PROFIT | J32: 2500 | K32: iPhone 14 Pro Max Deep Purple 256GB IOS UPDATE | L32: PERFECT | M32: income | N32: PAID | O32: service | Q32: 46149
H33: 46149 | I33: PHONE PROFIT | J33: 645000 | K33: IPHONE 14 PRO P + E | L33: DON | M33: income | N33: PAID | O33: phone | Q33: 46149
H34: 46149 | I34: SERVICE PROFIT | J34: 2500 | K34: IPHONE 14 PRO SPACE BLACK 128GB IOS UPDATE | L34: DON | M34: income | N34: PAID | O34: service | Q34: 46149
H35: 46149 | I35: SERVICE PROFIT | J35: 2500 | K35: IPHONE 17 PRO MAX IOS UPDATE: ORANGE | L35: DON | M35: income | N35: PAID | O35: service | Q35: 46149
H36: 46149 | I36: SERVICE PROFIT | J36: 5000 | K36: ICLOUD OPENING | L36: DON | M36: income | N36: PAID | O36: service | Q36: 46149
H37: 46149 | I37: SERVICE PROFIT | J37: 3000 | K37: IPHONE 17 PRO MAX SILVER IOS UPDATE | L37: DON | M37: income | N37: PAID | O37: service | Q37: 46149
H38: 46149 | I38: SERVICE PROFIT | J38: 2000 | K38: 2K CASH | L38: DON | M38: income | N38: PAID | O38: service | Q38: 46149
H39: 46149 | I39: PHONE PROFIT | J39: 560000 | K39: IPHONE 15 | L39: SALVAGE YARD | M39: income | N39: PAID | O39: phone | Q39: 46149
H40: 46149 | I40: SERVICE PROFIT | J40: 3000 | K40: SIGNAL TRANSFER | L40: IPRO GADGET | M40: income | N40: PAID | O40: service | Q40: 46149
H41: 46149 | I41: SERVICE EXPENSE | J41: 118150 | K41: IPHONE 16 PLUS FACTORY UNLOCKING | L41: PANKYGEE | M41: expense | O41: expense
H42: 46149 | I42: SERVICE PROFIT | J42: 2500 | K42: PINK 16 IOS UPDATE | L42: MOBILE TRENDS | M42: income | N42: PAID | O42: service | Q42: 46149
H43: 46149 | I43: SERVICE PROFIT | J43: 2500 | K43: IPHONE 16 PLUS TEAL 128GB IOS UPDATE | L43: MOBILE TRENDS | M43: income | N43: PAID | O43: service | Q43: 46149
H44: 46149 | I44: SERVICE PROFIT | J44: 5000 | K44: PICTURES BACKUP AND RESTORE | L44: GNF | M44: income | N44: PAID | O44: service | Q44: 46149
H45: 46149 | I45: SERVICE PROFIT | J45: 10000 | K45: ICLOUD RECOVERY | L45: EMMZY | M45: income | N45: PAID | O45: service | Q45: 46149
H46: 46149 | I46: SERVICE PROFIT | J46: 2500 | K46: IPHONE 13 PRO MAX BATTERY CALIBRATION: GRAPHITE | L46: PANKYGEE | M46: income | N46: PAID | O46: service | Q46: 46149
H47: 46149 | I47: SERVICE PROFIT | J47: 145000 | K47: IPHONE 16 PLUS FACTORY UNLOCKING | L47: PANKYGEE | M47: income | N47: PAID | O47: service | Q47: 46149
H48: 46149 | I48: SERVICE PROFIT | J48: 5000 | K48: ICLOUD OPENING: Nigeria | L48: EMMANUEL DAMILARE | M48: income | N48: PAID | O48: service | Q48: 46149
H49: 46150 | I49: esim 3 months | J49: 29090 | L49: admin | M49: expense | O49: expense
H50: 46150 | I50: for 17 pro max unlocking | J50: 118150 | L50: admin | M50: expense | O50: expense
H51: 46150 | I51: TRACE | J51: 111 | K51: TRACE LOOP 1778245008 | L51: admin | M51: expense | O51: expense
H52: 46150 | I52: TRACE | J52: 111 | K52: TRACE LOOP 1778245026 | L52: admin | M52: expense | O52: expense
H53: 46150 | I53: TRACE | J53: 222 | K53: TRACE PATCH 1778245120 | L53: admin | M53: expense | O53: expense
H54: 46150 | I54: TRACE | J54: 222 | K54: TRACE PATCH 1778245139 | L54: admin | M54: expense | O54: expense
H55: 46150 | I55: TRACE | J55: 222 | K55: TRACE PATCH 1778245156 | L55: admin | M55: expense | O55: expense
H56: 46150 | I56: TRACE | J56: 333 | K56: TRACE LIVEFIX 1778245333 | L56: admin | M56: expense | O56: expense
H57: 46150 | I57: TRACE | J57: 333 | K57: TRACE LIVEFIX 1778245333 | L57: admin | M57: expense | O57: expense
H58: 46150 | I58: TRACE | J58: 333 | K58: TRACE LIVEFIX 1778245359 | L58: admin | M58: expense | O58: expense
H59: 46150 | I59: TRACE | J59: 333 | K59: TRACE LIVEFIX 1778245359 | L59: admin | M59: expense | O59: expense
H60: 46150 | I60: TRACE | J60: 333 | K60: TRACE LIVEFIX 1778245385 | L60: admin | M60: expense | O60: expense
H61: 46150 | I61: TRACE | J61: 333 | K61: TRACE LIVEFIX 1778245385 | L61: admin | M61: expense | O61: expense
H62: 46150 | I62: TRACE APPLY | J62: 777 | K62: TRACE APPLY 1778245602 | L62: admin | M62: expense | O62: expense
... H81: 46150 | I81: DELTA NOW | J81: 321 | K81: DELTA NOW 1778246714 | L81: admin | M81: expense | O81: expense
H82: 46239 | I82: SERVICE PROFIT | J82: 40000 | K82: IPHONE 12 PRO UNLOCKING | L82: TOP NATION | M82: income | N82: PAID | O82: service | Q82: 46239
H83: 46239 | I83: SERVICE PROFIT | J83: 40000 | K83: IPHONE 12 PRO UNLOCKING | L83: TOP NATION | M83: income | N83: PAID | O83: service | Q83: 46239
H84: 46239 | I84: SERVICE EXPENSE | J84: 308 | K84: IPHONE 12 PRO UNLOCKING | L84: TOP NATION | M84: expense | O84: expense
H85: 46239 | I85: SERVICE EXPENSE | J85: 308 | K85: IPHONE 12 PRO UNLOCKING | L85: TOP NATION | M85: expense | O85: expense
H86: 46150 | I86: PHONE PROFIT | J86: 40000 | K86: Item record_id: 8fe2d586d14f4a96b55cab34eb095c62, sale: 240000.00, cost: 200000.00 | L86: admin | M86: income | N86: PAID | O86: phone | P86: 200000 | Q86: 46150
H87: 46150 | I87: PHONE PROFIT | J87: 40000 | K87: Item record_id: 8fe2d586d14f4a96b55cab34eb095c62, sale: 240000.00, cost: 200000.00 | L87: admin | M87: income | N87: PAID | O87: phone | P87: 200000 | Q87: 46150
H88: 46150 | I88: SERVICE PROFIT | J88: 5000 | K88: TEST SERVICE [ROW 1049] | L88: TEST CLIENT | M88: income | N88: PAID | O88: service | Q88: 46150
H89: 46150 | I89: SERVICE PROFIT | J89: 5000 | K89: TEST SERVICE [ROW 1049] | L89: TEST CLIENT | M89: income | N89: PAID | O89: service | Q89: 46150
H90: 46239 | I90: SERVICE EXPENSE | J90: 500000 | K90: 500K | L90: DENIS4WARD | M90: expense | O90: expense
H91: 46239 | I91: SERVICE EXPENSE | J91: 500000 | K91: 500K | L91: DENIS4WARD | M91: expense | O91: expense
H92: 46239 | I92: SERVICE PROFIT | J92: 5000 | K92: ICLOUD OPENING: NIGERIA | L92: OLUWATOMI VICTOR AVE | M92: income | N92: PAID | O92: service | Q92: 46239
H93: 46239 | I93: SERVICE PROFIT | J93: 5000 | K93: ICLOUD OPENING: NIGERIA | L93: OLUWATOMI VICTOR AVE | M93: income | N93: PAID | O93: service | Q93: 46239
H94: 46151 | I94: SERVICE PROFIT | J94: 2500 | K94: iPhone 13 Pro Graphite 128GB IOS UPDATE [ROW 1061] | L94: ANNIE | M94: income | N94: PAID | O94: service | Q94: 46151
H95: 46151 | I95: SERVICE PROFIT | J95: 2500 | K95: IPHONE 14 PRO MAX IOS UPDATE: Space Black [ROW 1063] | L95: ANNIE | M95: income | N95: PAID | O95: service | Q95: 46151
H96: 46152 | I96: PHONE PROFIT | J96: 820000 | K96: IPHONE 16 P + E | L96: TEE BEST GADGET | M96: income | N96: PAID | O96: phone | Q96: 46152
H97: 46331 | I97: SERVICE EXPENSE | J97: 600000 | K97: 600K CASH | L97: STARBOX | M97: expense | O97: expense
H98: 46331 | I98: SERVICE PROFIT | J98: 5000 | K98: ICLOUD OPENING: Nigeria | L98: SAINTYUNG | M98: income | N98: PAID | O98: service | Q98: 46331
H99: 46153 | I99: SERVICE PROFIT | J99: 5000 | K99: iPhone 15 Yellow 256GB UPGRADE & WIPING [ROW 1069] | L99: FOLAKEMI | M99: income | N99: PAID | O99: service | Q99: 46153
H100: 46153 | I100: SERVICE PROFIT | J100: 20000 | K100: FILE TRANSFER + MDM BYPASS | L100: MARVY T.M | M100: income | N100: PAID | O100: service | Q100: 46153
H101: 46153 | I101: SERVICE PROFIT | J101: 2500 | K101: IPHONE 13 MIDNIGHT IOS UPDATE | L101: MARVY T.M | M101: income | N101: PAID | O101: service | Q101: 46153
H102: 46153 | I102: SERVICE PROFIT | J102: 2500 | K102: IPHONE 11 WHITE 64GB IOS UPDATE | L102: MARVY T.M | M102: income | N102: PAID | O102: service | Q102: 46153
H103: 46153 | I103: SERVICE PROFIT | J103: 2500 | K103: IPHONE 12 PRO GRAPHITE 128GB IOS UPDATE | L103: MARVY T.M | M103: income | N103: PAID | O103: service | Q103: 46153
H104: 46153 | I104: SERVICE PROFIT | J104: 3000 | K104: ICLOUD OPENING: Nigeria | L104: PROMISE OKON | M104: income | N104: PAID | O104: service | Q104: 46153
H105: 46153 | I105: SERVICE PROFIT | J105: 2500 | K105: IPHONE 14 PRO SILVER 128GB IOS UPDATE | NOTE: SENT DAUNSI | L105: CH4 | M105: income | N105: PAID | O105: service | Q105: 46153
H106: 46153 | I106: SERVICE PROFIT | J106: 2500 | K106: IPHONE 15 BLUE 128GB IOS UPDATE | L106: CH4 | M106: income | N106: PAID | O106: service | Q106: 46153
H107: 46153 | I107: SERVICE PROFIT | J107: 2500 | K107: IPHONE XR BLUE 64GB IOS UODATE | L107: CH4 | M107: income | N107: PAID | O107: service | Q107: 46153
H108: 46153 | I108: PHONE PROFIT | J108: 1680000 | K108: SEALED IPHONE 17 PRO P + E | L108: CH4 | M108: income | N108: PAID | O108: phone | Q108: 46153
H109: 46153 | I109: SERVICE PROFIT | J109: 3000 | K109: IPHONE 17 PRO DEEPBLUE 256GB IOS UPDATE | L109: CH4 | M109: income | N109: PAID | O109: service | Q109: 46153
... H113: 46153 | I113: SERVICE PROFIT | J113: 5000 | K113: CUSTOMER WITHDREW 5K TO POS (FOR APPLE ID) | L113: DENIS4WARD | M113: income | N113: PAID | O113: service | Q113: 46153

Sheet BACKUP_BILLING_SERVICES
A1: sync_key | B1: record_id | C1: source_hash | D1: sheet_row_num | E1: imei | F1: customer_name | G1: payment_status | H1: payment_date | I1: paid_date | J1: expense_amount | K1: expense_description | L1: calculated_profit | M1: payload_json | N1: created_at | O1: updated_at
A2: 9dcfec929c764ae7a52bfd4caf78d6c5 | B2: 9dcfec929c764ae7a52bfd4caf78d6c5 | C2: 182bd7f4e09edca5570efa1ba87659792e0fcc62d66bae646bb204971c4c6ed8 | D2: 2 | F2: DEMEX | G2: PAID | I2: 2026-02-17T00:00:00+01:00 | J2: 0 | L2: 2500 | M2: {"in":1,"DATE":"2/17/2026","IMEI":"","NAME":"DEMEX","TIME":1,"PRICE":"\u20a62,500.00","STATUS":"paid","PAID DATE":"","RECORD_ID":"9dcfec929c764ae7a52bfd4caf78d6c5","Amount paid":"\u20a62,500.00","DESCRIPTION":"IPHONE 16 BLACK UPDATE","PHONE NUMBER":2347067462101,"DEAL LOCATION":"","INTERNAL NOTE":"","EXPENSE AMOUNT":"","CALCULATED PROFIT":"","EXPENSE DESCRIPTION":"","IMEI FOR SWAPPED DEAL":""} | N2: 2026-05-11T22:24:59.205205+01:00 | O2: 2026-05-11T22:24:59.205205+01:00
A3: e1e76866b2b44537a367a48baed4cbb7 | B3: e1e76866b2b44537a367a48baed4cbb7 | C3: 372f3ec78b24323147b4f700dffe4e8aa3c1d6aeef50adb5615f6d5cf63b3e6a | D3: 3 | F3: DAH UNIQUE | G3: PAID | I3: 2026-02-17T00:00:00+01:00 | J3: 0 | L3: 2500 | M3: {"in":2,"DATE":"2/17/2026","IMEI":"","NAME":"DAH UNIQUE","TIME":2,"PRICE":"\u20a62,500.00","STATUS":"PAID","PAID DATE":"","RECORD_ID":"e1e76866b2b44537a367a48baed4cbb7","Amount paid":"\u20a62,500.00","DESCRIPTION":"GOLD IPHONE 14 PRO","PHONE NUMBER":2349070536253,"DEAL LOCATION":"","INTERNAL NOTE":"","EXPENSE AMOUNT":"","CALCULATED PROFIT":"","EXPENSE DESCRIPTION":"","IMEI FOR SWAPPED DEAL":""} | N3: 2026-05-11T22:00:09.855781+01:00 | O3: 2026-05-11T22:00:09.855781+01:00
A4: 252820e05f6641b4aec1103a18424f72 | B4: 252820e05f6641b4aec1103a18424f72 | C4: 312f2e7e6a48d84f1357c43e5364158446c10ef131b927ada6e57a707cc4207e | D4: 4 | F4: HUNTER LIFE | G4: PAID | I4: 2026-02-17T00:00:00+01:00 | J4: 0 | L4: 185000 | M4: {"in":3,"DATE":"2/17/2026","IMEI":"","NAME":"HUNTER LIFE","TIME":3,"PRICE":"\u20a6185,000.00","STATUS":"PAID","PAID DATE":"","RECORD_ID":"252820e05f6641b4aec1103a18424f72","Amount paid":"\u20a6185,000.00","DESCRIPTION":"SWAPPED IPHONE 13 TO 11 PRO SILVER","PHONE NUMBER":"","DEAL LOCATION":"","INTERNAL NOTE":"","EXPENSE AMOUNT":"","CALCULATED PROFIT":"","EXPENSE DESCRIPTION":"","IMEI FOR SWAPPED DEAL":""} | N4: 2026-05-11T22:00:09.855781+01:00 | O4: 2026-05-11T22:00:09.855781+01:00
A5: 13b8f92dda7b4ff7825daa1e2676f734 | B5: 13b8f92dda7b4ff7825daa1e2676f734 | C5: b342de0a85ca7015b921d37136e8df4efbe26d5ac38b88660361376b52d05439 | D5: 5 | F5: RICKY | G5: PAID | I5: 2026-02-17T00:00:00+01:00 | J5: 0 | L5: 280000 | M5: {"in":4,"DATE":"2/17/2026","IMEI":"","NAME":"RICKY","TIME":4,"PRICE":"\u20a6280,000.00","STATUS":"PAID","PAID DATE":"","RECORD_ID":"13b8f92dda7b4ff7825daa1e2676f734","Amount paid":"\u20a6280,000.00","DESCRIPTION":"IPHONE 16 PRO GOLD 100% SWAPPED WITH IPHONE 15 PRO 512GB","PHONE NUMBER":"","DEAL LOCATION":"","INTERNAL NOTE":"","EXPENSE AMOUNT":"","CALCULATED PROFIT":"","EXPENSE DESCRIPTION":"","IMEI FOR SWAPPED DEAL":""} | N5: 2026-05-11T22:00:09.855781+01:00 | O5: 2026-05-11T22:00:09.855781+01:00
A6: c2a8339184ce430f975db6123c51a7fb | B6: c2a8339184ce430f975db6123c51a7fb | C6: 04433d211be85f3310bc12392fe78ad9267c483d15f928cfeedd6495fe0c0099 | D6: 6 | F6: OSES | G6: PAID | I6: 2026-02-17T00:00:00+01:00 | J6: 0 | L6: 2500 | M6: {"in":5,"DATE":"2/17/2026","IMEI":"","NAME":"OSES","TIME":5,"PRICE":"\u20a62,500.00","STATUS":"PAID","PAID DATE":"","RECORD_ID":"c2a8339184ce430f975db6123c51a7fb","Amount paid":"\u20a62,500.00","DESCRIPTION":"IPHONE 14 PLUS UPDATE MIDNIGHT COLOR","PHONE NUMBER":"","DEAL LOCATION":"","INTERNAL NOTE":"","EXPENSE AMOUNT":"","CALCULATED PROFIT":"","EXPENSE DESCRIPTION":"","IMEI FOR SWAPPED DEAL":""} | N6: 2026-05-11T22:00:09.855781+01:00 | O6: 2026-05-11T22:00:09.855781+01:00
A7: 3debc2aabaa842ce9d440b9b84980f2d | B7: 3debc2aabaa842ce9d440b9b84980f2d | C7: 1cf3d8e50fa7d4466cfac22718dad2a957bc970ef8057e8e7bd5c07b6f68c88e | D7: 7 | F7: KEMI FROM SEUN | G7: PAID | I7: 2026-02-17T00:00:00+01:00 | J7: 0 | L7: 1500000 | M7: {"in":6,"DATE":"2/17/2026","IMEI":"","NAME":"KEMI FROM SEUN","TIME":6,"PRICE":"\u20a61,500,000.00","STATUS":"PAID","PAID DATE":"","RECORD_ID":"3debc2aabaa842ce9d440b9b84980f2d","Amount paid":"\u20a61,500,000.00","DESCRIPTION":"IPHONE 15 PRO MAX 512GB TO IPHONE ","PHONE NUMBER":"","DEAL LOCATION":"","INTERNAL NOTE":"","EXPENSE AMOUNT":"","CALCULATED PROFIT":"","EXPENSE DESCRIPTION":"","IMEI FOR SWAPPED DEAL":""} | N7: 2026-05-11T22:00:09.855781+01:00 | O7: 2026-05-11T22:00:09.855781+01:00
A8: ad63bb932f7e47abb64bae4d1546a4d8 | B8: ad63bb932f7e47abb64bae4d1546a4d8 | C8: a72c6adfd6571cb40c0e58670dcaca91f1237ed0dce6b37b07fa2bced7ab1d89 | D8: 8 | F8: IBIRONKE FAVOUR | G8: PAID | I8: 2026-02-17T00:00:00+01:00 | J8: 0 | L8: 10000 | M8: {"in":7,"DATE":"2/17/2026","IMEI":"","NAME":"IBIRONKE FAVOUR","TIME":7,"PRICE":"\u20a610,000.00","STATUS":"PAID","PAID DATE":"","RECORD_ID":"ad63bb932f7e47abb64bae4d1546a4d8","Amount paid":"\u20a610,000.00","DESCRIPTION":"APPLE ID CREATE & SIGN IN","PHONE NUMBER":"","DEAL LOCATION":"","INTERNAL NOTE":"","EXPENSE AMOUNT":"","CALCULATED PROFIT":"","EXPENSE DESCRIPTION":"","IMEI FOR SWAPPED DEAL":""} | N8: 2026-05-11T22:00:09.855781+01:00 | O8: 2026-05-11T22:00:09.855781+01:00
A9: ff964ae5a2f2444187915c0d21934773 | B9: ff964ae5a2f2444187915c0d21934773 | C9: fa6f408304c6f398b59360e9e27e83e1473c89e0742d62036655e231c564f9bf | D9: 9 | F9: CLINTON GADGET | G9: PAID | I9: 2026-02-17T00:00:00+01:00 | J9: 0 | L9: 800000 | M9: {"in":8,"DATE":"2/17/2026","IMEI":"","NAME":"CLINTON GADGET","TIME":8,"PRICE":"\u20a6800,000.00","STATUS":"PAID","PAID DATE":"","RECORD_ID":"ff964ae5a2f2444187915c0d21934773","Amount paid":"\u20a6800,000.00","DESCRIPTION":"IPHONE 16 256GB 354178509660284","PHONE NUMBER":"","DEAL LOCATION":"","INTERNAL NOTE":"","EXPENSE AMOUNT":"","CALCULATED PROFIT":"","EXPENSE DESCRIPTION":"","IMEI FOR SWAPPED DEAL":""} | N9: 2026-05-11T22:00:09.855781+01:00 | O9: 2026-05-11T22:00:09.855781+01:00
A10: fb2d541894b74a0a9fcffa10378d8580 | B10: fb2d541894b74a0a9fcffa10378d8580 | C10: 752ed674e7c3e5b952090af84d410bfe0c4b4399c82e0b2f2372f6fc655ed8d4 | D10: 10 | F10: NURUDEEN | G10: PAID | I10: 2026-02-17T00:00:00+01:00 | J10: 0 | L10: 25000 | M10: {"in":9,"DATE":"2/17/2026","IMEI":"","NAME":"NURUDEEN","TIME":9,"PRICE":"\u20a625,000.00","STATUS":"PAID","PAID DATE":"","RECORD_ID":"fb2d541894b74a0a9fcffa10378d8580","Amount paid":"\u20a625,000.00","DESCRIPTION":"CHIP FOR IPHONE 12 PRO PACIFIC BLUE","PHONE NUMBER":9122727950,"DEAL LOCATION":"","INTERNAL NOTE":"","EXPENSE AMOUNT":"","CALCULATED PROFIT":"","EXPENSE DESCRIPTION":"","IMEI FOR SWAPPED DEAL":""} | N10: 2026-05-11T22:00:09.855781+01:00 | O10: 2026-05-11T22:00:09.855781+01:00
A11: 38425b848c1e4f8195ec6df4938be5ca | B11: 38425b848c1e4f8195ec6df4938be5ca | C11: abc1305ba32ad02576483dce4e9c28a4a3b2c1b92f2cace07e66d83d0f3b96f9 | D11: 11 | F11: WIZZY | G11: PAID | I11: 2026-02-17T00:00:00+01:00 | J11: 0 | L11: 2500 | M11: {"in":10,"DATE":"2/17/2026","IMEI":"","NAME":"WIZZY","TIME":10,"PRICE":"\u20a62,500.00","STATUS":"PAID","PAID DATE":"","RECORD_ID":"38425b848c1e4f8195ec6df4938be5ca","Amount paid":"\u20a62,500.00","DESCRIPTION":"NATURAL TITANIUM IPHONE 15 PRO MAX IOS UPDATE","PHONE NUMBER":2348108686713,"DEAL LOCATION":"","INTERNAL NOTE":"","EXPENSE AMOUNT":"","CALCULATED PROFIT":"","EXPENSE DESCRIPTION":"","IMEI FOR SWAPPED DEAL":""} | N11: 2026-05-11T22:00:09.855781+01:00 | O11: 2026-05-11T22:00:09.855781+01:00
A12: 7f9250f3a89542a69db22bdb2807f36b | B12: 7f9250f3a89542a69db22bdb2807f36b | C12: cc53046a2b49f5d4ad8aa9e79267f3851b15ee26ac8a813f9a3a35657598cd51 | D12: 12 | F12: ZEE TECH | G12: PAID | I12: 2026-02-15T00:00:00+01:00 | J12: 0 | L12: 2500 | M12: {"in":11,"DATE":"2/15/2026","IMEI":"","NAME":"ZEE TECH","TIME":11,"PRICE":"\u20a62,500.00","STATUS":"PAID","PAID DATE":"","RECORD_ID":"7f9250f3a89542a69db22bdb2807f36b","Amount paid":"\u20a62,500.00","DESCRIPTION":"IPHONE 13 IOS UPDATE ","PHONE NUMBER":2349033724061,"DEAL LOCATION":"","INTERNAL NOTE":"","EXPENSE AMOUNT":"","CALCULATED PROFIT":"","EXPENSE DESCRIPTION":"","IMEI FOR SWAPPED DEAL":""} | N12: 2026-05-11T22:00:09.855781+01:00 | O12: 2026-05-11T22:00:09.855781+01:00
A13: c8dc8dfa28c343c484a7f2ba7fbf5b3f | B13: c8dc8dfa28c343c484a7f2ba7fbf5b3f | C13: 0f2f93f4f889a4fde8c557267248a9bea0311aff0d24971f6bf1788d8543f881 | D13: 13 | F13: ZEE TECH | G13: PAID | I13: 2026-02-16T00:00:00+01:00 | J13: 0 | L13: 2500 | M13: {"in":12,"DATE":"2/16/2026","IMEI":"","NAME":"ZEE TECH","TIME":12,"PRICE":"\u20a62,500.00","STATUS":"PAID","PAID DATE":"","RECORD_ID":"c8dc8dfa28c343c484a7f2ba7fbf5b3f","Amount paid":"\u20a62,500.00","DESCRIPTION":"IPHONE 13 PRO MAX IOS UPDATE","PHONE NUMBER":2349033724061,"DEAL LOCATION":"","INTERNAL NOTE":"","EXPENSE AMOUNT":"","CALCULATED PROFIT":"","EXPENSE DESCRIPTION":"","IMEI FOR SWAPPED DEAL":""} | N13: 2026-05-11T22:00:09.855781+01:00 | O13: 2026-05-11T22:00:09.855781+01:00
... A24: 4590d23eb8fa43579501fbc6bd071bd1 | B24: 4590d23eb8fa43579501fbc6bd071bd1 | C24: 7406a1cd32b6bd330690fccbe8eb52b7e7dcdbc585eabec1cff4b8f9210026b3 | D24: 24 | F24: VERTEX | G24: PAID | I24: 2026-02-07T00:00:00+01:00 | J24: 0 | L24: 2500 | M24: {"in":23,"DATE":"2/7/2026","IMEI":"","NAME":"VERTEX","TIME":7,"PRICE":"\u20a62,500.00","STATUS":"PAID","PAID DATE":"","RECORD_ID":"4590d23eb8fa43579501fbc6bd071bd1","Amount paid":"","DESCRIPTION":"PINK IPHONE 15 PLUS UPDATE","PHONE NUMBER":2348103663581,"DEAL LOCATION":"","INTERNAL NOTE":"","EXPENSE AMOUNT":"","CALCULATED PROFIT":"","EXPENSE DESCRIPTION":"","IMEI FOR SWAPPED DEAL":""} | N24: 2026-05-11T22:00:09.855781+01:00 | O24: 2026-05-11T22:00:09.855781+01:00
A25: 9bbbf52992df41bca266eeb13d53ad91 | B25: 9bbbf52992df41bca266eeb13d53ad91 | C25: 5b6345f98ee7ddc5975f7556450e58fa26488177d5bf12fb500cace71f7c0771 | D25: 25 | F25: MIKKY | G25: RETURNED | J25: 0 | L25: 0 | M25: {"in":24,"DATE":"2/7/2026","IMEI":"","NAME":"MIKKY","TIME":8,"PRICE":"\u20a620,000.00","STATUS":"RETURNED","PAID DATE":"","RECORD_ID":"9bbbf52992df41bca266eeb13d53ad91","Amount paid":"","DESCRIPTION":"IPHONE 13 PRO MAX CHIP","PHONE NUMBER":"","DEAL LOCATION":"","INTERNAL NOTE":"","EXPENSE AMOUNT":"","CALCULATED PROFIT":"","EXPENSE DESCRIPTION":"","IMEI FOR SWAPPED DEAL":""} | N25: 2026-05-11T22:00:09.855781+01:00 | O25: 2026-05-11T22:00:09.855781+01:00
A26: f902b4c8ea8c49a2bdb4466ed2b99884 | B26: f902b4c8ea8c49a2bdb4466ed2b99884 | C26: b44bb2a34ad93d59d783d069cbb33ac5913e4e6d2c23c5ab3467462aa4146e05 | D26: 26 | F26: PRINZE GADGET | G26: PAID | I26: 2026-02-07T00:00:00+01:00 | J26: 0 | L26: 2500 | M26: {"in":25,"DATE":"2/7/2026","IMEI":"","NAME":"PRINZE GADGET","TIME":9,"PRICE":"\u20a62,500.00","STATUS":"PAID","PAID DATE":"","RECORD_ID":"f902b4c8ea8c49a2bdb4466ed2b99884","Amount paid":"","DESCRIPTION":"IPHONE 13 UPDATE","PHONE NUMBER":"","DEAL LOCATION":"","INTERNAL NOTE":"","EXPENSE AMOUNT":"","CALCULATED PROFIT":"","EXPENSE DESCRIPTION":"","IMEI FOR SWAPPED DEAL":""} | N26: 2026-05-11T22:00:09.855781+01:00 | O26: 2026-05-11T22:00:09.855781+01:00
A27: c6f548765acd4277a3081301ea7558e0 | B27: c6f548765acd4277a3081301ea7558e0 | C27: aa2d1a016de77c6be26beb0db821c23e89ea727afecb9edb748679048b20bd7f | D27: 27 | F27: DENIS4WARD | G27: PAID | I27: 2026-02-05T00:00:00+01:00 | J27: 0 | L27: 225000 | M27: {"in":26,"DATE":"2/5/2026","IMEI":"","NAME":"DENIS4WARD","TIME":10,"PRICE":"\u20a6225,000.00","STATUS":"PAID","PAID DATE":"","RECORD_ID":"c6f548765acd4277a3081301ea7558e0","Amount paid":"","DESCRIPTION":"PS4 SLIM AND ONE GAMEPAD","PHONE NUMBER":2348038551439,"DEAL LOCATION":"","INTERNAL NOTE":"","EXPENSE AMOUNT":"","CALCULATED PROFIT":"","EXPENSE DESCRIPTION":"","IMEI FOR SWAPPED DEAL":""} | N27: 2026-05-11T22:00:09.855781+01:00 | O27: 2026-05-11T22:00:09.855781+01:00
A28: 1a175228683e4c7f83fa4ff7d78edd6c | B28: 1a175228683e4c7f83fa4ff7d78edd6c | C28: 740495f672b7b4c2891484bb2dc5878d1a23c225e75c0475fda8e0cea4ea8514 | D28: 28 | F28: MIDE GADGET | G28: PAID | I28: 2026-02-04T00:00:00+01:00 | J28: 0 | L28: 2500 | M28: {"in":27,"DATE":"2/4/2026","IMEI":"","NAME":"MIDE GADGET","TIME":11,"PRICE":"\u20a62,500.00","STATUS":"PAID","PAID DATE":"","RECORD_ID":"1a175228683e4c7f83fa4ff7d78edd6c","Amount paid":"","DESCRIPTION":"BLUE IPHONE 16 UPDATE","PHONE NUMBER":"","DEAL LOCATION":"","INTERNAL NOTE":"","EXPENSE AMOUNT":"","CALCULATED PROFIT":"","EXPENSE DESCRIPTION":"","IMEI FOR SWAPPED DEAL":""} | N28: 2026-05-11T22:00:09.855781+01:00 | O28: 2026-05-11T22:00:09.855781+01:00
A29: cfb45f1f05604357b7eca2af401cc1b6 | B29: cfb45f1f05604357b7eca2af401cc1b6 | C29: 2a50123134633308eebf7031c4989b9feda4911c49226f101627a6108a8f921e | D29: 29 | F29: ZADDY ROLLAND | G29: PENDING | J29: 0 | L29: 0 | M29: {"in":28,"DATE":"2/3/2026","IMEI":"","NAME":"ZADDY ROLLAND","TIME":12,"PRICE":"\u20a6450,000.00","STATUS":"PENDING","PAID DATE":"","RECORD_ID":"cfb45f1f05604357b7eca2af401cc1b6","Amount paid":"","DESCRIPTION":"TEAL 16 P+E BALANCE","PHONE NUMBER":2348050554029,"DEAL LOCATION":"","INTERNAL NOTE":"","EXPENSE AMOUNT":"","CALCULATED PROFIT":"","EXPENSE DESCRIPTION":"","IMEI FOR SWAPPED DEAL":""} | N29: 2026-05-11T22:00:09.855781+01:00 | O29: 2026-05-11T22:00:09.855781+01:00
A30: 08f797e6e883406aafbd18de33d0fe07 | B30: 08f797e6e883406aafbd18de33d0fe07 | C30: 5b580a6a615ab9873d8276cd7c915dada1eee55df93b2927f2758553d0952aeb | D30: 30 | F30: ZADDY ROLLAND | G30: UNPAID | J30: 0 | L30: 0 | M30: {"in":29,"DATE":"2/3/2026","IMEI":"","NAME":"ZADDY ROLLAND","TIME":13,"PRICE":"\u20a62,500.00","STATUS":"UNPAID","PAID DATE":"","RECORD_ID":"08f797e6e883406aafbd18de33d0fe07","Amount paid":"","DESCRIPTION":"TEAL 16 P+E UPDATE","PHONE NUMBER":2348050554029,"DEAL LOCATION":"","INTERNAL NOTE":"","EXPENSE AMOUNT":"","CALCULATED PROFIT":"","EXPENSE DESCRIPTION":"","IMEI FOR SWAPPED DEAL":""} | N30: 2026-05-11T22:00:09.855781+01:00 | O30: 2026-05-11T22:00:09.855781+01:00
A31: 19d21d47029d41d0af0fc380928ba2cb | B31: 19d21d47029d41d0af0fc380928ba2cb | C31: 49a74b47836baff80a3ab73ab966b0431f06e0f0d0285985a895073c58730bf7 | D31: 31 | F31: JAMEX | G31: PENDING | J31: 0 | L31: 0 | M31: {"in":30,"DATE":"2/18/2026","IMEI":"","NAME":"JAMEX","TIME":14,"PRICE":"\u20a6395,000.00","STATUS":"PENDING","PAID DATE":"","RECORD_ID":"19d21d47029d41d0af0fc380928ba2cb","Amount paid":"","DESCRIPTION":"OUTSTANDING BALANCE","PHONE NUMBER":2347033260364,"DEAL LOCATION":"","INTERNAL NOTE":"","EXPENSE AMOUNT":"","CALCULATED PROFIT":"","EXPENSE DESCRIPTION":"","IMEI FOR SWAPPED DEAL":""} | N31: 2026-05-11T22:00:09.855781+01:00 | O31: 2026-05-11T22:00:09.855781+01:00
A32: ee70de5352b248dda16ed018caac6dab | B32: ee70de5352b248dda16ed018caac6dab | C32: ecefa2e26506ec3543ff677bbadafac492e6e1c1d27bd2d7f1f30b4c499b311b | D32: 32 | F32: AYANFE | G32: PAID | I32: 2026-01-28T00:00:00+01:00 | J32: 0 | L32: 10000 | M32: {"in":31,"DATE":"1/28/2026","IMEI":"","NAME":"AYANFE","TIME":15,"PRICE":"\u20a610,000.00","STATUS":"PAID","PAID DATE":"","RECORD_ID":"ee70de5352b248dda16ed018caac6dab","Amount paid":"","DESCRIPTION":"APPLE ID RECOVERY","PHONE NUMBER":2348138108648,"DEAL LOCATION":"","INTERNAL NOTE":"","EXPENSE AMOUNT":"","CALCULATED PROFIT":"","EXPENSE DESCRIPTION":"","IMEI FOR SWAPPED DEAL":""} | N32: 2026-05-11T22:00:09.855781+01:00 | O32: 2026-05-11T22:00:09.855781+01:00
A33: 1e7c1962321a484b82cda53c4bbc338e | B33: 1e7c1962321a484b82cda53c4bbc338e | C33: 616bd1ccc1d6fd6c67dda5cdca62cd727478c4901be9bf360d93028d1a0cd732 | D33: 33 | F33: DENIS4WARD | G33: PAID | I33: 2026-01-27T00:00:00+01:00 | J33: 0 | L33: 5000 | M33: {"in":32,"DATE":"1/27/2026","IMEI":"","NAME":"DENIS4WARD","TIME":16,"PRICE":"\u20a65,000.00","STATUS":"PAID","PAID DATE":"","RECORD_ID":"1e7c1962321a484b82cda53c4bbc338e","Amount paid":"","DESCRIPTION":"ILESHA DRIVER","PHONE NUMBER":2348038551439,"DEAL LOCATION":"","INTERNAL NOTE":"","EXPENSE AMOUNT":"","CALCULATED PROFIT":"","EXPENSE DESCRIPTION":"","IMEI FOR SWAPPED DEAL":""} | N33: 2026-05-11T22:00:09.855781+01:00 | O33: 2026-05-11T22:00:09.855781+01:00
A34: 523b7a62015f4f16aaa6fdcfe135e889 | B34: 523b7a62015f4f16aaa6fdcfe135e889 | C34: eb97ad278df237441a3c5555308dbe623d8176cc6ee1491f5f33a84170fa3b39 | D34: 34 | E34: 356295374969208 | F34: PRINZE GADGETS | G34: PAID | I34: 2026-01-27T00:00:00+01:00 | J34: 0 | L34: 280000 | M34: {"in":"","DATE":"1/27/2026","IMEI":356295374969208,"NAME":"PRINZE GADGETS","TIME":17,"PRICE":"\u20a6280,000.00","STATUS":"PAID","PAID DATE":"","RECORD_ID":"523b7a62015f4f16aaa6fdcfe135e889","Amount paid":"","DESCRIPTION":"MIDNIGET LOCKED 14 PLUS. 81%","PHONE NUMBER":2348073229131,"DEAL LOCATION":"","INTERNAL NOTE":"","EXPENSE AMOUNT":"","CALCULATED PROFIT":"","EXPENSE DESCRIPTION":"","IMEI FOR SWAPPED DEAL":""} | N34: 2026-05-11T22:00:09.855781+01:00 | O34: 2026-05-11T22:00:09.855781+01:00
A35: 69bdbb71ddb34659b3c51ffc3f27914b | B35: 69bdbb71ddb34659b3c51ffc3f27914b | C35: f6a2b0a479da4c76351c87230b72fd1b3862b5d7ae3ad20f855d2c437af8b5a6 | D35: 35 | F35: DENIS4WARD | G35: PAID | I35: 2026-01-27T00:00:00+01:00 | J35: 0 | L35: 16250 | M35: {"in":33,"DATE":"1/27/2026","IMEI":"","NAME":"DENIS4WARD","TIME":18,"PRICE":"\u20a616,250.00","STATUS":"PAID","PAID DATE":"","RECORD_ID":"69bdbb71ddb34659b3c51ffc3f27914b","Amount paid":"","DESCRIPTION":"GAS FILL","PHONE NUMBER":2348038551439,"DEAL LOCATION":"","INTERNAL NOTE":"","EXPENSE AMOUNT":"","CALCULATED PROFIT":"","EXPENSE DESCRIPTION":"","IMEI FOR SWAPPED DEAL":""} | N35: 2026-05-11T22:00:09.855781+01:00 | O35: 2026-05-11T22:00:09.855781+01:00
A36: 259c651fb2fc45bea1649447a37d344c | B36: 259c651fb2fc45bea1649447a37d344c | C36: 334c799d74c2440de1ec4bb963fc655a4aa3d5224833622a72a25ab03f186612 | D36: 36 | E36: .. | F36: .. | J36: 0 | L36: 0 | M36: {"in":34,"DATE":"..","IMEI":"..","NAME":"..","TIME":"..","PRICE":"..","STATUS":"","PAID DATE":"","RECORD_ID":"259c651fb2fc45bea1649447a37d344c","Amount paid":"","DESCRIPTION":"..","PHONE NUMBER":"","DEAL LOCATION":"","INTERNAL NOTE":"","EXPENSE AMOUNT":"","CALCULATED PROFIT":"","EXPENSE DESCRIPTION":"","IMEI FOR SWAPPED DEAL":""} | N36: 2026-05-11T22:00:09.855781+01:00 | O36: 2026-05-11T22:00:09.855781+01:00
A37: 3a3ee298459f443e97ad50509eb0e3dd | B37: 3a3ee298459f443e97ad50509eb0e3dd | C37: 6e96988d2e8f6e42c38bb194995f9da7ebebe4a4b0eb706d605d7beaac7a767b | D37: 37 | F37: NURUDEEN | G37: PAID | I37: 2026-02-18T00:00:00+01:00 | J37: 0 | L37: 2500 | M37: {"in":35,"DATE":"2/18/2026","IMEI":"","NAME":"NURUDEEN","TIME":1,"PRICE":"\u20a62,500.00","STATUS":"PAID","PAID DATE":"","RECORD_ID":"3a3ee298459f443e97ad50509eb0e3dd","Amount paid":"","DESCRIPTION":"NATURAL TITANIUM 15 PRO UPDATE","PHONE NUMBER":9122727950,"DEAL LOCATION":"","INTERNAL NOTE":"","EXPENSE AMOUNT":"","CALCULATED PROFIT":"","EXPENSE DESCRIPTION":"","IMEI FOR SWAPPED DEAL":""} | N37: 2026-05-11T22:00:09.855781+01:00 | O37: 2026-05-11T22:00:09.855781+01:00
A38: 860f6063e1f64ed69181fea34c1331b6 | B38: 860f6063e1f64ed69181fea34c1331b6 | C38: bc4b08c1ef7d6185d7c8aaaf1b46ac32f88fe32a2e8b0ee6e29458329da13aef | D38: 38 | F38: DAMBOX | G38: PAID | I38: 2026-02-18T00:00:00+01:00 | J38: 0 | L38: 2500 | M38: {"in":36,"DATE":"2/18/2026","IMEI":"","NAME":"DAMBOX","TIME":2,"PRICE":"\u20a62,500.00","STATUS":"PAID","PAID DATE":"","RECORD_ID":"860f6063e1f64ed69181fea34c1331b6","Amount paid":"","DESCRIPTION":"ORANGE IPHONE 17 PRO IOS UPDATE","PHONE NUMBER":9040943517,"DEAL LOCATION":"","INTERNAL NOTE":"","EXPENSE AMOUNT":"","CALCULATED PROFIT":"","EXPENSE DESCRIPTION":"","IMEI FOR SWAPPED DEAL":""} | N38: 2026-05-11T22:00:09.855781+01:00 | O38: 2026-05-11T22:00:09.855781+01:00
A39: b263752956ea49d493083d288125523d | B39: b263752956ea49d493083d288125523d | C39: b0b5106a9951fc9542fff4536d761f739c44551d5ff25b3eb1f1f70556ba31de | D39: 39 | F39: KAYWISE | G39: PAID | I39: 2026-02-18T00:00:00+01:00 | J39: 0 | L39: 2000 | M39: {"in":37,"DATE":"2/18/2026","IMEI":"","NAME":"KAYWISE","TIME":3,"PRICE":"\u20a62,000.00","STATUS":"PAID","PAID DATE":"","RECORD_ID":"b263752956ea49d493083d288125523d","Amount paid":"\u20a62,000.00","DESCRIPTION":"ULTRAMARINE IPHONE 16 PLUS UPDATE","PHONE NUMBER":2349032614464,"DEAL LOCATION":"","INTERNAL NOTE":"","EXPENSE AMOUNT":"","CALCULATED PROFIT":"","EXPENSE DESCRIPTION":"","IMEI FOR SWAPPED DEAL":""} | N39: 2026-05-11T22:00:09.855781+01:00 | O39: 2026-05-11T22:00:09.855781+01:00
A40: 1cbe6952e28545e786673dbdbb797adf | B40: 1cbe6952e28545e786673dbdbb797adf | C40: aac2441f94784d902fac74d40ecd85f515a23623a7d3d872d65e137f0f5e4acb | D40: 40 | F40: PANKEY | G40: PAID | I40: 2026-02-18T00:00:00+01:00 | J40: 0 | L40: 2500 | M40: {"in":38,"DATE":"2/18/2026","IMEI":"","NAME":"PANKEY","TIME":4,"PRICE":"\u20a62,500.00","STATUS":"PAID","PAID DATE":"","RECORD_ID":"1cbe6952e28545e786673dbdbb797adf","Amount paid":"","DESCRIPTION":"WHITE IPHONE 15 FIX BATTERY FLASH","PHONE NUMBER":"","DEAL LOCATION":"","INTERNAL NOTE":"","EXPENSE AMOUNT":"","CALCULATED PROFIT":"","EXPENSE DESCRIPTION":"","IMEI FOR SWAPPED DEAL":""} | N40: 2026-05-11T22:00:09.855781+01:00 | O40: 2026-05-11T22:00:09.855781+01:00
A41: bf9eb880a87d40c59d132b0de1fa1c21 | B41: bf9eb880a87d40c59d132b0de1fa1c21 | C41: 9fc8fe6c46c7f3e3e44fcb16779f5e20e18f0e3e3b46d9c99fabd6d046a63c57 | D41: 41 | F41: THANKGOD | G41: PAID | I41: 2026-02-18T00:00:00+01:00 | J41: 0 | L41: 380000 | M41: {"in":39,"DATE":"2/18/2026","IMEI":"","NAME":"THANKGOD","TIME":5,"PRICE":"\u20a6380,000.00","STATUS":"PAID","PAID DATE":"","RECORD_ID":"bf9eb880a87d40c59d132b0de1fa1c21","Amount paid":"","DESCRIPTION":"IPHONE 16 ROUGH BODY SWAPPED WITH IPHONE 15 PTO MAX LOCKED NATURAL TITANIUM","PHONE NUMBER":"","DEAL LOCATION":"","INTERNAL NOTE":"","EXPENSE AMOUNT":"","CALCULATED PROFIT":"","EXPENSE DESCRIPTION":"","IMEI FOR SWAPPED DEAL":""} | N41: 2026-05-11T22:00:09.855781+01:00 | O41: 2026-05-11T22:00:09.855781+01:00
A42: 1fb7ef6836d24151a7f090a42d18e786 | B42: 1fb7ef6836d24151a7f090a42d18e786 | C42: e4858f20b221f4b149a42a29917c1cbf62c73ee7b0d60e6f5ef278b4a4797bda | D42: 42 | F42: JAYJOSH | G42: PAID | I42: 2026-02-18T00:00:00+01:00 | J42: 0 | L42: 10000 | M42: {"in":40,"DATE":"2/18/2026","IMEI":"","NAME":"JAYJOSH","TIME":6,"PRICE":"\u20a610,000.00","STATUS":"PAID","PAID DATE":"","RECORD_ID":"1fb7ef6836d24151a7f090a42d18e786","Amount paid":"","DESCRIPTION":"CHIP FIX IPHONE 13","PHONE NUMBER":"","DEAL LOCATION":"","INTERNAL NOTE":"","EXPENSE AMOUNT":"","CALCULATED PROFIT":"","EXPENSE DESCRIPTION":"","IMEI FOR SWAPPED DEAL":""} | N42: 2026-05-11T22:00:09.855781+01:00 | O42: 2026-05-11T22:00:09.855781+01:00
A43: 303affb6d32d4981b8b8fedc73b99291 | B43: 303affb6d32d4981b8b8fedc73b99291 | C43: 0e9bf5289070a1804b3d3f304e0c0deb319aae94530b4c03fbf7912adbb3c30d | D43: 43 | F43: BIGGIE - MELTRONICS | G43: PAID | I43: 2026-02-18T00:00:00+01:00 | J43: 0 | L43: 290000 | M43: {"in":41,"DATE":"2/18/2026","IMEI":"","NAME":"BIGGIE - MELTRONICS","TIME":7,"PRICE":"\u20a6290,000.00","STATUS":"PAID","PAID DATE":"","RECORD_ID":"303affb6d32d4981b8b8fedc73b99291","Amount paid":"","DESCRIPTION":"HP PAVILION 1TB HDD","PHONE NUMBER":"","DEAL LOCATION":"","INTERNAL NOTE":"","EXPENSE AMOUNT":"","CALCULATED PROFIT":"","EXPENSE DESCRIPTION":"","IMEI FOR SWAPPED DEAL":""} | N43: 2026-05-11T22:00:09.855781+01:00 | O43: 2026-05-11T22:00:09.855781+01:00
A44: 659a57f80bc94538946b864ec33870e7 | B44: 659a57f80bc94538946b864ec33870e7 | C44: 51eec0e370719d946db4b415be10d322cf25393e2a51dd24b7f3595500881135 | D44: 44 | F44: EMPEROR CORPER | G44: PAID | I44: 2026-02-18T00:00:00+01:00 | J44: 0 | L44: 3000 | M44: {"in":42,"DATE":"2/18/2026","IMEI":"","NAME":"EMPEROR CORPER","TIME":8,"PRICE":"\u20a63,000.00","STATUS":"PAID","PAID DATE":"","RECORD_ID":"659a57f80bc94538946b864ec33870e7","Amount paid":"","DESCRIPTION":"SUPERBIKE MAN DISPATCH TO ENGINEER ISAAC","PHONE NUMBER":"","DEAL LOCATION":"","INTERNAL NOTE":"","EXPENSE AMOUNT":"","CALCULATED PROFIT":"","EXPENSE DESCRIPTION":"","IMEI FOR SWAPPED DEAL":""} | N44: 2026-05-11T22:00:09.855781+01:00 | O44: 2026-05-11T22:00:09.855781+01:00
A45: b1f5c60eb3504112b40d0c61a6075916 | B45: b1f5c60eb3504112b40d0c61a6075916 | C45: d13ee6bfa23a1a7c7929a25376a547a0aa86c35aea58b391917d4ed09be4eeb2 | D45: 45 | F45: OLLY | G45: PAID | I45: 2026-02-18T00:00:00+01:00 | J45: 0 | L45: 35000 | M45: {"in":43,"DATE":"2/18/2026","IMEI":"","NAME":"OLLY","TIME":9,"PRICE":"\u20a635,000.00","STATUS":"PAID","PAID DATE":"","RECORD_ID":"b1f5c60eb3504112b40d0c61a6075916","Amount paid":"","DESCRIPTION":"ESIM 1 MONTH","PHONE NUMBER":"","DEAL LOCATION":"","INTERNAL NOTE":"","EXPENSE AMOUNT":"","CALCULATED PROFIT":"","EXPENSE DESCRIPTION":"","IMEI FOR SWAPPED DEAL":""} | N45: 2026-05-11T22:00:09.855781+01:00 | O45: 2026-05-11T22:00:09.855781+01:00
A46: 11f19a7f43ff44c189d963304bd3b32c | B46: 11f19a7f43ff44c189d963304bd3b32c | C46: 6e5c6a93c7dd072b1cfeed890b5a2665134dda07d9b3ef9d502101781cfa9e39 | D46: 46 | F46: DENIS4WARD | G46: PAID | I46: 2025-11-14T00:00:00+01:00 | J46: 0 | L46: 40000 | M46: {"in":44,"DATE":"11/14/2025","IMEI":"","NAME":"DENIS4WARD","TIME":10,"PRICE":"\u20a640,000.00","STATUS":"PAID","PAID DATE":"","RECORD_ID":"11f19a7f43ff44c189d963304bd3b32c","Amount paid":"","DESCRIPTION":"CONVOCATION DRINK","PHONE NUMBER":2348038551439,"DEAL LOCATION":"","INTERNAL NOTE":"","EXPENSE AMOUNT":"","CALCULATED PROFIT":"","EXPENSE DESCRIPTION":"","IMEI FOR SWAPPED DEAL":""} | N46: 2026-05-11T22:00:09.855781+01:00 | O46: 2026-05-11T22:00:09.855781+01:00
A47: b5279189300d42909bff74710f3f263a | B47: b5279189300d42909bff74710f3f263a | C47: 6eead6b54d6ee72159e37bc6d628df8a2cae07028ed5996104446be801dcbb71 | D47: 47 | F47: DENIS4WARD | G47: PAID | I47: 2026-01-13T00:00:00+01:00 | J47: 0 | L47: 16250 | M47: {"in":"","DATE":"1/13/2026","IMEI":"","NAME":"DENIS4WARD","TIME":11,"PRICE":"\u20a616,250.00","STATUS":"PAID","PAID DATE":"","RECORD_ID":"b5279189300d42909bff74710f3f263a","Amount paid":"","DESCRIPTION":"GAS FILL","PHONE NUMBER":2348038551439,"DEAL LOCATION":"","INTERNAL NOTE":"","EXPENSE AMOUNT":"","CALCULATED PROFIT":"","EXPENSE DESCRIPTION":"","IMEI FOR SWAPPED DEAL":""} | N47: 2026-05-11T22:00:09.855781+01:00 | O47: 2026-05-11T22:00:09.855781+01:00
A48: 99aa324644f94ceea7045ff30a389a90 | B48: 99aa324644f94ceea7045ff30a389a90 | C48: 94e699455683858ebfad3f296dee43141ee5c15cb2a8ac3887fa1e27045fbcfc | D48: 48 | E48: .. | F48: .. | G48: .. | J48: 0 | L48: 0 | M48: {"in":45,"DATE":"..","IMEI":"..","NAME":"..","TIME":"","PRICE":"..","STATUS":"..","PAID DATE":"","RECORD_ID":"99aa324644f94ceea7045ff30a389a90","Amount paid":"","DESCRIPTION":"..","PHONE NUMBER":"","DEAL LOCATION":"","INTERNAL NOTE":"","EXPENSE AMOUNT":"","CALCULATED PROFIT":"","EXPENSE DESCRIPTION":"","IMEI FOR SWAPPED DEAL":""} | N48: 2026-05-11T22:00:09.855781+01:00 | O48: 2026-05-11T22:00:09.855781+01:00
A49: 77b5d09c077f4d6bb71031d0575f0baa | B49: 77b5d09c077f4d6bb71031d0575f0baa | C49: 18e6b9953dd9f7d6e3b10e0671cb008eac9fc853368c8a634e8cde7256477223 | D49: 49 | F49: MOBILETRENDS | G49: RETURNED | J49: 0 | L49: 0 | M49: {"in":46,"DATE":"2/19/2026","IMEI":"","NAME":"MOBILETRENDS","TIME":1,"PRICE":"\u20a612,000.00","STATUS":"RETURNED","PAID DATE":"","RECORD_ID":"77b5d09c077f4d6bb71031d0575f0baa","Amount paid":"","DESCRIPTION":"IPHONE 11 APPLE ID INACTIVE FIX","PHONE NUMBER":"","DEAL LOCATION":"","INTERNAL NOTE":"","EXPENSE AMOUNT":"","CALCULATED PROFIT":"","EXPENSE DESCRIPTION":"","IMEI FOR SWAPPED DEAL":""} | N49: 2026-05-11T22:00:09.855781+01:00 | O49: 2026-05-11T22:00:09.855781+01:00
A50: cb1db8e857d84f30a5621e87a66cf2fd | B50: cb1db8e857d84f30a5621e87a66cf2fd | C50: 9c27d577bffdeac4de91495a0505ebaa9f6d79718064f79f4ee94fdf0f219c0c | D50: 50 | F50: BARRY | G50: UNPAID | J50: 0 | L50: 0 | M50: {"in":47,"DATE":"2/19/2026","IMEI":"","NAME":"BARRY","TIME":2,"PRICE":"\u20a62,500.00","STATUS":"UNPAID","PAID DATE":"","RECORD_ID":"cb1db8e857d84f30a5621e87a66cf2fd","Amount paid":"","DESCRIPTION":"PURPLE 14 PRO MAX IOS UPDATE TO 26.3","PHONE NUMBER":2347031524935,"DEAL LOCATION":"","INTERNAL NOTE":"","EXPENSE AMOUNT":"","CALCULATED PROFIT":"","EXPENSE DESCRIPTION":"","IMEI FOR SWAPPED DEAL":""} | N50: 2026-05-11T22:00:09.855781+01:00 | O50: 2026-05-11T22:00:09.855781+01:00
A51: 011c609d98814386ad639710a2987b95 | B51: 011c609d98814386ad639710a2987b95 | C51: 716218f8d9f1e45bae5061b86268681d28fbc4233146ce3a3d85c53030e8a5da | D51: 51 | F51: DEMEX | G51: PAID | I51: 2026-02-19T00:00:00+01:00 | J51: 0 | L51: 2500 | M51: {"in":48,"DATE":"2/19/2026","IMEI":"","NAME":"DEMEX","TIME":3,"PRICE":"\u20a62,500.00","STATUS":"paid","PAID DATE":"","RECORD_ID":"011c609d98814386ad639710a2987b95","Amount paid":"\u20a62,500.00","DESCRIPTION":"BLACK 15 PRO IOS UPDATE TO IOS 26.3","PHONE NUMBER":2347067462101,"DEAL LOCATION":"","INTERNAL NOTE":"","EXPENSE AMOUNT":"","CALCULATED PROFIT":"","EXPENSE DESCRIPTION":"","IMEI FOR SWAPPED DEAL":""} | N51: 2026-05-11T22:00:09.855781+01:00 | O51: 2026-05-11T22:00:09.855781+01:00
A52: 7f9d7500f604451d8bb942ea99fdbd24 | B52: 7f9d7500f604451d8bb942ea99fdbd24 | C52: f516c06be18ebbc1f74449f00075ed4ab915e6c511382c30dd7db63bd0812a1a | D52: 52 | F52: DAMBOX | G52: PAID | I52: 2026-02-19T00:00:00+01:00 | J52: 0 | L52: 2500 | M52: {"in":49,"DATE":"2/19/2026","IMEI":"","NAME":"DAMBOX","TIME":4,"PRICE":"\u20a62,500.00","STATUS":"PAID","PAID DATE":"","RECORD_ID":"7f9d7500f604451d8bb942ea99fdbd24","Amount paid":"","DESCRIPTION":"BLACK 16 PLUS IOS UPDATE","PHONE NUMBER":9040943517,"DEAL LOCATION":"","INTERNAL NOTE":"","EXPENSE AMOUNT":"","CALCULATED PROFIT":"","EXPENSE DESCRIPTION":"","IMEI FOR SWAPPED DEAL":""} | N52: 2026-05-11T22:00:09.855781+01:00 | O52: 2026-05-11T22:00:09.855781+01:00
A53: 28546211501b4ccd86b71da450e83548 | B53: 28546211501b4ccd86b71da450e83548 | C53: 72da228a4430ce8c3e0b36bdd21933323a1e58853ba4c5e97808351df29401ab | D53: 53 | F53: TUNDE BABZ | G53: PAID | I53: 2026-02-19T00:00:00+01:00 | J53: 0 | L53: 5000 | M53: {"in":50,"DATE":"2/19/2026","IMEI":"","NAME":"TUNDE BABZ","TIME":5,"PRICE":"\u20a65,000.00","STATUS":"PAID","PAID DATE":"","RECORD_ID":"28546211501b4ccd86b71da450e83548","Amount paid":"","DESCRIPTION":"NIGERIA APPLE ID","PHONE NUMBER":2348130793960,"DEAL LOCATION":"","INTERNAL NOTE":"","EXPENSE AMOUNT":"","CALCULATED PROFIT":"","EXPENSE DESCRIPTION":"","IMEI FOR SWAPPED DEAL":""} | N53: 2026-05-11T22:00:09.855781+01:00 | O53: 2026-05-11T22:00:09.855781+01:00
A54: 23c2b2928df544d29c8108a50e93ab07 | B54: 23c2b2928df544d29c8108a50e93ab07 | C54: eae8427db977bab651cad50f6cb5e400ef33d070acbc46d14fb0b3d176cc8f1f | D54: 54 | F54: IBRAHIM GADGS | G54: PAID | I54: 2026-02-19T00:00:00+01:00 | J54: 0 | L54: 360000 | M54: {"in":51,"DATE":"2/19/2026","IMEI":"","NAME":"IBRAHIM GADGS","TIME":6,"PRICE":"\u20a6360,000.00","STATUS":"PAID","PAID DATE":"","RECORD_ID":"23c2b2928df544d29c8108a50e93ab07","Amount paid":"","DESCRIPTION":"HP ELITEBOOK 1030G2 16GB + 256GB SSD","PHONE NUMBER":"","DEAL LOCATION":"","INTERNAL NOTE":"","EXPENSE AMOUNT":"","CALCULATED PROFIT":"","EXPENSE DESCRIPTION":"","IMEI FOR SWAPPED DEAL":""} | N54: 2026-05-11T22:00:09.855781+01:00 | O54: 2026-05-11T22:00:09.855781+01:00
A55: d7f133b8cd1e4dd1ad64d817b1d16d34 | B55: d7f133b8cd1e4dd1ad64d817b1d16d34 | C55: fc3eaaf84bdb7616d4ff022d37a2f0621399fe51a470f3fe11e67e26d7fb621f | D55: 55 | F55: PHILIPS OLUWAFEMI | G55: PAID | I55: 2026-02-19T00:00:00+01:00 | J55: 0 | L55: 5000 | M55: {"in":52,"DATE":"2/19/2026","IMEI":"","NAME":"PHILIPS OLUWAFEMI","TIME":7,"PRICE":"\u20a65,000.00","STATUS":"PAID","PAID DATE":"","RECORD_ID":"d7f133b8cd1e4dd1ad64d817b1d16d34","Amount paid":"","DESCRIPTION":"LOCATION ON IPHONE AIR IOS 26","PHONE NUMBER":"","DEAL LOCATION":"","INTERNAL NOTE":"","EXPENSE AMOUNT":"","CALCULATED PROFIT":"","EXPENSE DESCRIPTION":"","IMEI FOR SWAPPED DEAL":""} | N55: 2026-05-11T22:00:09.855781+01:00 | O55: 2026-05-11T22:00:09.855781+01:00
A56: 307d09a37adb4a178a0f674eafd48d11 | B56: 307d09a37adb4a178a0f674eafd48d11 | C56: 834d4665c1de61e9e2153d6a810f541dd1a84e380347612e753367ae0de34399 | D56: 56 | F56: RAYMOND FLASH | G56: PAID | I56: 2026-02-19T00:00:00+01:00 | J56: 0 | L56: 830000 | M56: {"in":53,"DATE":"2/19/2026","IMEI":"","NAME":"RAYMOND FLASH","TIME":8,"PRICE":"\u20a6830,000.00","STATUS":"PAID","PAID DATE":"","RECORD_ID":"307d09a37adb4a178a0f674eafd48d11","Amount paid":"","DESCRIPTION":"IPHONE 15 PRO BLUE TITANIUM P + E 87%","PHONE NUMBER":"","DEAL LOCATION":"","INTERNAL NOTE":"","EXPENSE AMOUNT":"","CALCULATED PROFIT":"","EXPENSE DESCRIPTION":"","IMEI FOR SWAPPED DEAL":""} | N56: 2026-05-11T22:00:09.855781+01:00 | O56: 2026-05-11T22:00:09.855781+01:00
A57: d23616dfdf79461f8541f9ead5c0ce85 | B57: d23616dfdf79461f8541f9ead5c0ce85 | C57: ea67b10eb5ee0dc81543f116399989d6c0a1b40a06865a456e3fb47468aeb278 | D57: 57 | F57: JENNIFER | G57: PAID | I57: 2026-02-19T00:00:00+01:00 | J57: 0 | L57: 400000 | M57: {"in":54,"DATE":"2/19/2026","IMEI":"","NAME":"JENNIFER","TIME":9,"PRICE":"\u20a6400,000.00","STATUS":"PAID","PAID DATE":"","RECORD_ID":"d23616dfdf79461f8541f9ead5c0ce85","Amount paid":"","DESCRIPTION":"IPHOPNE 16 E BLACK 354741550229463","PHONE NUMBER":"","DEAL LOCATION":"","INTERNAL NOTE":"","EXPENSE AMOUNT":"","CALCULATED PROFIT":"","EXPENSE DESCRIPTION":"","IMEI FOR SWAPPED DEAL":""} | N57: 2026-05-11T22:00:09.855781+01:00 | O57: 2026-05-11T22:00:09.855781+01:00
A58: b6692a162ae94d16960dfcdd3c59e242 | B58: b6692a162ae94d16960dfcdd3c59e242 | C58: b7a52a1bac939c7524c602aaeddf96a12bddcfc23814021d365715720e4d0900 | D58: 58 | E58: ... | F58: .. | G58: .. | J58: 0 | L58: 0 | M58: {"in":55,"DATE":"..","IMEI":"...","NAME":"..","TIME":"..","PRICE":"...","STATUS":"..","PAID DATE":"","RECORD_ID":"b6692a162ae94d16960dfcdd3c59e242","Amount paid":"","DESCRIPTION":"..","PHONE NUMBER":"","DEAL LOCATION":"","INTERNAL NOTE":"","EXPENSE AMOUNT":"","CALCULATED PROFIT":"","EXPENSE DESCRIPTION":"","IMEI FOR SWAPPED DEAL":""} | N58: 2026-05-11T22:00:09.855781+01:00 | O58: 2026-05-11T22:00:09.855781+01:00
A59: 82ff85b965ef4000b65f89e3d3a96c2a | B59: 82ff85b965ef4000b65f89e3d3a96c2a | C59: e520cd8c90c13f3df02045ef6270826f4570a36490823d70efd03501d92c57ae | D59: 59 | E59: ... | F59: .. | G59: .. | J59: 0 | L59: 0 | M59: {"in":56,"DATE":"..","IMEI":"...","NAME":"..","TIME":"..","PRICE":"...","STATUS":"..","PAID DATE":"","RECORD_ID":"82ff85b965ef4000b65f89e3d3a96c2a","Amount paid":"","DESCRIPTION":"..","PHONE NUMBER":"","DEAL LOCATION":"","INTERNAL NOTE":"","EXPENSE AMOUNT":"","CALCULATED PROFIT":"","EXPENSE DESCRIPTION":"","IMEI FOR SWAPPED DEAL":""} | N59: 2026-05-11T22:00:09.855781+01:00 | O59: 2026-05-11T22:00:09.855781+01:00
A60: 97b672e02eca43ca8ee818a9261eea9e | B60: 97b672e02eca43ca8ee818a9261eea9e | C60: e504b97449b411157f5c9f159d19e3335fd0c224a46f404fa8e70337aae4970c | D60: 60 | F60: BAYESH | G60: PAID | I60: 2026-02-20T00:00:00+01:00 | J60: 0 | L60: 2500 | M60: {"in":57,"DATE":"2/20/2026","IMEI":"","NAME":"BAYESH","TIME":1,"PRICE":"\u20a62,500.00","STATUS":"PAID","PAID DATE":"","RECORD_ID":"97b672e02eca43ca8ee818a9261eea9e","Amount paid":"","DESCRIPTION":"GOLD IPHONE XS IOS UPDATE","PHONE NUMBER":2348136276066,"DEAL LOCATION":"","INTERNAL NOTE":"","EXPENSE AMOUNT":"","CALCULATED PROFIT":"","EXPENSE DESCRIPTION":"","IMEI FOR SWAPPED DEAL":""} | N60: 2026-05-11T22:00:09.855781+01:00 | O60: 2026-05-11T22:00:09.855781+01:00
A61: 20810a056f264a6d8dad7b02782070fb | B61: 20810a056f264a6d8dad7b02782070fb | C61: ef42d5841abf3f35470c327718a22428366fd3f77d03a0579803801af6734463 | D61: 61 | F61: FEMZ GADGET | G61: PAID | I61: 2026-02-20T00:00:00+01:00 | J61: 0 | L61: 265000 | M61: {"in":58,"DATE":"2/20/2026","IMEI":"","NAME":"FEMZ GADGET","TIME":2,"PRICE":"\u20a6265,000.00","STATUS":"PAID","PAID DATE":"","RECORD_ID":"20810a056f264a6d8dad7b02782070fb","Amount paid":"","DESCRIPTION":"IPHONE 12 128GB WHITE 359035292273391 91%","PHONE NUMBER":"","DEAL LOCATION":"","INTERNAL NOTE":"","EXPENSE AMOUNT":"","CALCULATED PROFIT":"","EXPENSE DESCRIPTION":"","IMEI FOR SWAPPED DEAL":""} | N61: 2026-05-11T22:00:09.855781+01:00 | O61: 2026-05-11T22:00:09.855781+01:00
A62: 8b827bfe21c94d37b87a9c19e6cd1540 | B62: 8b827bfe21c94d37b87a9c19e6cd1540 | C62: 4acff15af30e198ab57ba2f8ec7a94b8aacf7d628967b79940c62ae8e5031272 | D62: 62 | F62: FM LORD | G62: PAID | I62: 2026-02-20T00:00:00+01:00 | J62: 0 | L62: 5000 | M62: {"in":59,"DATE":"2/20/2026","IMEI":"","NAME":"FM LORD","TIME":3,"PRICE":"\u20a65,000.00","STATUS":"PAID","PAID DATE":"","RECORD_ID":"8b827bfe21c94d37b87a9c19e6cd1540","Amount paid":"","DESCRIPTION":"NIGERIA APPLE ID CREATE","PHONE NUMBER":"","DEAL LOCATION":"","INTERNAL NOTE":"","EXPENSE AMOUNT":"","CALCULATED PROFIT":"","EXPENSE DESCRIPTION":"","IMEI FOR SWAPPED DEAL":""} | N62: 2026-05-11T22:00:09.855781+01:00 | O62: 2026-05-11T22:00:09.855781+01:00
A63: ccedac4140b9443684d14cf83f03a2ec | B63: ccedac4140b9443684d14cf83f03a2ec | C63: 28bfc0d2824a96a6f0db970824e0c1d40d5043291146d2bc5e895f76932effd1 | D63: 63 | F63: FORMULA | G63: PAID | I63: 2026-02-20T00:00:00+01:00 | J63: 0 | L63: 2500 | M63: {"in":60,"DATE":"2/20/2026","IMEI":"","NAME":" FORMULA","TIME":4,"PRICE":"\u20a62,500.00","STATUS":"PAID","PAID DATE":"","RECORD_ID":"ccedac4140b9443684d14cf83f03a2ec","Amount paid":"","DESCRIPTION":"BLUE IPHONE 13 IOS UPDATE","PHONE NUMBER":2347067612418,"DEAL LOCATION":"","INTERNAL NOTE":"","EXPENSE AMOUNT":"","CALCULATED PROFIT":"","EXPENSE DESCRIPTION":"","IMEI FOR SWAPPED DEAL":""} | N63: 2026-05-11T22:00:09.855781+01:00 | O63: 2026-05-11T22:00:09.855781+01:00
A64: f47836ca49134dfd903ed1d3f420dbaa | B64: f47836ca49134dfd903ed1d3f420dbaa | C64: 856dbfb12bc9720750e5c81884915d7dd4017f1ec1fa68b25b3c01cb71216d19 | D64: 64 | F64: FOLAKEMI | G64: PAID | I64: 2026-02-20T00:00:00+01:00 | J64: 0 | L64: 2500 | M64: {"in":61,"DATE":"2/20/2026","IMEI":"","NAME":"FOLAKEMI","TIME":5,"PRICE":"\u20a62,500.00","STATUS":"PAID","PAID DATE":"","RECORD_ID":"f47836ca49134dfd903ed1d3f420dbaa","Amount paid":"","DESCRIPTION":"PURPLE IPHONE 14 PRO MAX IOS UPDATE","PHONE NUMBER":2349075624207,"DEAL LOCATION":"","INTERNAL NOTE":"","EXPENSE AMOUNT":"","CALCULATED PROFIT":"","EXPENSE DESCRIPTION":"","IMEI FOR SWAPPED DEAL":""} | N64: 2026-05-11T22:00:09.855781+01:00 | O64: 2026-05-11T22:00:09.855781+01:00
A65: 95319025ec8b4cd5a83f755bde556535 | B65: 95319025ec8b4cd5a83f755bde556535 | C65: 7c7d2dfad96f076675333d54f71fcdecb21d6d935805172f200fee28bf889484 | D65: 65 | F65: BIMKEM | G65: PAID | I65: 2026-02-20T00:00:00+01:00 | J65: 0 | L65: 368000 | M65: {"in":62,"DATE":"2/20/2026","IMEI":"","NAME":"BIMKEM","TIME":6,"PRICE":"\u20a6368,000.00","STATUS":"PAID","PAID DATE":"","RECORD_ID":"95319025ec8b4cd5a83f755bde556535","Amount paid":"","DESCRIPTION":"IPHONE 13 128GB 100% ","PHONE NUMBER":"","DEAL LOCATION":"","INTERNAL NOTE":"","EXPENSE AMOUNT":"","CALCULATED PROFIT":"","EXPENSE DESCRIPTION":"","IMEI FOR SWAPPED DEAL":""} | N65: 2026-05-11T22:00:09.855781+01:00 | O65: 2026-05-11T22:00:09.855781+01:00
A66: c2c427764c2a4778990c3b8c76c360b8 | B66: c2c427764c2a4778990c3b8c76c360b8 | C66: 511f23daffe083b934fced62c92fdb6257a38470dc4ca34e7e6ac7853984d149 | D66: 66 | F66: FORMULA | G66: PAID | I66: 2026-02-20T00:00:00+01:00 | J66: 0 | L66: 2500 | M66: {"in":63,"DATE":"2/20/2026","IMEI":"","NAME":" FORMULA","TIME":7,"PRICE":"\u20a62,500.00","STATUS":"PAID","PAID DATE":"","RECORD_ID":"c2c427764c2a4778990c3b8c76c360b8","Amount paid":"","DESCRIPTION":" IPHONE 16 TEAL","PHONE NUMBER":2347067612418,"DEAL LOCATION":"","INTERNAL NOTE":"","EXPENSE AMOUNT":"","CALCULATED PROFIT":"","EXPENSE DESCRIPTION":"","IMEI FOR SWAPPED DEAL":""} | N66: 2026-05-11T22:00:09.855781+01:00 | O66: 2026-05-11T22:00:09.855781+01:00
A67: 85e27ef19a9f4982952a54eaf24ca700 | B67: 85e27ef19a9f4982952a54eaf24ca700 | C67: cee82062cc33c828e6d77509c3f19183c49187e3faea0c670aacff6269547fdf | D67: 67 | F67: ANOINTED WEALTH | G67: PAID | I67: 2026-02-20T00:00:00+01:00 | J67: 0 | L67: 2500 | M67: {"in":64,"DATE":"2/20/2026","IMEI":"","NAME":"ANOINTED WEALTH","TIME":8,"PRICE":"\u20a62,500.00","STATUS":"PAID","PAID DATE":"","RECORD_ID":"85e27ef19a9f4982952a54eaf24ca700","Amount paid":"","DESCRIPTION":"IPHONE 15 UPDATE","PHONE NUMBER":2348137226383,"DEAL LOCATION":"","INTERNAL NOTE":"","EXPENSE AMOUNT":"","CALCULATED PROFIT":"","EXPENSE DESCRIPTION":"","IMEI FOR SWAPPED DEAL":""} | N67: 2026-05-11T22:00:09.855781+01:00 | O67: 2026-05-11T22:00:09.855781+01:00
A68: 9da89966b8024927962ca916a386bf9c | B68: 9da89966b8024927962ca916a386bf9c | C68: cbb01d30a2edde8ce524a949cab775bb276fcf9c6faf67badfa2498a7f0e772e | D68: 68 | F68: ANOINTED WEALTH | G68: PAID | I68: 2026-02-05T00:00:00+01:00 | J68: 0 | L68: 2500 | M68: {"in":65,"DATE":"2/5/2026","IMEI":"","NAME":"ANOINTED WEALTH","TIME":9,"PRICE":"\u20a62,500.00","STATUS":"PAID","PAID DATE":"","RECORD_ID":"9da89966b8024927962ca916a386bf9c","Amount paid":"","DESCRIPTION":"IPHONE 16 PRO MAX UPDATE","PHONE NUMBER":2348137226383,"DEAL LOCATION":"","INTERNAL NOTE":"","EXPENSE AMOUNT":"","CALCULATED PROFIT":"","EXPENSE DESCRIPTION":"","IMEI FOR SWAPPED DEAL":""} | N68: 2026-05-11T22:00:09.855781+01:00 | O68: 2026-05-11T22:00:09.855781+01:00
A69: a38eafede69a423e9af8336b7c02c409 | B69: a38eafede69a423e9af8336b7c02c409 | C69: 20594ff64dad51ccd3b7a9b4d40792ae9d70eb8d4891883f1246cbab1281b817 | D69: 69 | F69: POPOOLA MATTHEW | G69: PAID | I69: 2026-02-20T00:00:00+01:00 | J69: 0 | L69: 10000 | M69: {"in":66,"DATE":"2/20/2026","IMEI":"","NAME":"POPOOLA MATTHEW","TIME":10,"PRICE":"\u20a610,000.00","STATUS":"PAID","PAID DATE":"","RECORD_ID":"a38eafede69a423e9af8336b7c02c409","Amount paid":"","DESCRIPTION":"2 LOCATION CHANGE FOR IOS 18+","PHONE NUMBER":"","DEAL LOCATION":"","INTERNAL NOTE":"","EXPENSE AMOUNT":"","CALCULATED PROFIT":"","EXPENSE DESCRIPTION":"","IMEI FOR SWAPPED DEAL":""} | N69: 2026-05-11T22:00:09.855781+01:00 | O69: 2026-05-11T22:00:09.855781+01:00
A70: da4ee50a72ba4777942c220a4b94198e | B70: da4ee50a72ba4777942c220a4b94198e | C70: 225b54d24210a18d88b20f5b89d71d5b031b0d24494357a326ae08b1bb6c8d95 | D70: 70 | F70: GOLD GADGET | G70: PAID | I70: 2026-02-20T00:00:00+01:00 | J70: 0 | L70: 5000 | M70: {"in":67,"DATE":"2/20/2026","IMEI":"","NAME":"GOLD GADGET","TIME":11,"PRICE":"\u20a65,000.00","STATUS":"PAID","PAID DATE":"","RECORD_ID":"da4ee50a72ba4777942c220a4b94198e","Amount paid":"","DESCRIPTION":"IPHONE 12 LOCATION CHANGE","PHONE NUMBER":"","DEAL LOCATION":"","INTERNAL NOTE":"","EXPENSE AMOUNT":"","CALCULATED PROFIT":"","EXPENSE DESCRIPTION":"","IMEI FOR SWAPPED DEAL":""} | N70: 2026-05-11T22:00:09.855781+01:00 | O70: 2026-05-11T22:00:09.855781+01:00
A71: 9d987e002bde459998b1af78298c570e | B71: 9d987e002bde459998b1af78298c570e | C71: f34ff9ee3b5d9293f218c18db131fcf8569cd0f8a88df85022bac582c1eface7 | D71: 71 | F71: OLAFISOYE OLUWATOSIN | G71: PAID | I71: 2026-02-20T00:00:00+01:00 | J71: 0 | L71: 15000 | M71: {"in":68,"DATE":"2/20/2026","IMEI":"","NAME":"OLAFISOYE OLUWATOSIN","TIME":12,"PRICE":"\u20a615,000.00","STATUS":"PAID","PAID DATE":"","RECORD_ID":"9d987e002bde459998b1af78298c570e","Amount paid":"","DESCRIPTION":"CHIP FOR PURPLE IPHONE 11","PHONE NUMBER":"","DEAL LOCATION":"","INTERNAL NOTE":"","EXPENSE AMOUNT":"","CALCULATED PROFIT":"","EXPENSE DESCRIPTION":"","IMEI FOR SWAPPED DEAL":""} | N71: 2026-05-11T22:00:09.855781+01:00 | O71: 2026-05-11T22:00:09.855781+01:00
... A79: b493d019bdab44d99219bbfe48f534aa | B79: b493d019bdab44d99219bbfe48f534aa | C79: 521bdda9568fb942e7180a2a058470ddfea1586893cc6804b9bd16a41be89783 | D79: 79 | F79: TOBI DAVID | G79: PAID | I79: 2026-02-20T00:00:00+01:00 | J79: 0 | L79: 15000 | M79: {"in":77,"DATE":"2/20/2026","IMEI":"","NAME":"TOBI DAVID","TIME":20,"PRICE":"\u20a615,000.00","STATUS":"PAID","PAID DATE":"","RECORD_ID":"b493d019bdab44d99219bbfe48f534aa","Amount paid":"","DESCRIPTION":"11 PRO MAX CHIP","PHONE NUMBER":"","DEAL LOCATION":"","INTERNAL NOTE":"","EXPENSE AMOUNT":"","CALCULATED PROFIT":"","EXPENSE DESCRIPTION":"","IMEI FOR SWAPPED DEAL":""} | N79: 2026-05-11T22:00:09.855781+01:00 | O79: 2026-05-11T22:00:09.855781+01:00
A80: 2bae46277e624bb497f4ea485378b54e | B80: 2bae46277e624bb497f4ea485378b54e | C80: 08dbc17a78e8d9970f41608bb04696978b057150be727f4a546b5d56b7bbc41d | D80: 80 | E80: .. | F80: .. | G80: .. | J80: 0 | L80: 0 | M80: {"in":78,"DATE":"..","IMEI":"..","NAME":"..","TIME":"..","PRICE":"..","STATUS":"..","PAID DATE":"","RECORD_ID":"2bae46277e624bb497f4ea485378b54e","Amount paid":"","DESCRIPTION":"..","PHONE NUMBER":"","DEAL LOCATION":"","INTERNAL NOTE":"","EXPENSE AMOUNT":"","CALCULATED PROFIT":"","EXPENSE DESCRIPTION":"","IMEI FOR SWAPPED DEAL":""} | N80: 2026-05-11T22:00:09.855781+01:00 | O80: 2026-05-11T22:00:09.855781+01:00
A81: 8034b9cfc29146a7b02f995313a82b96 | B81: 8034b9cfc29146a7b02f995313a82b96 | C81: 0cbcd1fe58e20c9d02acf66c8a77c38272b1ed0a7f78af3a924938b3d2674063 | D81: 81 | E81: .. | F81: .. | G81: .. | J81: 0 | L81: 0 | M81: {"in":79,"DATE":"..","IMEI":"..","NAME":"..","TIME":"","PRICE":"..","STATUS":"..","PAID DATE":"","RECORD_ID":"8034b9cfc29146a7b02f995313a82b96","Amount paid":"","DESCRIPTION":"..","PHONE NUMBER":"","DEAL LOCATION":"","INTERNAL NOTE":"","EXPENSE AMOUNT":"","CALCULATED PROFIT":"","EXPENSE DESCRIPTION":"","IMEI FOR SWAPPED DEAL":""} | N81: 2026-05-11T22:00:09.855781+01:00 | O81: 2026-05-11T22:00:09.855781+01:00
A82: c694551436c641b2905b330e7ffde5d9 | B82: c694551436c641b2905b330e7ffde5d9 | C82: 1534a1aadee6db6bd4e68ee0e089d958e0e88e08aa6e745f8cef54591f057148 | D82: 82 | F82: DAMBOX | G82: PAID | I82: 2026-02-21T00:00:00+01:00 | J82: 0 | L82: 2500 | M82: {"in":80,"DATE":"2/21/2026","IMEI":"","NAME":"DAMBOX","TIME":1,"PRICE":"\u20a62,500.00","STATUS":"PAID","PAID DATE":"","RECORD_ID":"c694551436c641b2905b330e7ffde5d9","Amount paid":"","DESCRIPTION":"IPHONE AIR IOS UPDATE","PHONE NUMBER":9040943517,"DEAL LOCATION":"","INTERNAL NOTE":"","EXPENSE AMOUNT":"","CALCULATED PROFIT":"","EXPENSE DESCRIPTION":"","IMEI FOR SWAPPED DEAL":""} | N82: 2026-05-11T22:00:09.855781+01:00 | O82: 2026-05-11T22:00:09.855781+01:00
A83: 4d85b5525de34cb0b3cd164ba76d018f | B83: 4d85b5525de34cb0b3cd164ba76d018f | C83: 5869075777414dde5880f77af04c5c9dcd47667ffaffb5497c2d65cd81920e68 | D83: 83 | F83: DAH UNIQUE | G83: PAID | I83: 2026-02-21T00:00:00+01:00 | J83: 0 | L83: 2500 | M83: {"in":81,"DATE":"2/21/2026","IMEI":"","NAME":"DAH UNIQUE","TIME":2,"PRICE":"\u20a62,500.00","STATUS":"PAID","PAID DATE":"","RECORD_ID":"4d85b5525de34cb0b3cd164ba76d018f","Amount paid":"","DESCRIPTION":"BLACK 14 PRO MAX IOS UPDATE","PHONE NUMBER":2349070536253,"DEAL LOCATION":"","INTERNAL NOTE":"","EXPENSE AMOUNT":"","CALCULATED PROFIT":"","EXPENSE DESCRIPTION":"","IMEI FOR SWAPPED DEAL":""} | N83: 2026-05-11T22:00:09.855781+01:00 | O83: 2026-05-11T22:00:09.855781+01:00
A84: 52e1028a443d421a8f616965d43f7198 | B84: 52e1028a443d421a8f616965d43f7198 | C84: a883cbe38c890ded005d7e3c5ba8f6f87e28f488ad62db276c81b32517d015f3 | D84: 84 | F84: LIZZIE TECHBOX | G84: PAID | I84: 2026-02-21T00:00:00+01:00 | J84: 0 | L84: 15000 | M84: {"in":82,"DATE":"2/21/2026","IMEI":"","NAME":"LIZZIE TECHBOX","TIME":3,"PRICE":"\u20a615,000.00","STATUS":"PAID","PAID DATE":"","RECORD_ID":"52e1028a443d421a8f616965d43f7198","Amount paid":"","DESCRIPTION":"APPLE ID PASSWORD RECOVERY","PHONE NUMBER":"","DEAL LOCATION":"","INTERNAL NOTE":"","EXPENSE AMOUNT":"","CALCULATED PROFIT":"","EXPENSE DESCRIPTION":"","IMEI FOR SWAPPED DEAL":""} | N84: 2026-05-11T22:00:09.855781+01:00 | O84: 2026-05-11T22:00:09.855781+01:00
A85: c4718bc3cc4d40d7b902fb22cc4140c1 | B85: c4718bc3cc4d40d7b902fb22cc4140c1 | C85: 95fdfe2d143c3921acf92f143d8ceffc0c49fe6c25cefe52d58dd26f160cdb6f | D85: 85 | F85: RAYMOND FLASH | G85: PAID | I85: 2026-02-21T00:00:00+01:00 | J85: 0 | L85: 9300000 | M85: {"in":83,"DATE":"2/21/2026","IMEI":"","NAME":"RAYMOND FLASH","TIME":4,"PRICE":"\u20a69,300,000.00","STATUS":"PAID","PAID DATE":"","RECORD_ID":"c4718bc3cc4d40d7b902fb22cc4140c1","Amount paid":"","DESCRIPTION":"IPHONE 16 PRO BLACK 352657194592433 95%","PHONE NUMBER":"","DEAL LOCATION":"","INTERNAL NOTE":"","EXPENSE AMOUNT":"","CALCULATED PROFIT":"","EXPENSE DESCRIPTION":"","IMEI FOR SWAPPED DEAL":""} | N85: 2026-05-11T22:00:09.855781+01:00 | O85: 2026-05-11T22:00:09.855781+01:00
A86: 3708bbba431146d7a8ce439730664e4d | B86: 3708bbba431146d7a8ce439730664e4d | C86: 42f49ad02c89fef1d42547aeeb4fe773d9ec779a2dd4ac2ac2ef7e88d36c4cc4 | D86: 86 | F86: PABLO | G86: PAID | I86: 2026-02-21T00:00:00+01:00 | J86: 0 | L86: 2500 | M86: {"in":84,"DATE":"2/21/2026","IMEI":"","NAME":"PABLO","TIME":5,"PRICE":"\u20a62,500.00","STATUS":"PAID","PAID DATE":"","RECORD_ID":"3708bbba431146d7a8ce439730664e4d","Amount paid":"","DESCRIPTION":"GOLD IPHONE 16 PRO MAX IOS UPDATE","PHONE NUMBER":"","DEAL LOCATION":"","INTERNAL NOTE":"","EXPENSE AMOUNT":"","CALCULATED PROFIT":"","EXPENSE DESCRIPTION":"","IMEI FOR SWAPPED DEAL":""} | N86: 2026-05-11T22:00:09.855781+01:00 | O86: 2026-05-11T22:00:09.855781+01:00
A87: ebf56a10fdf24b9f86c1b7f2d24127e4 | B87: ebf56a10fdf24b9f86c1b7f2d24127e4 | C87: 4aff0ba2c1016e0fbce621f181bdcf1f0f1860d27426f485ed93e8bca791792e | D87: 87 | F87: PABLO | G87: PAID | I87: 2026-02-22T00:00:00+01:00 | J87: 0 | L87: 15000 | M87: {"in":85,"DATE":"2/22/2026","IMEI":"","NAME":"PABLO","TIME":6,"PRICE":"\u20a615,000.00","STATUS":"PAID","PAID DATE":"","RECORD_ID":"ebf56a10fdf24b9f86c1b7f2d24127e4","Amount paid":"","DESCRIPTION":"CHIP ONLY FOR IPHONE 16 PRO MAX WITHOUT ESIM","PHONE NUMBER":"","DEAL LOCATION":"","INTERNAL NOTE":"","EXPENSE AMOUNT":"","CALCULATED PROFIT":"","EXPENSE DESCRIPTION":"","IMEI FOR SWAPPED DEAL":""} | N87: 2026-05-11T22:00:09.855781+01:00 | O87: 2026-05-11T22:00:09.855781+01:00
A88: 84b08607f0144d3d9159c52f38331244 | B88: 84b08607f0144d3d9159c52f38331244 | C88: 9f84a0b30cc0b6c5c605f4926ea170966a84e3ba4de4f6aae90539593a104936 | D88: 88 | F88: PANKEY | G88: PAID | I88: 2026-02-21T00:00:00+01:00 | J88: 0 | L88: 2500 | M88: {"in":86,"DATE":"2/21/2026","IMEI":"","NAME":"PANKEY","TIME":7,"PRICE":"\u20a62,500.00","STATUS":"PAID","PAID DATE":"","RECORD_ID":"84b08607f0144d3d9159c52f38331244","Amount paid":"","DESCRIPTION":"SILVER IPHONE 17 PRO MAX IOS UPDATE","PHONE NUMBER":"","DEAL LOCATION":"","INTERNAL NOTE":"","EXPENSE AMOUNT":"","CALCULATED PROFIT":"","EXPENSE DESCRIPTION":"","IMEI FOR SWAPPED DEAL":""} | N88: 2026-05-11T22:00:09.855781+01:00 | O88: 2026-05-11T22:00:09.855781+01:00
A89: cbf8150f13c64c69bf9f24433737d50f | B89: cbf8150f13c64c69bf9f24433737d50f | C89: 78c9a96ae23cd429a09261999b219ead15cb11f5ffb8b167744c2a31d33f68e6 | D89: 89 | F89: MR AYODELE | G89: PAID | I89: 2026-02-21T00:00:00+01:00 | J89: 0 | L89: 15000 | M89: {"in":87,"DATE":"2/21/2026","IMEI":"","NAME":"MR AYODELE","TIME":8,"PRICE":"\u20a615,000.00","STATUS":"PAID","PAID DATE":"","RECORD_ID":"cbf8150f13c64c69bf9f24433737d50f","Amount paid":"","DESCRIPTION":"SAMSUNG A17 FRP FIX","PHONE NUMBER":"","DEAL LOCATION":"","INTERNAL NOTE":"","EXPENSE AMOUNT":"","CALCULATED PROFIT":"","EXPENSE DESCRIPTION":"","IMEI FOR SWAPPED DEAL":""} | N89: 2026-05-11T22:00:09.855781+01:00 | O89: 2026-05-11T22:00:09.855781+01:00
A90: 01e26a8d2b654b60a6a3d0bfd4232177 | B90: 01e26a8d2b654b60a6a3d0bfd4232177 | C90: ab100cd018f1df1342c23abea82cf3dcdfdb793f2b4d2a1052446c9bbc235a31 | D90: 90 | F90: TOP MAN | G90: PAID | I90: 2026-02-21T00:00:00+01:00 | J90: 0 | L90: 2500 | M90: {"in":88,"DATE":"2/21/2026","IMEI":"","NAME":"TOP MAN","TIME":9,"PRICE":"\u20a62,500.00","STATUS":"PAID","PAID DATE":"","RECORD_ID":"01e26a8d2b654b60a6a3d0bfd4232177","Amount paid":"","DESCRIPTION":"IPHONE 13 WHITE IOS UPDATE","PHONE NUMBER":"","DEAL LOCATION":"","INTERNAL NOTE":"","EXPENSE AMOUNT":"","CALCULATED PROFIT":"","EXPENSE DESCRIPTION":"","IMEI FOR SWAPPED DEAL":""} | N90: 2026-05-11T22:00:09.855781+01:00 | O90: 2026-05-11T22:00:09.855781+01:00
A91: c6bfd29e311547ecbda0a4d8f5e08821 | B91: c6bfd29e311547ecbda0a4d8f5e08821 | C91: e287b9df815fe80d7385bf086e97746ce1beaec2f9153f6a30a2710c68723427 | D91: 91 | E91: ... | F91: .. | G91: .. | J91: 0 | L91: 0 | M91: {"in":89,"DATE":"..","IMEI":"...","NAME":"..","TIME":".","PRICE":"..","STATUS":"..","PAID DATE":"","RECORD_ID":"c6bfd29e311547ecbda0a4d8f5e08821","Amount paid":"","DESCRIPTION":"..","PHONE NUMBER":"","DEAL LOCATION":"","INTERNAL NOTE":"","EXPENSE AMOUNT":"","CALCULATED PROFIT":"","EXPENSE DESCRIPTION":"","IMEI FOR SWAPPED DEAL":""} | N91: 2026-05-11T22:00:09.855781+01:00 | O91: 2026-05-11T22:00:09.855781+01:00
A92: 6bb782d201984c2999cf627a821b01fe | B92: 6bb782d201984c2999cf627a821b01fe | C92: 8dec639ded570fe7950175a99c5579462b69889766bbca164548f207c51c569d | D92: 92 | E92: .. | F92: .. | G92: .. | J92: 0 | L92: 0 | M92: {"in":90,"DATE":"..","IMEI":"..","NAME":"..","TIME":"","PRICE":"..","STATUS":"..","PAID DATE":"","RECORD_ID":"6bb782d201984c2999cf627a821b01fe","Amount paid":"","DESCRIPTION":"..","PHONE NUMBER":"","DEAL LOCATION":"","INTERNAL NOTE":"","EXPENSE AMOUNT":"","CALCULATED PROFIT":"","EXPENSE DESCRIPTION":"","IMEI FOR SWAPPED DEAL":""} | N92: 2026-05-11T22:00:09.855781+01:00 | O92: 2026-05-11T22:00:09.855781+01:00
A93: 761d456d208b4da796a02b920dbd55c5 | B93: 761d456d208b4da796a02b920dbd55c5 | C93: 3a8bfb0bd397665f54f3a720ea253a651aadee52e795faac0834c510164b227d | D93: 93 | F93: CHUSTER | G93: PAID | I93: 2026-02-23T00:00:00+01:00 | J93: 0 | L93: 4000 | M93: {"in":91,"DATE":"2/23/2026","IMEI":"","NAME":"CHUSTER","TIME":1,"PRICE":"\u20a64,000.00","STATUS":"PAID","PAID DATE":"","RECORD_ID":"761d456d208b4da796a02b920dbd55c5","Amount paid":"","DESCRIPTION":"NIGERIA APPLE ID","PHONE NUMBER":"","DEAL LOCATION":"","INTERNAL NOTE":"","EXPENSE AMOUNT":"","CALCULATED PROFIT":"","EXPENSE DESCRIPTION":"","IMEI FOR SWAPPED DEAL":""} | N93: 2026-05-11T22:00:09.855781+01:00 | O93: 2026-05-11T22:00:09.855781+01:00
A94: 0d28acc2d09f4982a4e8313c2fb14917 | B94: 0d28acc2d09f4982a4e8313c2fb14917 | C94: 4a5bfc67d1c9c538b6e5125dd70db28f69ced13c349edb2f64ecc19139a7c0e9 | D94: 94 | F94: AWILO | G94: PAID | I94: 2026-02-23T00:00:00+01:00 | J94: 0 | L94: 250000 | M94: {"in":92,"DATE":"2/23/2026","IMEI":"","NAME":"AWILO","TIME":2,"PRICE":"\u20a6250,000.00","STATUS":"PAID","PAID DATE":"","RECORD_ID":"0d28acc2d09f4982a4e8313c2fb14917","Amount paid":"","DESCRIPTION":"APPLE WATCH SERIES 9","PHONE NUMBER":"","DEAL LOCATION":"","INTERNAL NOTE":"","EXPENSE AMOUNT":"","CALCULATED PROFIT":"","EXPENSE DESCRIPTION":"","IMEI FOR SWAPPED DEAL":""} | N94: 2026-05-11T22:00:09.855781+01:00 | O94: 2026-05-11T22:00:09.855781+01:00
A95: d983d9aa162748069b6402ab482f72ff | B95: d983d9aa162748069b6402ab482f72ff | C95: b6965cca68a66230dc0d99c6cd8ac8ccf6a79304775ae485b9bd67f0d3f06739 | D95: 95 | F95: DAMBOX | G95: PAID | I95: 2026-02-23T00:00:00+01:00 | J95: 0 | L95: 2500 | M95: {"in":93,"DATE":"2/23/2026","IMEI":"","NAME":"DAMBOX","TIME":3,"PRICE":"\u20a62,500.00","STATUS":"PAID","PAID DATE":"","RECORD_ID":"d983d9aa162748069b6402ab482f72ff","Amount paid":"","DESCRIPTION":"IPHONE 17 AIR IOS UPDATE","PHONE NUMBER":9040943517,"DEAL LOCATION":"","INTERNAL NOTE":"","EXPENSE AMOUNT":"","CALCULATED PROFIT":"","EXPENSE DESCRIPTION":"","IMEI FOR SWAPPED DEAL":""} | N95: 2026-05-11T22:00:09.855781+01:00 | O95: 2026-05-11T22:00:09.855781+01:00
A96: 5abfcab43e33484e8348fbebb46dd850 | B96: 5abfcab43e33484e8348fbebb46dd850 | C96: 6ac45447f5f53f49ce4e9c9a2c728569fede56f72294a12ae4d3842cea0076c9 | D96: 96 | F96: ZEE TECH | G96: PAID | I96: 2026-02-23T00:00:00+01:00 | J96: 0 | L96: 2500 | M96: {"in":94,"DATE":"2/23/2026","IMEI":"","NAME":"ZEE TECH","TIME":4,"PRICE":"\u20a62,500.00","STATUS":"PAID","PAID DATE":"","RECORD_ID":"5abfcab43e33484e8348fbebb46dd850","Amount paid":"","DESCRIPTION":"IPHONE 11 PRO PASSWORD FLASH","PHONE NUMBER":2349033724061,"DEAL LOCATION":"","INTERNAL NOTE":"","EXPENSE AMOUNT":"","CALCULATED PROFIT":"","EXPENSE DESCRIPTION":"","IMEI FOR SWAPPED DEAL":""} | N96: 2026-05-11T22:00:09.855781+01:00 | O96: 2026-05-11T22:00:09.855781+01:00
A97: d08f3e69b6f74269a268ddd490ebf54b | B97: d08f3e69b6f74269a268ddd490ebf54b | C97: 26c5db2695f755c259e677578b8bbe4c0683e5a9ed00bf372b7a7d9bdcf3b652 | D97: 97 | F97: OSAMA CUSTOMER | G97: PAID | I97: 2026-02-23T00:00:00+01:00 | J97: 0 | L97: 5000 | M97: {"in":95,"DATE":"2/23/2026","IMEI":"","NAME":"OSAMA CUSTOMER","TIME":5,"PRICE":"\u20a65,000.00","STATUS":"PAID","PAID DATE":"","RECORD_ID":"d08f3e69b6f74269a268ddd490ebf54b","Amount paid":"","DESCRIPTION":"NIGERIA APPLE ID CREATE ","PHONE NUMBER":"","DEAL LOCATION":"","INTERNAL NOTE":"","EXPENSE AMOUNT":"","CALCULATED PROFIT":"","EXPENSE DESCRIPTION":"","IMEI FOR SWAPPED DEAL":""} | N97: 2026-05-11T22:00:09.855781+01:00 | O97: 2026-05-11T22:00:09.855781+01:00
A98: c134793da67c4565aa3aeb4f41d85c6b | B98: c134793da67c4565aa3aeb4f41d85c6b | C98: a6ada57a35c47e0c084c6c4f0a87e3e12d40bac9333594bc22f86e2639138215 | D98: 98 | F98: OSAMA | G98: PAID | I98: 2026-02-23T00:00:00+01:00 | J98: 0 | L98: 3000 | M98: {"in":96,"DATE":"2/23/2026","IMEI":"","NAME":"OSAMA","TIME":6,"PRICE":"\u20a63,000.00","STATUS":"PAID","PAID DATE":"","RECORD_ID":"c134793da67c4565aa3aeb4f41d85c6b","Amount paid":"","DESCRIPTION":"IPHONE 12 PRO SDP FLASH","PHONE NUMBER":2348140672915,"DEAL LOCATION":"","INTERNAL NOTE":"","EXPENSE AMOUNT":"","CALCULATED PROFIT":"","EXPENSE DESCRIPTION":"","IMEI FOR SWAPPED DEAL":""} | N98: 2026-05-11T22:00:09.855781+01:00 | O98: 2026-05-11T22:00:09.855781+01:00
A99: 94357384bea040b9861cca9151d11585 | B99: 94357384bea040b9861cca9151d11585 | C99: 8d72e19c75f8d75758f3f63c6ce4fe4ff15d45ddf3928742e84a9585b1a07b7d | D99: 99 | F99: DENIS4WARD | G99: PAID | I99: 2026-02-23T00:00:00+01:00 | J99: 0 | L99: 3000 | M99: {"in":97,"DATE":"2/23/2026","IMEI":"","NAME":"DENIS4WARD","TIME":7,"PRICE":"\u20a63,000.00","STATUS":"PAID","PAID DATE":"","RECORD_ID":"94357384bea040b9861cca9151d11585","Amount paid":"","DESCRIPTION":"3K CASH FOR DISPATCH","PHONE NUMBER":2348038551439,"DEAL LOCATION":"","INTERNAL NOTE":"","EXPENSE AMOUNT":"","CALCULATED PROFIT":"","EXPENSE DESCRIPTION":"","IMEI FOR SWAPPED DEAL":""} | N99: 2026-05-11T22:00:09.855781+01:00 | O99: 2026-05-11T22:00:09.855781+01:00
A100: 40edcb7b32b04aa8b425278bbdb1eae4 | B100: 40edcb7b32b04aa8b425278bbdb1eae4 | C100: 69e66a531ea1acb3954eee64a0ab00b84ce4207dec1312b7cf8cfd634676227e | D100: 100 | F100: STARBOX | G100: PAID | I100: 2026-02-23T00:00:00+01:00 | J100: 0 | L100: 2500 | M100: {"in":98,"DATE":"2/23/2026","IMEI":"","NAME":"STARBOX","TIME":8,"PRICE":"\u20a62,500.00","STATUS":"PAID","PAID DATE":"","RECORD_ID":"40edcb7b32b04aa8b425278bbdb1eae4","Amount paid":"","DESCRIPTION":"IPHONE 17 AIR IOS UPDATE","PHONE NUMBER":2349063620334,"DEAL LOCATION":"","INTERNAL NOTE":"","EXPENSE AMOUNT":"","CALCULATED PROFIT":"","EXPENSE DESCRIPTION":"","IMEI FOR SWAPPED DEAL":""} | N100: 2026-05-11T22:00:09.855781+01:00 | O100: 2026-05-11T22:00:09.855781+01:00
A101: 593e7329fb6241aabcac32cf957f82e1 | B101: 593e7329fb6241aabcac32cf957f82e1 | C101: 379d5ce8fa2431652375097f50c09583e2032d91e6c1393ed715140c17cb71b6 | D101: 101 | F101: IA GADGET | G101: PAID | I101: 2026-02-23T00:00:00+01:00 | J101: 0 | L101: 2500 | M101: {"in":99,"DATE":"2/23/2026","IMEI":"","NAME":"IA GADGET","TIME":9,"PRICE":"\u20a62,500.00","STATUS":"PAID","PAID DATE":"","RECORD_ID":"593e7329fb6241aabcac32cf957f82e1","Amount paid":"\u20a62,500.00","DESCRIPTION":"GREEN IPHONE 15 IOS UPDATE","PHONE NUMBER":2347046539922,"DEAL LOCATION":"","INTERNAL NOTE":"","EXPENSE AMOUNT":"","CALCULATED PROFIT":"","EXPENSE DESCRIPTION":"","IMEI FOR SWAPPED DEAL":""} | N101: 2026-05-11T22:00:09.855781+01:00 | O101: 2026-05-11T22:00:09.855781+01:00
A102: d10271fc729a488c8157a6e8437325c6 | B102: d10271fc729a488c8157a6e8437325c6 | C102: a8584c81a393ce60e33df610b695fb13522accc5941d8da267974b1e8e26c01f | D102: 102 | F102: ZEE TECH | G102: PAID | I102: 2026-02-23T00:00:00+01:00 | J102: 0 | L102: 2500 | M102: {"in":100,"DATE":"2/23/2026","IMEI":"","NAME":"ZEE TECH","TIME":10,"PRICE":"\u20a62,500.00","STATUS":"PAID","PAID DATE":"","RECORD_ID":"d10271fc729a488c8157a6e8437325c6","Amount paid":"","DESCRIPTION":"BLACK IPHONE 15 IOS UPDATE","PHONE NUMBER":2349033724061,"DEAL LOCATION":"","INTERNAL NOTE":"","EXPENSE AMOUNT":"","CALCULATED PROFIT":"","EXPENSE DESCRIPTION":"","IMEI FOR SWAPPED DEAL":""} | N102: 2026-05-11T22:00:09.855781+01:00 | O102: 2026-05-11T22:00:09.855781+01:00
A103: b943380596eb48249bff8cd7c88d75b9 | B103: b943380596eb48249bff8cd7c88d75b9 | C103: e9ba3f2c17e7397c7efe611513ee38d9ea3f0260910214ec02c327d1cf97a9fd | D103: 103 | F103: YUSLORD GADGET | G103: PAID | I103: 2026-02-23T00:00:00+01:00 | J103: 0 | L103: 2500 | M103: {"in":101,"DATE":"2/23/2026","IMEI":"","NAME":"YUSLORD GADGET","TIME":11,"PRICE":"\u20a62,500.00","STATUS":"PAID","PAID DATE":"","RECORD_ID":"b943380596eb48249bff8cd7c88d75b9","Amount paid":"","DESCRIPTION":"BLACK 16 PRO MAX IOS UPDATE","PHONE NUMBER":"","DEAL LOCATION":"","INTERNAL NOTE":"","EXPENSE AMOUNT":"","CALCULATED PROFIT":"","EXPENSE DESCRIPTION":"","IMEI FOR SWAPPED DEAL":""} | N103: 2026-05-11T22:00:09.855781+01:00 | O103: 2026-05-11T22:00:09.855781+01:00
A104: 531ec737d3b84d2a9c00cb9d925a22cd | B104: 531ec737d3b84d2a9c00cb9d925a22cd | C104: 4ee6064105cf082b7d151cdd85a9bfdb25c91c65c33418265426d68a31b05b20 | D104: 104 | F104: CH4 | G104: PAID | I104: 2026-02-23T00:00:00+01:00 | J104: 0 | L104: 2500 | M104: {"in":102,"DATE":"2/23/2026","IMEI":"","NAME":"CH4","TIME":12,"PRICE":"\u20a62,500.00","STATUS":"PAID","PAID DATE":"","RECORD_ID":"531ec737d3b84d2a9c00cb9d925a22cd","Amount paid":"\u20a62,500.00","DESCRIPTION":"PURPLE IPHONE 14 PRO MAX IOS UPDATE","PHONE NUMBER":2348131941406,"DEAL LOCATION":"","INTERNAL NOTE":"","EXPENSE AMOUNT":"","CALCULATED PROFIT":"","EXPENSE DESCRIPTION":"","IMEI FOR SWAPPED DEAL":""} | N104: 2026-05-11T22:00:09.855781+01:00 | O104: 2026-05-11T22:00:09.855781+01:00
... A108: 77323c5bb41c4b50ba0bd8d4fabb9d0b | B108: 77323c5bb41c4b50ba0bd8d4fabb9d0b | C108: c886e7b53455d98bb1e0c2dae216e73ed12900524ccb65a390e4c367af5bd59e | D108: 108 | F108: MOSIMI | G108: PAID | I108: 2026-02-23T00:00:00+01:00 | J108: 0 | L108: 15000 | M108: {"in":106,"DATE":"2/23/2026","IMEI":"","NAME":"MOSIMI","TIME":"","PRICE":"\u20a615,000.00","STATUS":"PAID","PAID DATE":"","RECORD_ID":"77323c5bb41c4b50ba0bd8d4fabb9d0b","Amount paid":"","DESCRIPTION":"RED IPHONE 12 MDM BYPAS","PHONE NUMBER":"","DEAL LOCATION":"","INTERNAL NOTE":"","EXPENSE AMOUNT":"","CALCULATED PROFIT":"","EXPENSE DESCRIPTION":"","IMEI FOR SWAPPED DEAL":""} | N108: 2026-05-11T22:00:09.855781+01:00 | O108: 2026-05-11T22:00:09.855781+01:00
A109: a3e8d7b93aea445f8ff4deca7f1322f3 | B109: a3e8d7b93aea445f8ff4deca7f1322f3 | C109: e627dbae4023f731f6a65bf4f4c106b323f820dfb88a273917e0ecb9cf81c5e1 | D109: 109 | E109: .. | F109: .. | G109: ./ | J109: 0 | L109: 0 | M109: {"in":107,"DATE":"..","IMEI":"..","NAME":"..","TIME":"","PRICE":"..","STATUS":"./","PAID DATE":"","RECORD_ID":"a3e8d7b93aea445f8ff4deca7f1322f3","Amount paid":"","DESCRIPTION":"..","PHONE NUMBER":"","DEAL LOCATION":"","INTERNAL NOTE":"","EXPENSE AMOUNT":"","CALCULATED PROFIT":"","EXPENSE DESCRIPTION":"","IMEI FOR SWAPPED DEAL":""} | N109: 2026-05-11T22:00:09.855781+01:00 | O109: 2026-05-11T22:00:09.855781+01:00
A110: d1cc9188c03c416487da81cf76e782ea | B110: d1cc9188c03c416487da81cf76e782ea | C110: 25ff895d0d1b5de0c12c8b2ca12f7cdd4b305b3416def820e050d21590aaf6f5 | D110: 110 | E110: .. | F110: .. | G110: .. | J110: 0 | L110: 0 | M110: {"in":108,"DATE":"..","IMEI":"..","NAME":"..","TIME":".","PRICE":"..","STATUS":"..","PAID DATE":"","RECORD_ID":"d1cc9188c03c416487da81cf76e782ea","Amount paid":"","DESCRIPTION":"..","PHONE NUMBER":"","DEAL LOCATION":"","INTERNAL NOTE":"","EXPENSE AMOUNT":"","CALCULATED PROFIT":"","EXPENSE DESCRIPTION":"","IMEI FOR SWAPPED DEAL":""} | N110: 2026-05-11T22:00:09.855781+01:00 | O110: 2026-05-11T22:00:09.855781+01:00
A111: 7770a4380b2d4519820e2113702bcc1d | B111: 7770a4380b2d4519820e2113702bcc1d | C111: 53518bc9cc5b827b9aa901e160efce421cdff9e09e5c766316e2b6640090fa79 | D111: 111 | F111: OMONLA BUGATTI | G111: PAID | I111: 2026-02-24T00:00:00+01:00 | J111: 0 | L111: 2500 | M111: {"in":109,"DATE":"2/24/2026","IMEI":"","NAME":" OMONLA BUGATTI","TIME":1,"PRICE":"\u20a62,500.00","STATUS":"PAID","PAID DATE":"","RECORD_ID":"7770a4380b2d4519820e2113702bcc1d","Amount paid":"","DESCRIPTION":"GRAPHITE 12 PRO BATTERY FIX","PHONE NUMBER":2349036489677,"DEAL LOCATION":"","INTERNAL NOTE":"","EXPENSE AMOUNT":"","CALCULATED PROFIT":"","EXPENSE DESCRIPTION":"","IMEI FOR SWAPPED DEAL":""} | N111: 2026-05-11T22:00:09.855781+01:00 | O111: 2026-05-11T22:00:09.855781+01:00
A112: e29441e6ca074e05a971a67d4e4ae254 | B112: e29441e6ca074e05a971a67d4e4ae254 | C112: 164ed4b9597aab1c7a1b11c359dc0d84ae659eacea865d4fc3db28fc1d6a9ba6 | D112: 112 | F112: OMONLA BUGATTI | G112: PAID | I112: 2026-02-24T00:00:00+01:00 | J112: 0 | L112: 2500 | M112: {"in":110,"DATE":"2/24/2026","IMEI":"","NAME":"OMONLA BUGATTI","TIME":"","PRICE":"\u20a62,500.00","STATUS":"PAID","PAID DATE":"","RECORD_ID":"e29441e6ca074e05a971a67d4e4ae254","Amount paid":"","DESCRIPTION":"SKY BLUE 15 FIX BATTERY FLASH","PHONE NUMBER":2349036489677,"DEAL LOCATION":"","INTERNAL NOTE":"","EXPENSE AMOUNT":"","CALCULATED PROFIT":"","EXPENSE DESCRIPTION":"","IMEI FOR SWAPPED DEAL":""} | N112: 2026-05-11T22:00:09.855781+01:00 | O112: 2026-05-11T22:00:09.855781+01:00
A113: ddba4472d40a447c95c7a8068e9fd905 | B113: ddba4472d40a447c95c7a8068e9fd905 | C113: 6e252614de44bc57b836d4f24be420b291f92a7eacdeafac4feadddee4700c8b | D113: 113 | F113: TECH BOX | G113: PAID | I113: 2026-02-24T00:00:00+01:00 | J113: 0 | L113: 3000 | M113: {"in":111,"DATE":"2/24/2026","IMEI":"","NAME":"TECH BOX","TIME":"","PRICE":"\u20a63,000.00","STATUS":"PAID","PAID DATE":"","RECORD_ID":"ddba4472d40a447c95c7a8068e9fd905","Amount paid":"","DESCRIPTION":"IWATCH UPDATE","PHONE NUMBER":2348169747697,"DEAL LOCATION":"","INTERNAL NOTE":"","EXPENSE AMOUNT":"","CALCULATED PROFIT":"","EXPENSE DESCRIPTION":"","IMEI FOR SWAPPED DEAL":""} | N113: 2026-05-11T22:00:09.855781+01:00 | O113: 2026-05-11T22:00:09.855781+01:00
A114: 19cbc5535e3f4399ae440e34dd82675f | B114: 19cbc5535e3f4399ae440e34dd82675f | C114: 9efde67e29f6e9f5411c3f592109e158c59a6dd8a7aacfe544e386d9d775dc94 | D114: 114 | F114: ZEE GUY | G114: PAID | I114: 2026-02-24T00:00:00+01:00 | J114: 0 | L114: 3000 | M114: {"in":112,"DATE":"2/24/2026","IMEI":"","NAME":"ZEE GUY","TIME":"","PRICE":"\u20a63,000.00","STATUS":"PAID","PAID DATE":"","RECORD_ID":"19cbc5535e3f4399ae440e34dd82675f","Amount paid":"","DESCRIPTION":"FILE TRANSFER","PHONE NUMBER":"","DEAL LOCATION":"","INTERNAL NOTE":"","EXPENSE AMOUNT":"","CALCULATED PROFIT":"","EXPENSE DESCRIPTION":"","IMEI FOR SWAPPED DEAL":""} | N114: 2026-05-11T22:00:09.855781+01:00 | O114: 2026-05-11T22:00:09.855781+01:00
A115: 4c466f6f742b4166af6af1c145d78ef3 | B115: 4c466f6f742b4166af6af1c145d78ef3 | C115: 10232b0196dc6282aba2c15dd39f3c51fd6bf5c5ec62def998ffd89ed143c3fa | D115: 115 | F115: TOSIN FRO BUGATTI | G115: PAID | I115: 2026-02-24T00:00:00+01:00 | J115: 0 | L115: 2500 | M115: {"in":113,"DATE":"2/24/2026","IMEI":"","NAME":"TOSIN FRO BUGATTI","TIME":"","PRICE":"\u20a62,500.00","STATUS":"PAID","PAID DATE":"","RECORD_ID":"4c466f6f742b4166af6af1c145d78ef3","Amount paid":"","DESCRIPTION":"BLUE IPHONE 15 PRO MAX UPDATE ","PHONE NUMBER":"","DEAL LOCATION":"","INTERNAL NOTE":"","EXPENSE AMOUNT":"","CALCULATED PROFIT":"","EXPENSE DESCRIPTION":"","IMEI FOR SWAPPED DEAL":""} | N115: 2026-05-11T22:00:09.855781+01:00 | O115: 2026-05-11T22:00:09.855781+01:00
A116: 609453ec545a4c0ab400937297f6c229 | B116: 609453ec545a4c0ab400937297f6c229 | C116: cb82d1a36748807fad24a660ea434a45c5361fc3708878924abfaf01e75d266c | D116: 116 | F116: STAR BUSSY | G116: PAID | I116: 2026-02-24T00:00:00+01:00 | J116: 0 | L116: 5000 | M116: {"in":114,"DATE":"2/24/2026","IMEI":"","NAME":"STAR BUSSY","TIME":"","PRICE":"\u20a65,000.00","STATUS":"PAID","PAID DATE":"","RECORD_ID":"609453ec545a4c0ab400937297f6c229","Amount paid":"","DESCRIPTION":"NIGERIA APPLE ID","PHONE NUMBER":2348127738411,"DEAL LOCATION":"","INTERNAL NOTE":"","EXPENSE AMOUNT":"","CALCULATED PROFIT":"","EXPENSE DESCRIPTION":"","IMEI FOR SWAPPED DEAL":""} | N116: 2026-05-11T22:00:09.855781+01:00 | O116: 2026-05-11T22:00:09.855781+01:00
A117: 9708ae6ef84b4eed804dfc4203ae4ea4 | B117: 9708ae6ef84b4eed804dfc4203ae4ea4 | C117: 69a7470e71cd1a5faf744b98db24ad2376352596f85141b32beb7ecc4d6ceeb6 | D117: 117 | F117: NURUDEEN | G117: PAID | I117: 2026-02-24T00:00:00+01:00 | J117: 0 | L117: 2500 | M117: {"in":115,"DATE":"2/24/2026","IMEI":"","NAME":"NURUDEEN","TIME":"","PRICE":"\u20a62,500.00","STATUS":"PAID","PAID DATE":"","RECORD_ID":"9708ae6ef84b4eed804dfc4203ae4ea4","Amount paid":"","DESCRIPTION":"DESERT TITANIUM IPHONE 16 PRO MAX UPDATE","PHONE NUMBER":9122727950,"DEAL LOCATION":"","INTERNAL NOTE":"","EXPENSE AMOUNT":"","CALCULATED PROFIT":"","EXPENSE DESCRIPTION":"","IMEI FOR SWAPPED DEAL":""} | N117: 2026-05-11T22:00:09.855781+01:00 | O117: 2026-05-11T22:00:09.855781+01:00
A118: 8239bdaf880f455b944be61abd0bb6ed | B118: 8239bdaf880f455b944be61abd0bb6ed | C118: 4f32b8ae7f1d48696c5cb698ac97903caaa71a87ee42d1cfb611fcf801c925a8 | D118: 118 | F118: NURUDEEN | G118: PAID | I118: 2026-02-25T00:00:00+01:00 | J118: 0 | L118: 2500 | M118: {"in":116,"DATE":"2/25/2026","IMEI":"","NAME":"NURUDEEN","TIME":"","PRICE":"\u20a62,500.00","STATUS":"PAID","PAID DATE":"","RECORD_ID":"8239bdaf880f455b944be61abd0bb6ed","Amount paid":"","DESCRIPTION":" IPHONE 12 FIX BATTERY FIX ","PHONE NUMBER":9122727950,"DEAL LOCATION":"","INTERNAL NOTE":"","EXPENSE AMOUNT":"","CALCULATED PROFIT":"","EXPENSE DESCRIPTION":"","IMEI FOR SWAPPED DEAL":""} | N118: 2026-05-11T22:00:09.855781+01:00 | O118: 2026-05-11T22:00:09.855781+01:00
A119: cdea63fd3b37419e8f81a2b824d0ba43 | B119: cdea63fd3b37419e8f81a2b824d0ba43 | C119: c308b093b38c6d9d3f7156f58054d3c9e288f4aeda3d22474a793b62090cf51b | D119: 119 | E119: .. | F119: .. | G119: .. | J119: 0 | L119: 0 | M119: {"in":117,"DATE":"..","IMEI":"..","NAME":"..","TIME":"","PRICE":"..","STATUS":"..","PAID DATE":"","RECORD_ID":"cdea63fd3b37419e8f81a2b824d0ba43","Amount paid":"","DESCRIPTION":"..","PHONE NUMBER":"","DEAL LOCATION":"","INTERNAL NOTE":"","EXPENSE AMOUNT":"","CALCULATED PROFIT":"","EXPENSE DESCRIPTION":"","IMEI FOR SWAPPED DEAL":""} | N119: 2026-05-11T22:00:09.855781+01:00 | O119: 2026-05-11T22:00:09.855781+01:00
A120: 48a9302452254f41abe0a50a714f9e19 | B120: 48a9302452254f41abe0a50a714f9e19 | C120: a9210d637075d3d944b32047e1cdeba73af17d67ff094894d86f648a70ef9b71 | D120: 120 | E120: .. | F120: .. | G120: .. | J120: 0 | L120: 0 | M120: {"in":118,"DATE":"..","IMEI":"..","NAME":"..","TIME":".","PRICE":"..","STATUS":"..","PAID DATE":"","RECORD_ID":"48a9302452254f41abe0a50a714f9e19","Amount paid":"","DESCRIPTION":"..","PHONE NUMBER":"","DEAL LOCATION":"","INTERNAL NOTE":"","EXPENSE AMOUNT":"","CALCULATED PROFIT":"","EXPENSE DESCRIPTION":"","IMEI FOR SWAPPED DEAL":""} | N120: 2026-05-11T22:00:09.855781+01:00 | O120: 2026-05-11T22:00:09.855781+01:00
...

Sheet BACKUP_STOCK_PRODUCTS
A1: sync_key | B1: record_id | C1: source_hash | D1: sheet_row_num | E1: imei | F1: customer_name | G1: payment_status | H1: payment_date | I1: paid_date | J1: expense_amount | K1: expense_description | L1: calculated_profit | M1: payload_json | N1: created_at | O1: updated_at
A2: f4c0873e338746d89216ac34497d6f0b | B2: f4c0873e338746d89216ac34497d6f0b | C2: 14a8cfe388308096c071b929309db327aa00bc0bd9a7e0cb8be6c50c4e9dd2ab | D2: 4 | E2: 359428791784739 | F2: IYANUOLUWA DEMIGLOBAL | G2: SOLD | J2: 0 | L2: 0 | M2: {"S/N":"1","IMEI":"359428791784739","TIME":"","COLOUR":"BLUE TITANIUM","DEVICE":"IPHONE","STORAGE":"256GB","Column 17":"","Column 24":"","Column 25":"","Column 26":"","Column 27":"","Column 28":"","Column 29":"","Column 30":"","Column 31":"","Column 36":"","Column 37":"","Column 38":"","Column 39":"","Column 40":"","Column 41":"","Column 42":"","Column 43":"","Column 44":"","Column 45":"","Column 46":"","Column 47":"","PAID DATE":"","RECORD_ID":"f4c0873e338746d89216ac34497d6f0b","BATTERY. H":"89","CONDITIONS":"NONE","COST PRICE":"","DATE BOUGHT":"OCTOBER, 6, 2024","DESCRIPTION":"IPHONE 15 PRO MAX","DEAL LOCATION":"","INTERNAL NOTE":"","NAME OF BUYER":"IYANUOLUWA DEMIGLOBAL","EXPENSE AMOUNT":"","NAME OF SELLER":"O.Z GADGET","PRODUCT STATUS":"SOLD","STATUS OF DEVICE":"LOCKED","CALCULATED PROFIT":"","EXPENSE DESCRIPTION":"","PHONE NUMBER OF BUYER":"08088480573","AVAILABILITY/DATE SOLD":"","PHONE NUMBER OF SELLER":"08106293924","RECEIPT & EVIDIENCE LINK":""} | N2: 2026-05-11T22:24:59.340311+01:00 | O2: 2026-05-11T22:24:59.340311+01:00
A3: 3768e50b53064b5ba6ba5b400c6d2b89 | B3: 3768e50b53064b5ba6ba5b400c6d2b89 | C3: 2a7873bf50294f5b00dea2eb84e63f1f5018f8f5c69dd9bd1650e67c9bd88982 | D3: 5 | E3: 352846114777907 | F3: OLUFAD TELECOMMUNICATION | G3: SOLD | J3: 0 | L3: 0 | M3: {"S/N":"2","IMEI":"352846114777907","TIME":"","COLOUR":"GOLD","DEVICE":"IPHONE","STORAGE":"128GB","Column 17":"","Column 24":"","Column 25":"","Column 26":"","Column 27":"","Column 28":"","Column 29":"","Column 30":"","Column 31":"","Column 36":"","Column 37":"","Column 38":"","Column 39":"","Column 40":"","Column 41":"","Column 42":"","Column 43":"","Column 44":"","Column 45":"","Column 46":"","Column 47":"","PAID DATE":"","RECORD_ID":"3768e50b53064b5ba6ba5b400c6d2b89","BATTERY. H":"90","CONDITIONS":"NONE","COST PRICE":"","DATE BOUGHT":"SEPTEMBER, 30, 2024","DESCRIPTION":"IPHONE 13 PRO MAX","DEAL LOCATION":"","INTERNAL NOTE":"","NAME OF BUYER":"OLUFAD TELECOMMUNICATION","EXPENSE AMOUNT":"","NAME OF SELLER":"PAPPYTECH GADGET","PRODUCT STATUS":"SOLD","STATUS OF DEVICE":"LOCKED (THEN UNLOCKED)","CALCULATED PROFIT":"","EXPENSE DESCRIPTION":"","PHONE NUMBER OF BUYER":"09033780767","AVAILABILITY/DATE SOLD":"12/23/2024","PHONE NUMBER OF SELLER":"09064677372","RECEIPT & EVIDIENCE LINK":""} | N3: 2026-05-11T22:00:10.014056+01:00 | O3: 2026-05-11T22:00:10.014056+01:00
A4: cfa6b8aee46f496baf1bbf870b763913 | B4: cfa6b8aee46f496baf1bbf870b763913 | C4: 340828b1a19347fddcc37394bc5c1079fa907512081be760f04273f3ee20640c | D4: 6 | E4: RWRGQWTLDG | F4: RUL | G4: SOLD | J4: 0 | L4: 0 | M4: {"S/N":"3","IMEI":"RWRGQWTLDG","TIME":"","COLOUR":"BLACK","DEVICE":"IWATCH","STORAGE":"90+","Column 17":"","Column 24":"","Column 25":"","Column 26":"","Column 27":"","Column 28":"","Column 29":"","Column 30":"","Column 31":"","Column 36":"","Column 37":"","Column 38":"","Column 39":"","Column 40":"","Column 41":"","Column 42":"","Column 43":"","Column 44":"","Column 45":"","Column 46":"","Column 47":"","PAID DATE":"","RECORD_ID":"cfa6b8aee46f496baf1bbf870b763913","BATTERY. H":"97","CONDITIONS":"NONE","COST PRICE":"","DATE BOUGHT":"SEPTEMBER, 30, 2024","DESCRIPTION":"IWATCH SERIES 7","DEAL LOCATION":"","INTERNAL NOTE":"","NAME OF BUYER":"RUL ","EXPENSE AMOUNT":"","NAME OF SELLER":"AKINRULI","PRODUCT STATUS":"SOLD","STATUS OF DEVICE":"UNLOCKED (GPS)","CALCULATED PROFIT":"","EXPENSE DESCRIPTION":"","PHONE NUMBER OF BUYER":"08153978826","AVAILABILITY/DATE SOLD":"","PHONE NUMBER OF SELLER":"08153978826","RECEIPT & EVIDIENCE LINK":""} | N4: 2026-05-11T22:00:10.014056+01:00 | O4: 2026-05-11T22:00:10.014056+01:00
A5: de50ff235ae54e7bab6d84c727a8dfdb | B5: de50ff235ae54e7bab6d84c727a8dfdb | C5: 7cc6965aa60791361cff910a084530b1728b34d8017b28783e3c8291cf1cdfa3 | D5: 7 | E5: 351646277325994 | F5: MARVY FCG | G5: SOLD | J5: 0 | L5: 0 | M5: {"S/N":"4","IMEI":"351646277325994","TIME":"","COLOUR":"BLUE TITANIUM","DEVICE":"IPHONE","STORAGE":"256GB","Column 17":"","Column 24":"","Column 25":"","Column 26":"","Column 27":"","Column 28":"","Column 29":"","Column 30":"","Column 31":"","Column 36":"","Column 37":"","Column 38":"","Column 39":"","Column 40":"","Column 41":"","Column 42":"","Column 43":"","Column 44":"","Column 45":"","Column 46":"","Column 47":"","PAID DATE":"","RECORD_ID":"de50ff235ae54e7bab6d84c727a8dfdb","BATTERY. H":"100","CONDITIONS":"NONE","COST PRICE":"","DATE BOUGHT":"SEPTEMBER, 25, 2024","DESCRIPTION":"IPHONE 15 PRO MAX","DEAL LOCATION":"","INTERNAL NOTE":"","NAME OF BUYER":"MARVY FCG","EXPENSE AMOUNT":"","NAME OF SELLER":"O.Z GADGET","PRODUCT STATUS":"SOLD","STATUS OF DEVICE":"LOCKED","CALCULATED PROFIT":"","EXPENSE DESCRIPTION":"","PHONE NUMBER OF BUYER":"08138375326","AVAILABILITY/DATE SOLD":"October 26, 2024","PHONE NUMBER OF SELLER":"08106293924","RECEIPT & EVIDIENCE LINK":""} | N5: 2026-05-11T22:00:10.014056+01:00 | O5: 2026-05-11T22:00:10.014056+01:00
A6: 66863ec018eb4afcaa4f3d1c0dd63c8c | B6: 66863ec018eb4afcaa4f3d1c0dd63c8c | C6: 62d23667755195e63b5d5234f30938f95904ff364f3992fe99461567ff17b30e | D6: 8 | E6: 357343096709841 | F6: AZIMUTHAL | G6: SOLD | J6: 0 | L6: 0 | M6: {"S/N":"5","IMEI":"357343096709841","TIME":"","COLOUR":"BLUE","DEVICE":"IPHONE","STORAGE":"64GB","Column 17":"","Column 24":"","Column 25":"","Column 26":"","Column 27":"","Column 28":"","Column 29":"","Column 30":"","Column 31":"","Column 36":"","Column 37":"","Column 38":"","Column 39":"","Column 40":"","Column 41":"","Column 42":"","Column 43":"","Column 44":"","Column 45":"","Column 46":"","Column 47":"","PAID DATE":"","RECORD_ID":"66863ec018eb4afcaa4f3d1c0dd63c8c","BATTERY. H":"86","CONDITIONS":"NONE","COST PRICE":"","DATE BOUGHT":"OCTOBER, 9, 2024","DESCRIPTION":"IPHONE XR ","DEAL LOCATION":"","INTERNAL NOTE":"","NAME OF BUYER":"AZIMUTHAL","EXPENSE AMOUNT":"","NAME OF SELLER":"COWBELL","PRODUCT STATUS":"SOLD","STATUS OF DEVICE":"UNLOCKED","CALCULATED PROFIT":"","EXPENSE DESCRIPTION":"","PHONE NUMBER OF BUYER":"08135659717","AVAILABILITY/DATE SOLD":"OCTOBER, 9, 2024","PHONE NUMBER OF SELLER":"08027964718","RECEIPT & EVIDIENCE LINK":""} | N6: 2026-05-11T22:00:10.014056+01:00 | O6: 2026-05-11T22:00:10.014056+01:00
A7: a7c86fc0132e49188954358ad06be091 | B7: a7c86fc0132e49188954358ad06be091 | C7: 914a6f96c95e55f4d90856c90dcc818e71f98e5910ac6810cd4f5586f1f5e81e | D7: 9 | E7: 355591190747054 | F7: AYOMIDE FROM KING | G7: SOLD | J7: 0 | L7: 0 | M7: {"S/N":"6","IMEI":"355591190747054","TIME":"","COLOUR":"PACIFIC BLUE","DEVICE":"IPHONE","STORAGE":"128GB","Column 17":"","Column 24":"","Column 25":"","Column 26":"","Column 27":"","Column 28":"","Column 29":"","Column 30":"","Column 31":"","Column 36":"","Column 37":"","Column 38":"","Column 39":"","Column 40":"","Column 41":"","Column 42":"","Column 43":"","Column 44":"","Column 45":"","Column 46":"","Column 47":"","PAID DATE":"","RECORD_ID":"a7c86fc0132e49188954358ad06be091","BATTERY. H":"89","CONDITIONS":"NONE","COST PRICE":"","DATE BOUGHT":"SEPTEMBER, 5, 2024","DESCRIPTION":"IPHONE 12 PRO MAX","DEAL LOCATION":"","INTERNAL NOTE":"","NAME OF BUYER":"AYOMIDE FROM KING","EXPENSE AMOUNT":"","NAME OF SELLER":"HAYKINZ TECH","PRODUCT STATUS":"SOLD","STATUS OF DEVICE":"LOCKED","CALCULATED PROFIT":"","EXPENSE DESCRIPTION":"","PHONE NUMBER OF BUYER":"07036545521","AVAILABILITY/DATE SOLD":"OCTOBER, 25, 2024","PHONE NUMBER OF SELLER":"07030279101","RECEIPT & EVIDIENCE LINK":""} | N7: 2026-05-11T22:00:10.014056+01:00 | O7: 2026-05-11T22:00:10.014056+01:00
A8: 0b280c8acbac4c488c0d68ea13e375b9 | B8: 0b280c8acbac4c488c0d68ea13e375b9 | C8: d514a45e827bc32624e7f37fd801279408187400d9d64b3dbb8657d62a7f01ba | D8: 10 | E8: 358614725800789 | F8: CLARK TMOBILE | G8: SOLD | J8: 0 | L8: 0 | M8: {"S/N":"7","IMEI":"358614725800789","TIME":"","COLOUR":"YELLOW","DEVICE":"IPHONE","STORAGE":"128GB","Column 17":"","Column 24":"","Column 25":"","Column 26":"","Column 27":"","Column 28":"","Column 29":"","Column 30":"","Column 31":"","Column 36":"","Column 37":"","Column 38":"","Column 39":"","Column 40":"","Column 41":"","Column 42":"","Column 43":"","Column 44":"","Column 45":"","Column 46":"","Column 47":"","PAID DATE":"","RECORD_ID":"0b280c8acbac4c488c0d68ea13e375b9","BATTERY. H":"100","CONDITIONS":"NONE","COST PRICE":"","DATE BOUGHT":"OCTOBER, 9, 2024","DESCRIPTION":"IPHONE 15","DEAL LOCATION":"","INTERNAL NOTE":"","NAME OF BUYER":"CLARK TMOBILE","EXPENSE AMOUNT":"","NAME OF SELLER":"STAR BOX","PRODUCT STATUS":"SOLD","STATUS OF DEVICE":"LOCKED/INACTIVE (THEN UNLOCKED)","CALCULATED PROFIT":"","EXPENSE DESCRIPTION":"","PHONE NUMBER OF BUYER":"07064459910","AVAILABILITY/DATE SOLD":"OCTOBER, 9, 2024","PHONE NUMBER OF SELLER":"09063620334","RECEIPT & EVIDIENCE LINK":""} | N8: 2026-05-11T22:00:10.014056+01:00 | O8: 2026-05-11T22:00:10.014056+01:00
A9: 1fd8108519d94ba4ab573f6929f093e1 | B9: 1fd8108519d94ba4ab573f6929f093e1 | C9: 776c74d1412901845cd096bbc3fd3bd345fc84d89855d51676b4b61b17ed922d | D9: 11 | E9: 356028100922757 | F9: AZIMUTHAL | G9: SOLD | J9: 0 | L9: 0 | M9: {"S/N":"8","IMEI":"356028100922757","TIME":"","COLOUR":"BLUE","DEVICE":"SAMSUNG ","STORAGE":"8/128G","Column 17":"","Column 24":"","Column 25":"","Column 26":"","Column 27":"","Column 28":"","Column 29":"","Column 30":"","Column 31":"","Column 36":"","Column 37":"","Column 38":"","Column 39":"","Column 40":"","Column 41":"","Column 42":"","Column 43":"","Column 44":"","Column 45":"","Column 46":"","Column 47":"","PAID DATE":"","RECORD_ID":"1fd8108519d94ba4ab573f6929f093e1","BATTERY. H":"-","CONDITIONS":"NONE","COST PRICE":"","DATE BOUGHT":"OCTOBER, 5, 2024","DESCRIPTION":"SAMSUNG GALAXY S10","DEAL LOCATION":"","INTERNAL NOTE":"","NAME OF BUYER":"AZIMUTHAL","EXPENSE AMOUNT":"","NAME OF SELLER":"DENIS4WARD TECHNOLOGY ","PRODUCT STATUS":"SOLD","STATUS OF DEVICE":"UNLOCKED","CALCULATED PROFIT":"","EXPENSE DESCRIPTION":"","PHONE NUMBER OF BUYER":"08135659717","AVAILABILITY/DATE SOLD":"OCTOBER, 9, 2024","PHONE NUMBER OF SELLER":"08038551439","RECEIPT & EVIDIENCE LINK":""} | N9: 2026-05-11T22:00:10.014056+01:00 | O9: 2026-05-11T22:00:10.014056+01:00
A10: 4e9da763a2e2438a88fed668796c4ca4 | B10: 4e9da763a2e2438a88fed668796c4ca4 | C10: ab85df81f1e5166a4ddb7d6ff8c3f908a979e585842eb959c7e6ee5d4693c9ca | D10: 12 | E10: 356611841620473 | F10: STARBOX | G10: SOLD | J10: 0 | L10: 0 | M10: {"S/N":"9","IMEI":"356611841620473","TIME":"","COLOUR":"NATURAL TITANIUM","DEVICE":"IPHONE","STORAGE":"128GB","Column 17":"","Column 24":"","Column 25":"","Column 26":"","Column 27":"","Column 28":"","Column 29":"","Column 30":"","Column 31":"","Column 36":"","Column 37":"","Column 38":"","Column 39":"","Column 40":"","Column 41":"","Column 42":"","Column 43":"","Column 44":"","Column 45":"","Column 46":"","Column 47":"","PAID DATE":"","RECORD_ID":"4e9da763a2e2438a88fed668796c4ca4","BATTERY. H":"100","CONDITIONS":"NONE","COST PRICE":"","DATE BOUGHT":"OCTOBER, 11, 2024","DESCRIPTION":"IPHONE 15 PRO","DEAL LOCATION":"","INTERNAL NOTE":"","NAME OF BUYER":"STARBOX","EXPENSE AMOUNT":"","NAME OF SELLER":"DENIS IPHONE CART","PRODUCT STATUS":"SOLD","STATUS OF DEVICE":"LOCKED","CALCULATED PROFIT":"","EXPENSE DESCRIPTION":"","PHONE NUMBER OF BUYER":"09063620334","AVAILABILITY/DATE SOLD":"OCTOBER, 29, 2024","PHONE NUMBER OF SELLER":"07019540544","RECEIPT & EVIDIENCE LINK":""} | N10: 2026-05-11T22:00:10.014056+01:00 | O10: 2026-05-11T22:00:10.014056+01:00
A11: 3da6080066fd4c92b3d68a4eb2d3352e | B11: 3da6080066fd4c92b3d68a4eb2d3352e | C11: 0d7902f183f31b329c93ba8901cc54f3ae20ecc58a158b541d0d9d8010168fff | D11: 13 | E11: C02CQ657ML7H | G11: SOLD | J11: 0 | L11: 0 | M11: {"S/N":"10","IMEI":"C02CQ657ML7H","TIME":"","COLOUR":"SILVER","DEVICE":"MACBOOK","STORAGE":"16/512GB","Column 17":"","Column 24":"","Column 25":"","Column 26":"","Column 27":"","Column 28":"","Column 29":"","Column 30":"","Column 31":"","Column 36":"","Column 37":"","Column 38":"","Column 39":"","Column 40":"","Column 41":"","Column 42":"","Column 43":"","Column 44":"","Column 45":"","Column 46":"","Column 47":"","PAID DATE":"","RECORD_ID":"3da6080066fd4c92b3d68a4eb2d3352e","BATTERY. H":"192 cc","CONDITIONS":"NONE","COST PRICE":"","DATE BOUGHT":"OCTOBER, 11, 2024","DESCRIPTION":"MACBOOK PRO 2020","DEAL LOCATION":"","INTERNAL NOTE":"","NAME OF BUYER":"","EXPENSE AMOUNT":"","NAME OF SELLER":"GADGET AND EXCHANGE","PRODUCT STATUS":"SOLD","STATUS OF DEVICE":"UNLOCKED (NO FMI)","CALCULATED PROFIT":"","EXPENSE DESCRIPTION":"","PHONE NUMBER OF BUYER":"","AVAILABILITY/DATE SOLD":"","PHONE NUMBER OF SELLER":"08142246838","RECEIPT & EVIDIENCE LINK":""} | N11: 2026-05-11T22:00:10.014056+01:00 | O11: 2026-05-11T22:00:10.014056+01:00
A12: 7b37f8c77cba4eeeb6a371dc23875e9b | B12: 7b37f8c77cba4eeeb6a371dc23875e9b | C12: 4d3fd4677d4701cf5f6e764b52627b3caf855eff4900ce886c2ca8b3ba2f0982 | D12: 14 | E12: 358835961632491/17 | F12: GEORGE | G12: SOLD | J12: 0 | L12: 0 | M12: {"S/N":"11","IMEI":"358835961632491/17","TIME":"","COLOUR":"BLACK","DEVICE":"SAMSUNG ","STORAGE":"12/512GB","Column 17":"","Column 24":"","Column 25":"","Column 26":"","Column 27":"","Column 28":"","Column 29":"","Column 30":"","Column 31":"","Column 36":"","Column 37":"","Column 38":"","Column 39":"","Column 40":"","Column 41":"","Column 42":"","Column 43":"","Column 44":"","Column 45":"","Column 46":"","Column 47":"","PAID DATE":"","RECORD_ID":"7b37f8c77cba4eeeb6a371dc23875e9b","BATTERY. H":"100","CONDITIONS":"NONE","COST PRICE":"","DATE BOUGHT":"AUGUST, 5, 2024","DESCRIPTION":"SAMSUNG GALAXY S23 ULTRA","DEAL LOCATION":"","INTERNAL NOTE":"","NAME OF BUYER":"GEORGE","EXPENSE AMOUNT":"","NAME OF SELLER":"DAMBOX GADGETS","PRODUCT STATUS":"SOLD","STATUS OF DEVICE":"UNLOCKED","CALCULATED PROFIT":"","EXPENSE DESCRIPTION":"","PHONE NUMBER OF BUYER":"08168364881","AVAILABILITY/DATE SOLD":"12/7/2024","PHONE NUMBER OF SELLER":"09040943517","RECEIPT & EVIDIENCE LINK":""} | N12: 2026-05-11T22:00:10.014056+01:00 | O12: 2026-05-11T22:00:10.014056+01:00
A13: d9b909f7d5084ca7a454f266ee9ce09b | B13: d9b909f7d5084ca7a454f266ee9ce09b | C13: 695e7926165babe9e52ddbb29a13846a34fbc68d92f96948ad996aed324a8b89 | D13: 15 | E13: 356370160169592 | F13: NURUDEEN | G13: SOLD | J13: 0 | L13: 0 | M13: {"S/N":"12","IMEI":"356370160169592","TIME":"","COLOUR":"SIERRA BLUE","DEVICE":"IPHONE","STORAGE":"128GB","Column 17":"","Column 24":"","Column 25":"","Column 26":"","Column 27":"","Column 28":"","Column 29":"","Column 30":"","Column 31":"","Column 36":"","Column 37":"","Column 38":"","Column 39":"","Column 40":"","Column 41":"","Column 42":"","Column 43":"","Column 44":"","Column 45":"","Column 46":"","Column 47":"","PAID DATE":"","RECORD_ID":"d9b909f7d5084ca7a454f266ee9ce09b","BATTERY. H":"93","CONDITIONS":"NONE","COST PRICE":"","DATE BOUGHT":"AUGUST, 31, 2024","DESCRIPTION":"IPHONE 13 PRO MAX","DEAL LOCATION":"","INTERNAL NOTE":"","NAME OF BUYER":"NURUDEEN","EXPENSE AMOUNT":"","NAME OF SELLER":"NURUDEEN","PRODUCT STATUS":"SOLD","STATUS OF DEVICE":"LOCKED","CALCULATED PROFIT":"","EXPENSE DESCRIPTION":"","PHONE NUMBER OF BUYER":"07067426927","AVAILABILITY/DATE SOLD":"OCTOBER, 12, 2024","PHONE NUMBER OF SELLER":"07067426927","RECEIPT & EVIDIENCE LINK":""} | N13: 2026-05-11T22:00:10.014056+01:00 | O13: 2026-05-11T22:00:10.014056+01:00
A14: f2b348f4a09343e68a415a8ec8b27f21 | B14: f2b348f4a09343e68a415a8ec8b27f21 | C14: 0f05bd745789c58be669981c00606126eabe6cba7ae62badef102c3c91f902ce | D14: 16 | E14: 351048874153335 | F14: ZEE TECH | G14: SOLD | J14: 0 | L14: 0 | M14: {"S/N":"13","IMEI":"351048874153335","TIME":"","COLOUR":"MIDNIGHT","DEVICE":"IPHONE","STORAGE":"128GB","Column 17":"","Column 24":"","Column 25":"","Column 26":"","Column 27":"","Column 28":"","Column 29":"","Column 30":"","Column 31":"","Column 36":"","Column 37":"","Column 38":"","Column 39":"","Column 40":"","Column 41":"","Column 42":"","Column 43":"","Column 44":"","Column 45":"","Column 46":"","Column 47":"","PAID DATE":"","RECORD_ID":"f2b348f4a09343e68a415a8ec8b27f21","BATTERY. H":"98","CONDITIONS":"NONE","COST PRICE":"","DATE BOUGHT":"OCTOBER, 12, 2024","DESCRIPTION":"IPHONE 15","DEAL LOCATION":"","INTERNAL NOTE":"","NAME OF BUYER":"ZEE TECH","EXPENSE AMOUNT":"","NAME OF SELLER":"IYANUOLUWA (WHYTE)","PRODUCT STATUS":"SOLD","STATUS OF DEVICE":"LOCKED","CALCULATED PROFIT":"","EXPENSE DESCRIPTION":"","PHONE NUMBER OF BUYER":"09033724061","AVAILABILITY/DATE SOLD":"OCTOBER, 12, 2024","PHONE NUMBER OF SELLER":"08088480573","RECEIPT & EVIDIENCE LINK":""} | N14: 2026-05-11T22:00:10.014056+01:00 | O14: 2026-05-11T22:00:10.014056+01:00
A15: 7c4f6b6c5d884933af704e01adf21dfd | B15: 7c4f6b6c5d884933af704e01adf21dfd | C15: 5c32a8a5122cd94b2733d5dea5538d6753094f7d33502e204b6d34e8b049392b | D15: 17 | E15: 3555609473866646 | F15: OZ GADGET | G15: SOLD | J15: 0 | L15: 0 | M15: {"S/N":"14","IMEI":"3555609473866646","TIME":"","COLOUR":"GOLD","DEVICE":"IPHONE","STORAGE":"256GB","Column 17":"","Column 24":"","Column 25":"","Column 26":"","Column 27":"","Column 28":"","Column 29":"","Column 30":"","Column 31":"","Column 36":"","Column 37":"","Column 38":"","Column 39":"","Column 40":"","Column 41":"","Column 42":"","Column 43":"","Column 44":"","Column 45":"","Column 46":"","Column 47":"","PAID DATE":"","RECORD_ID":"7c4f6b6c5d884933af704e01adf21dfd","BATTERY. H":"87","CONDITIONS":"NONE","COST PRICE":"","DATE BOUGHT":"OCTOBER 14, 2024","DESCRIPTION":"IPHONE 14 PRO MAX ","DEAL LOCATION":"","INTERNAL NOTE":"","NAME OF BUYER":"OZ GADGET","EXPENSE AMOUNT":"","NAME OF SELLER":"MOBILETRENDS LTD","PRODUCT STATUS":"SOLD","STATUS OF DEVICE":"LOCKED (THEN UNLOCKED)","CALCULATED PROFIT":"","EXPENSE DESCRIPTION":"","PHONE NUMBER OF BUYER":"08106293924","AVAILABILITY/DATE SOLD":"OCTOBERR, 16, 2024","PHONE NUMBER OF SELLER":"08034378180","RECEIPT & EVIDIENCE LINK":""} | N15: 2026-05-11T22:00:10.014056+01:00 | O15: 2026-05-11T22:00:10.014056+01:00
A16: a63214b0adaa4d1799c3214ba977256c | B16: a63214b0adaa4d1799c3214ba977256c | C16: 227e4e61b0d6e7b42078e1051bb5ca912273da40c82d856edec44c453e70bf2e | D16: 18 | E16: 353342884127308 | F16: PHLEMZY | G16: SOLD | J16: 0 | L16: 0 | M16: {"S/N":"15","IMEI":"353342884127308","TIME":"","COLOUR":"PURPLE","DEVICE":"IPHONE","STORAGE":"64GB","Column 17":"","Column 24":"","Column 25":"","Column 26":"","Column 27":"","Column 28":"","Column 29":"","Column 30":"","Column 31":"","Column 36":"","Column 37":"","Column 38":"","Column 39":"","Column 40":"","Column 41":"","Column 42":"","Column 43":"","Column 44":"","Column 45":"","Column 46":"","Column 47":"","PAID DATE":"","RECORD_ID":"a63214b0adaa4d1799c3214ba977256c","BATTERY. H":"87","CONDITIONS":"NONE","COST PRICE":"","DATE BOUGHT":"AUGUST, 28, 2024","DESCRIPTION":"IPHONE 12","DEAL LOCATION":"","INTERNAL NOTE":"","NAME OF BUYER":"PHLEMZY","EXPENSE AMOUNT":"","NAME OF SELLER":"BROOKS","PRODUCT STATUS":"SOLD","STATUS OF DEVICE":"LOCKED (THEN UNLOCKED)","CALCULATED PROFIT":"","EXPENSE DESCRIPTION":"","PHONE NUMBER OF BUYER":"09065642565","AVAILABILITY/DATE SOLD":"OCTOBER, 14, 2024","PHONE NUMBER OF SELLER":"08136762183","RECEIPT & EVIDIENCE LINK":""} | N16: 2026-05-11T22:00:10.014056+01:00 | O16: 2026-05-11T22:00:10.014056+01:00
A17: bd88096ea70d4c45829a1fa6c83ac3e5 | B17: bd88096ea70d4c45829a1fa6c83ac3e5 | C17: 6d97d67bf0e2614e356d6391a6d6944065ea943ca74b6cdff4332e3228368d7c | D17: 19 | E17: 5CG8263RYB | F17: FM LORD | G17: SOLD | J17: 0 | L17: 0 | M17: {"S/N":"16","IMEI":"5CG8263RYB","TIME":"","COLOUR":"SILVER","DEVICE":"LAPTOP","STORAGE":"8GB + 256GB(SSD) + 7TH GEN + i5 ","Column 17":"","Column 24":"","Column 25":"","Column 26":"","Column 27":"","Column 28":"","Column 29":"","Column 30":"","Column 31":"","Column 36":"","Column 37":"","Column 38":"","Column 39":"","Column 40":"","Column 41":"","Column 42":"","Column 43":"","Column 44":"","Column 45":"","Column 46":"","Column 47":"","PAID DATE":"","RECORD_ID":"bd88096ea70d4c45829a1fa6c83ac3e5","BATTERY. H":"2CC","CONDITIONS":"NONE","COST PRICE":"","DATE BOUGHT":"OCTOBER, 17, 2024","DESCRIPTION":"HP ELITEBOOK X360 1030 G2 // TOUCH SCREEN // 2CC","DEAL LOCATION":"","INTERNAL NOTE":"","NAME OF BUYER":"FM LORD","EXPENSE AMOUNT":"","NAME OF SELLER":"DENIS4WARD TECHNOLOGY ","PRODUCT STATUS":"SOLD","STATUS OF DEVICE":"","CALCULATED PROFIT":"","EXPENSE DESCRIPTION":"","PHONE NUMBER OF BUYER":"08157806332","AVAILABILITY/DATE SOLD":"October, 17, 2024","PHONE NUMBER OF SELLER":"08038551439","RECEIPT & EVIDIENCE LINK":""} | N17: 2026-05-11T22:00:10.014056+01:00 | O17: 2026-05-11T22:00:10.014056+01:00
A18: 27712ecfa97942f588ddb6ae92a448df | B18: 27712ecfa97942f588ddb6ae92a448df | C18: 01eaec41d3d112bf7cecd2e6977d658f2db1de402b88e41539d7a54746fb3630 | D18: 20 | E18: 355185496137241 | F18: MARIAM ADEDEJI | G18: SOLD | J18: 0 | L18: 0 | M18: {"S/N":"17","IMEI":"355185496137241","TIME":"","COLOUR":"MIDNIGHT","DEVICE":"IPHONE","STORAGE":"128GB","Column 17":"","Column 24":"","Column 25":"","Column 26":"","Column 27":"","Column 28":"","Column 29":"","Column 30":"","Column 31":"","Column 36":"","Column 37":"","Column 38":"","Column 39":"","Column 40":"","Column 41":"","Column 42":"","Column 43":"","Column 44":"","Column 45":"","Column 46":"","Column 47":"","PAID DATE":"","RECORD_ID":"27712ecfa97942f588ddb6ae92a448df","BATTERY. H":"100","CONDITIONS":"NONE","COST PRICE":"","DATE BOUGHT":"OCTOBER, 17, 2024","DESCRIPTION":"IPHONE 14 ","DEAL LOCATION":"","INTERNAL NOTE":"","NAME OF BUYER":"MARIAM ADEDEJI","EXPENSE AMOUNT":"","NAME OF SELLER":"KAYWISE","PRODUCT STATUS":"SOLD","STATUS OF DEVICE":"LOCKED","CALCULATED PROFIT":"","EXPENSE DESCRIPTION":"","PHONE NUMBER OF BUYER":"09129850861","AVAILABILITY/DATE SOLD":"OCTOBER, 17, 2024","PHONE NUMBER OF SELLER":"09032611871","RECEIPT & EVIDIENCE LINK":""} | N18: 2026-05-11T22:00:10.014056+01:00 | O18: 2026-05-11T22:00:10.014056+01:00
A19: b5ab29a5c6e449e98d85812fd69da4b5 | B19: b5ab29a5c6e449e98d85812fd69da4b5 | C19: 053b6a136681aa93fb93a2c25e6ebf45f9599baba203079b0ae35e356a9f9676 | D19: 21 | E19: 354242631252863 | F19: STOP PLAYING FROM Muller | G19: SOLD | J19: 0 | L19: 0 | M19: {"S/N":"18","IMEI":"354242631252863","TIME":"","COLOUR":"BLACK TITANIUM","DEVICE":"IPHONE","STORAGE":"256GB","Column 17":"","Column 24":"","Column 25":"","Column 26":"","Column 27":"","Column 28":"","Column 29":"","Column 30":"","Column 31":"","Column 36":"","Column 37":"","Column 38":"","Column 39":"","Column 40":"","Column 41":"","Column 42":"","Column 43":"","Column 44":"","Column 45":"","Column 46":"","Column 47":"","PAID DATE":"","RECORD_ID":"b5ab29a5c6e449e98d85812fd69da4b5","BATTERY. H":"100","CONDITIONS":"NONE","COST PRICE":"","DATE BOUGHT":"OCTOBER, 17, 2024","DESCRIPTION":"IPHONE 15 PRO MAX (PHYSICAL + ESIM)","DEAL LOCATION":"","INTERNAL NOTE":"","NAME OF BUYER":"STOP PLAYING FROM Muller","EXPENSE AMOUNT":"","NAME OF SELLER":"O.Z GADGET","PRODUCT STATUS":"SOLD","STATUS OF DEVICE":"UNLOCKED","CALCULATED PROFIT":"","EXPENSE DESCRIPTION":"","PHONE NUMBER OF BUYER":"08100428708","AVAILABILITY/DATE SOLD":"OCTOBER, 17, 2024","PHONE NUMBER OF SELLER":"08106293924","RECEIPT & EVIDIENCE LINK":""} | N19: 2026-05-11T22:00:10.014056+01:00 | O19: 2026-05-11T22:00:10.014056+01:00
A20: 6f31a787d1c84b538703747615d2ceb6 | B20: 6f31a787d1c84b538703747615d2ceb6 | C20: a4ecff8323d80e61414658f1c1285b4bcab859338e24a656f50052223c5a778a | D20: 22 | E20: 353303090689978 | F20: KHAFE GADGET | G20: SOLD | J20: 0 | L20: 0 | M20: {"S/N":"19","IMEI":"353303090689978","TIME":"","COLOUR":"LILAC","DEVICE":"SAMSUNG","STORAGE":"8/64GB","Column 17":"","Column 24":"","Column 25":"","Column 26":"","Column 27":"","Column 28":"","Column 29":"","Column 30":"","Column 31":"","Column 36":"","Column 37":"","Column 38":"","Column 39":"","Column 40":"","Column 41":"","Column 42":"","Column 43":"","Column 44":"","Column 45":"","Column 46":"","Column 47":"","PAID DATE":"","RECORD_ID":"6f31a787d1c84b538703747615d2ceb6","BATTERY. H":"-","CONDITIONS":"NONE","COST PRICE":"","DATE BOUGHT":"OCTOBER, 17, 2024","DESCRIPTION":"SAMSUNG GALAXY S9","DEAL LOCATION":"","INTERNAL NOTE":"","NAME OF BUYER":"KHAFE GADGET","EXPENSE AMOUNT":"","NAME OF SELLER":"LOVE STORE","PRODUCT STATUS":"SOLD","STATUS OF DEVICE":"UNLOCKED","CALCULATED PROFIT":"","EXPENSE DESCRIPTION":"","PHONE NUMBER OF BUYER":"07048121888","AVAILABILITY/DATE SOLD":"OCTOBER, 25, 2024","PHONE NUMBER OF SELLER":"09169140149","RECEIPT & EVIDIENCE LINK":""} | N20: 2026-05-11T22:00:10.014056+01:00 | O20: 2026-05-11T22:00:10.014056+01:00
A21: 9c6dff5ba86c460dbe3006034398ef34 | B21: 9c6dff5ba86c460dbe3006034398ef34 | C21: 3c3066b5dd80434c5999d397454eaa35994edc12fde13227c2ff5b536709853e | D21: 23 | E21: 5CG9459DK7 | F21: FM LORD | G21: SOLD | J21: 0 | L21: 0 | M21: {"S/N":"20","IMEI":"5CG9459DK7","TIME":"","COLOUR":"SILVER","DEVICE":"IPHONE","STORAGE":"8GB + 256GB(SSD) + 7TH GEN + i5 ","Column 17":"","Column 24":"","Column 25":"","Column 26":"","Column 27":"","Column 28":"","Column 29":"","Column 30":"","Column 31":"","Column 36":"","Column 37":"","Column 38":"","Column 39":"","Column 40":"","Column 41":"","Column 42":"","Column 43":"","Column 44":"","Column 45":"","Column 46":"","Column 47":"","PAID DATE":"","RECORD_ID":"9c6dff5ba86c460dbe3006034398ef34","BATTERY. H":"25CC","CONDITIONS":"NONE","COST PRICE":"","DATE BOUGHT":"OCTOBER 19, 2024","DESCRIPTION":"HP ELITEBOOK X360 1030 G2 // TOUCH SCREEN // 25CC","DEAL LOCATION":"","INTERNAL NOTE":"","NAME OF BUYER":"FM LORD","EXPENSE AMOUNT":"","NAME OF SELLER":"SEYI HYPO","PRODUCT STATUS":"SOLD","STATUS OF DEVICE":"-","CALCULATED PROFIT":"","EXPENSE DESCRIPTION":"","PHONE NUMBER OF BUYER":"08157806332","AVAILABILITY/DATE SOLD":"OCTOBER, 22, 2024","PHONE NUMBER OF SELLER":"08149133935","RECEIPT & EVIDIENCE LINK":""} | N21: 2026-05-11T22:00:10.014056+01:00 | O21: 2026-05-11T22:00:10.014056+01:00
A22: b66154cbd4bb4b8483e30393c1a86b25 | B22: b66154cbd4bb4b8483e30393c1a86b25 | C22: fa916da081c9d081332ddbb66042405f88448713c97d3628a22f306f1061a419 | D22: 24 | E22: 353629306995779 | F22: ZEE TECH | G22: SOLD | J22: 0 | L22: 0 | M22: {"S/N":"21","IMEI":"353629306995779","TIME":"","COLOUR":"NATURAL TITANIUM","DEVICE":"IPHONE","STORAGE":"128GB","Column 17":"","Column 24":"","Column 25":"","Column 26":"","Column 27":"","Column 28":"","Column 29":"","Column 30":"","Column 31":"","Column 36":"","Column 37":"","Column 38":"","Column 39":"","Column 40":"","Column 41":"","Column 42":"","Column 43":"","Column 44":"","Column 45":"","Column 46":"","Column 47":"","PAID DATE":"","RECORD_ID":"b66154cbd4bb4b8483e30393c1a86b25","BATTERY. H":"76(96)","CONDITIONS":"NONE","COST PRICE":"","DATE BOUGHT":"OCTOBER, 22, 2024","DESCRIPTION":"PHYSICAL SIM IPHONE 15 PRO ","DEAL LOCATION":"","INTERNAL NOTE":"","NAME OF BUYER":"ZEE TECH","EXPENSE AMOUNT":"","NAME OF SELLER":"SEBASTINE","PRODUCT STATUS":"SOLD","STATUS OF DEVICE":"UNLOCKED","CALCULATED PROFIT":"","EXPENSE DESCRIPTION":"","PHONE NUMBER OF BUYER":"09033724061","AVAILABILITY/DATE SOLD":"OCTOBER, 25, 2024","PHONE NUMBER OF SELLER":"07032069012","RECEIPT & EVIDIENCE LINK":""} | N22: 2026-05-11T22:00:10.014056+01:00 | O22: 2026-05-11T22:00:10.014056+01:00
A23: 2a06cb692cf64aed9b8c10f82c8b91ce | B23: 2a06cb692cf64aed9b8c10f82c8b91ce | C23: d4f72ea8c338a3cbbefe70b040c8d4662ca845f9c410cbfe446756c645b9304b | D23: 25 | E23: 353629303850753 | F23: NURUDEEN | G23: SOLD | J23: 0 | L23: 0 | M23: {"S/N":"22","IMEI":"353629303850753","TIME":"","COLOUR":"BLUE TITANIUM","DEVICE":"IPHONE","STORAGE":"128GB","Column 17":"","Column 24":"","Column 25":"","Column 26":"","Column 27":"","Column 28":"","Column 29":"","Column 30":"","Column 31":"","Column 36":"","Column 37":"","Column 38":"","Column 39":"","Column 40":"","Column 41":"","Column 42":"","Column 43":"","Column 44":"","Column 45":"","Column 46":"","Column 47":"","PAID DATE":"","RECORD_ID":"2a06cb692cf64aed9b8c10f82c8b91ce","BATTERY. H":"100 (10CC)","CONDITIONS":"NONE","COST PRICE":"","DATE BOUGHT":"OCTOBER, 22, 2024","DESCRIPTION":"IPHONE 15 PRO","DEAL LOCATION":"","INTERNAL NOTE":"","NAME OF BUYER":"NURUDEEN","EXPENSE AMOUNT":"","NAME OF SELLER":"DEMIGLOBAL MULTISERVICE","PRODUCT STATUS":"SOLD","STATUS OF DEVICE":"LOCKED","CALCULATED PROFIT":"","EXPENSE DESCRIPTION":"","PHONE NUMBER OF BUYER":"07067426927","AVAILABILITY/DATE SOLD":"OCTOBER, 26, 2024","PHONE NUMBER OF SELLER":"09066720385","RECEIPT & EVIDIENCE LINK":""} | N23: 2026-05-11T22:00:10.014056+01:00 | O23: 2026-05-11T22:00:10.014056+01:00
A24: 7056142f696849f4be32c48b948bcd7d | B24: 7056142f696849f4be32c48b948bcd7d | C24: 92b795ed3080dab9373046b5930b9587bcb0238e006d89122c6f499e365fecf1 | D24: 26 | E24: 350686386107454 | F24: DENIS4WARD TECHNOLOGY | G24: SOLD | J24: 0 | L24: 0 | M24: {"S/N":"23","IMEI":"350686386107454","TIME":"","COLOUR":"BLACK TITANIUM","DEVICE":"IPHONE","STORAGE":"128GB","Column 17":"","Column 24":"","Column 25":"","Column 26":"","Column 27":"","Column 28":"","Column 29":"","Column 30":"","Column 31":"","Column 36":"","Column 37":"","Column 38":"","Column 39":"","Column 40":"","Column 41":"","Column 42":"","Column 43":"","Column 44":"","Column 45":"","Column 46":"","Column 47":"","PAID DATE":"","RECORD_ID":"7056142f696849f4be32c48b948bcd7d","BATTERY. H":"100","CONDITIONS":"NONE","COST PRICE":"","DATE BOUGHT":"OCTOBER, 22, 2025","DESCRIPTION":"IPHONE 15 PLUS","DEAL LOCATION":"","INTERNAL NOTE":"","NAME OF BUYER":"DENIS4WARD TECHNOLOGY","EXPENSE AMOUNT":"","NAME OF SELLER":"SAMUEL. TBERNIES","PRODUCT STATUS":"SOLD","STATUS OF DEVICE":"LOCKED","CALCULATED PROFIT":"","EXPENSE DESCRIPTION":"","PHONE NUMBER OF BUYER":"08038551439","AVAILABILITY/DATE SOLD":"OCTOBER, 28, 2024","PHONE NUMBER OF SELLER":"08157806332","RECEIPT & EVIDIENCE LINK":""} | N24: 2026-05-11T22:00:10.014056+01:00 | O24: 2026-05-11T22:00:10.014056+01:00
A25: 7aaf1228897c43c487ea4e41805efc43 | B25: 7aaf1228897c43c487ea4e41805efc43 | C25: 5c50bce5970f2e70806bf077d4897dd92e9a07e89e791ca2446cd005ced3543d | D25: 27 | E25: 352851114282700 | F25: FAME GADGET | G25: SOLD | J25: 0 | L25: 0 | M25: {"S/N":"24","IMEI":"352851114282700","TIME":"","COLOUR":"GOLD","DEVICE":"IPHONE","STORAGE":"256GB","Column 17":"","Column 24":"","Column 25":"","Column 26":"","Column 27":"","Column 28":"","Column 29":"","Column 30":"","Column 31":"","Column 36":"","Column 37":"","Column 38":"","Column 39":"","Column 40":"","Column 41":"","Column 42":"","Column 43":"","Column 44":"","Column 45":"","Column 46":"","Column 47":"","PAID DATE":"","RECORD_ID":"7aaf1228897c43c487ea4e41805efc43","BATTERY. H":"73(92)","CONDITIONS":"NONE","COST PRICE":"","DATE BOUGHT":"OCTOBER, 25, 2024","DESCRIPTION":"IPHONE 11 PRO MAX ","DEAL LOCATION":"","INTERNAL NOTE":"","NAME OF BUYER":"FAME GADGET","EXPENSE AMOUNT":"","NAME OF SELLER":"DAMILOLA ADEFUNKE","PRODUCT STATUS":"SOLD","STATUS OF DEVICE":"LOCKED (THEN UNLOCKED)","CALCULATED PROFIT":"","EXPENSE DESCRIPTION":"","PHONE NUMBER OF BUYER":"08144970435","AVAILABILITY/DATE SOLD":"OCTOBER, 28, 2024","PHONE NUMBER OF SELLER":"07036545521","RECEIPT & EVIDIENCE LINK":""} | N25: 2026-05-11T22:00:10.014056+01:00 | O25: 2026-05-11T22:00:10.014056+01:00
A26: dfcd6b7ae48742f6a29a94066198460a | B26: dfcd6b7ae48742f6a29a94066198460a | C26: af83f2de81854b8fc3dc50c00b86796b7e78748a092843fb0fdeeb543ed38076 | D26: 28 | E26: 357275795496378 | F26: OFFICIALYUNG | G26: SOLD | J26: 0 | L26: 0 | M26: {"S/N":"25","IMEI":"357275795496378","TIME":"","COLOUR":"BLUE TITANIUM","DEVICE":"IPHONE","STORAGE":"256GB","Column 17":"","Column 24":"","Column 25":"","Column 26":"","Column 27":"","Column 28":"","Column 29":"","Column 30":"","Column 31":"","Column 36":"","Column 37":"","Column 38":"","Column 39":"","Column 40":"","Column 41":"","Column 42":"","Column 43":"","Column 44":"","Column 45":"","Column 46":"","Column 47":"","PAID DATE":"","RECORD_ID":"dfcd6b7ae48742f6a29a94066198460a","BATTERY. H":"100","CONDITIONS":"NONE","COST PRICE":"","DATE BOUGHT":"OCTOBER, 28, 2024","DESCRIPTION":"IPHONE 15 PRO MAX eSIM (104cc)","DEAL LOCATION":"","INTERNAL NOTE":"","NAME OF BUYER":"OFFICIALYUNG","EXPENSE AMOUNT":"","NAME OF SELLER":"ZEE TECH","PRODUCT STATUS":"SOLD","STATUS OF DEVICE":"LOCKED(THEN UNLOCKED)","CALCULATED PROFIT":"","EXPENSE DESCRIPTION":"","PHONE NUMBER OF BUYER":"07083395113","AVAILABILITY/DATE SOLD":"NOVEMBER, 02, 2024","PHONE NUMBER OF SELLER":"09033724061","RECEIPT & EVIDIENCE LINK":""} | N26: 2026-05-11T22:00:10.014056+01:00 | O26: 2026-05-11T22:00:10.014056+01:00
A27: 86e1b0b7b94c4bacb0e7f18ae9ecb1f0 | B27: 86e1b0b7b94c4bacb0e7f18ae9ecb1f0 | C27: 5e92a74d98e0467666f5f1ea86b820eb4ebd11fcaf2b5c91f3a01e63936d8f91 | D27: 29 | E27: 351698478562347 | F27: IPRO GADGET | G27: SOLD | J27: 0 | L27: 0 | M27: {"S/N":"26","IMEI":"351698478562347","TIME":"","COLOUR":"PINK","DEVICE":"IPHONE","STORAGE":"128GB","Column 17":"","Column 24":"","Column 25":"","Column 26":"","Column 27":"","Column 28":"","Column 29":"","Column 30":"","Column 31":"","Column 36":"","Column 37":"","Column 38":"","Column 39":"","Column 40":"","Column 41":"","Column 42":"","Column 43":"","Column 44":"","Column 45":"","Column 46":"","Column 47":"","PAID DATE":"","RECORD_ID":"86e1b0b7b94c4bacb0e7f18ae9ecb1f0","BATTERY. H":"100","CONDITIONS":"NONE","COST PRICE":"","DATE BOUGHT":"OCTOBER, 30, 2024","DESCRIPTION":"IPHONE 15 ","DEAL LOCATION":"","INTERNAL NOTE":"","NAME OF BUYER":"IPRO GADGET","EXPENSE AMOUNT":"","NAME OF SELLER":"AYANFE","PRODUCT STATUS":"SOLD","STATUS OF DEVICE":"LOCKED (UNLOCKED)","CALCULATED PROFIT":"","EXPENSE DESCRIPTION":"","PHONE NUMBER OF BUYER":"08109344663","AVAILABILITY/DATE SOLD":"","PHONE NUMBER OF SELLER":"08138108648","RECEIPT & EVIDIENCE LINK":""} | N27: 2026-05-11T22:00:10.014056+01:00 | O27: 2026-05-11T22:00:10.014056+01:00
A28: d35e393cbd73432281c20c5cac08cc3f | B28: d35e393cbd73432281c20c5cac08cc3f | C28: f7d5234b95e8c48106bfa1a551f6d0dab60e915f8edc19ebd865d657ebdee3b6 | D28: 30 | E28: 356028100922757 | F28: SCOTT STORE | G28: SOLD | J28: 0 | L28: 0 | M28: {"S/N":"27","IMEI":"356028100922757","TIME":"","COLOUR":"BLUE","DEVICE":"SAMSUNG","STORAGE":"128GB","Column 17":"","Column 24":"","Column 25":"","Column 26":"","Column 27":"","Column 28":"","Column 29":"","Column 30":"","Column 31":"","Column 36":"","Column 37":"","Column 38":"","Column 39":"","Column 40":"","Column 41":"","Column 42":"","Column 43":"","Column 44":"","Column 45":"","Column 46":"","Column 47":"","PAID DATE":"","RECORD_ID":"d35e393cbd73432281c20c5cac08cc3f","BATTERY. H":"-","CONDITIONS":"NONE","COST PRICE":"","DATE BOUGHT":"11/04/2024","DESCRIPTION":"SAMSUNG GALAXY S10","DEAL LOCATION":"","INTERNAL NOTE":"","NAME OF BUYER":"SCOTT STORE","EXPENSE AMOUNT":"","NAME OF SELLER":"AZIMUTHAL","PRODUCT STATUS":"SOLD","STATUS OF DEVICE":"UNLOCKED","CALCULATED PROFIT":"","EXPENSE DESCRIPTION":"","PHONE NUMBER OF BUYER":"09161940149","AVAILABILITY/DATE SOLD":"NOVEMBER, 05, 2024","PHONE NUMBER OF SELLER":"08135659717","RECEIPT & EVIDIENCE LINK":""} | N28: 2026-05-11T22:00:10.014056+01:00 | O28: 2026-05-11T22:00:10.014056+01:00
A29: 20417ee2bbfb4429bd619245524b031e | B29: 20417ee2bbfb4429bd619245524b031e | C29: ed9083e8b84d4fa0db325f30f9bfce24e87944499b033165fe7f2e4a2c0d1066 | D29: 31 | E29: 357330100397389 | F29: NURUDEEN | G29: SOLD | J29: 0 | L29: 0 | M29: {"S/N":"28","IMEI":"357330100397389","TIME":"","COLOUR":"BLUE","DEVICE":"SAMSUNG","STORAGE":"128GB","Column 17":"","Column 24":"","Column 25":"","Column 26":"","Column 27":"","Column 28":"","Column 29":"","Column 30":"","Column 31":"","Column 36":"","Column 37":"","Column 38":"","Column 39":"","Column 40":"","Column 41":"","Column 42":"","Column 43":"","Column 44":"","Column 45":"","Column 46":"","Column 47":"","PAID DATE":"","RECORD_ID":"20417ee2bbfb4429bd619245524b031e","BATTERY. H":"-","CONDITIONS":"NONE","COST PRICE":"","DATE BOUGHT":"11/05/2024","DESCRIPTION":"SAMSUNG GALAXY S10 PLUS","DEAL LOCATION":"","INTERNAL NOTE":"","NAME OF BUYER":"NURUDEEN","EXPENSE AMOUNT":"","NAME OF SELLER":"FM LORD","PRODUCT STATUS":"SOLD","STATUS OF DEVICE":"UNLOCKED","CALCULATED PROFIT":"","EXPENSE DESCRIPTION":"","PHONE NUMBER OF BUYER":"07067426927","AVAILABILITY/DATE SOLD":"NOVEMBER, 08, 2024","PHONE NUMBER OF SELLER":"08157806332","RECEIPT & EVIDIENCE LINK":""} | N29: 2026-05-11T22:00:10.014056+01:00 | O29: 2026-05-11T22:00:10.014056+01:00
A30: 5cb1975f141841a18602fcdc4496dc9c | B30: 5cb1975f141841a18602fcdc4496dc9c | C30: fcac8d09d6c71b9198eeb9f7e77e1058851216deec6ba679cbea4a9730461b67 | D30: 32 | E30: 357343096709541 | F30: PANKYGEE | G30: SOLD | J30: 0 | L30: 0 | M30: {"S/N":"29","IMEI":"357343096709541","TIME":"","COLOUR":"BLUE","DEVICE":"IPHONE","STORAGE":"64GB","Column 17":"","Column 24":"","Column 25":"","Column 26":"","Column 27":"","Column 28":"","Column 29":"","Column 30":"","Column 31":"","Column 36":"","Column 37":"","Column 38":"","Column 39":"","Column 40":"","Column 41":"","Column 42":"","Column 43":"","Column 44":"","Column 45":"","Column 46":"","Column 47":"","PAID DATE":"","RECORD_ID":"5cb1975f141841a18602fcdc4496dc9c","BATTERY. H":"83","CONDITIONS":"NONE","COST PRICE":"","DATE BOUGHT":"11/06/2024","DESCRIPTION":"IPHONE XR","DEAL LOCATION":"","INTERNAL NOTE":"","NAME OF BUYER":"PANKYGEE","EXPENSE AMOUNT":"","NAME OF SELLER":"AZIMUTHAL","PRODUCT STATUS":"SOLD","STATUS OF DEVICE":"UNLOCKED","CALCULATED PROFIT":"","EXPENSE DESCRIPTION":"","PHONE NUMBER OF BUYER":"07052247397","AVAILABILITY/DATE SOLD":"NOVEMBER, 07, 2024","PHONE NUMBER OF SELLER":"08135659717","RECEIPT & EVIDIENCE LINK":""} | N30: 2026-05-11T22:00:10.014056+01:00 | O30: 2026-05-11T22:00:10.014056+01:00
A31: a551359b10894c01b924ff9cd60ef59a | B31: a551359b10894c01b924ff9cd60ef59a | C31: 02509d5996fdac6f1510d956efac1a22e19c1e7ce606006d19437e2d9a481193 | D31: 33 | E31: 353065102623234 | F31: DENIS4WARD TECHNOLOGY | G31: SOLD | J31: 0 | L31: 0 | M31: {"S/N":"30","IMEI":"353065102623234","TIME":"","COLOUR":"RED","DEVICE":"IPHONE","STORAGE":"64GB","Column 17":"","Column 24":"","Column 25":"","Column 26":"","Column 27":"","Column 28":"","Column 29":"","Column 30":"","Column 31":"","Column 36":"","Column 37":"","Column 38":"","Column 39":"","Column 40":"","Column 41":"","Column 42":"","Column 43":"","Column 44":"","Column 45":"","Column 46":"","Column 47":"","PAID DATE":"","RECORD_ID":"a551359b10894c01b924ff9cd60ef59a","BATTERY. H":"80","CONDITIONS":"NONE","COST PRICE":"","DATE BOUGHT":"11/11/2024","DESCRIPTION":"IPHONE XR ","DEAL LOCATION":"","INTERNAL NOTE":"","NAME OF BUYER":"DENIS4WARD TECHNOLOGY","EXPENSE AMOUNT":"","NAME OF SELLER":"O.Z GADGET","PRODUCT STATUS":"SOLD","STATUS OF DEVICE":"UNLOCKED","CALCULATED PROFIT":"","EXPENSE DESCRIPTION":"","PHONE NUMBER OF BUYER":"08038551439","AVAILABILITY/DATE SOLD":"NOVEMBER, 12, 2024","PHONE NUMBER OF SELLER":"08106293924","RECEIPT & EVIDIENCE LINK":""} | N31: 2026-05-11T22:00:10.014056+01:00 | O31: 2026-05-11T22:00:10.014056+01:00
A32: 21b9eef9d5954558a57a313df42fbaa2 | B32: 21b9eef9d5954558a57a313df42fbaa2 | C32: 09b1d710a4976c93526ac1f781926f5c7d71c221bfd304e19efedda876eebb6f | D32: 34 | E32: 359271101948523 | F32: AZIMUTHAL | G32: SOLD | J32: 0 | L32: 0 | M32: {"S/N":"31","IMEI":"359271101948523","TIME":"","COLOUR":"BLACK","DEVICE":"SAMSUNG","STORAGE":"6GB + 256GB","Column 17":"","Column 24":"","Column 25":"","Column 26":"","Column 27":"","Column 28":"","Column 29":"","Column 30":"","Column 31":"","Column 36":"","Column 37":"","Column 38":"","Column 39":"","Column 40":"","Column 41":"","Column 42":"","Column 43":"","Column 44":"","Column 45":"","Column 46":"","Column 47":"","PAID DATE":"","RECORD_ID":"21b9eef9d5954558a57a313df42fbaa2","BATTERY. H":"-","CONDITIONS":"NONE","COST PRICE":"","DATE BOUGHT":"11/14/2024","DESCRIPTION":"SAMSUNG GALAXY NOTE 10+","DEAL LOCATION":"","INTERNAL NOTE":"","NAME OF BUYER":"AZIMUTHAL","EXPENSE AMOUNT":"","NAME OF SELLER":"SAMMY CONCEPT","PRODUCT STATUS":"SOLD","STATUS OF DEVICE":"UNLOCKED","CALCULATED PROFIT":"","EXPENSE DESCRIPTION":"","PHONE NUMBER OF BUYER":"08135659717","AVAILABILITY/DATE SOLD":"11/14/2024","PHONE NUMBER OF SELLER":"09037002617","RECEIPT & EVIDIENCE LINK":""} | N32: 2026-05-11T22:00:10.014056+01:00 | O32: 2026-05-11T22:00:10.014056+01:00
A33: a9035bf92cf4472a97fb6db5b3d079b6 | B33: a9035bf92cf4472a97fb6db5b3d079b6 | C33: 765dfe4238abba24154670e9e36df8c957990d2ff73ff1e3b011ccb884edacb7 | D33: 35 | E33: 353427814057830 | F33: DENIS4WARD TECHNOLOGY | G33: SOLD | J33: 0 | L33: 0 | M33: {"S/N":"32","IMEI":"353427814057830","TIME":"","COLOUR":"GOLD","DEVICE":"IPHONE","STORAGE":"128GB","Column 17":"","Column 24":"","Column 25":"","Column 26":"","Column 27":"","Column 28":"","Column 29":"","Column 30":"","Column 31":"","Column 36":"","Column 37":"","Column 38":"","Column 39":"","Column 40":"","Column 41":"","Column 42":"","Column 43":"","Column 44":"","Column 45":"","Column 46":"","Column 47":"","PAID DATE":"","RECORD_ID":"a9035bf92cf4472a97fb6db5b3d079b6","BATTERY. H":"87%","CONDITIONS":"NONE","COST PRICE":"","DATE BOUGHT":"11/06/2024","DESCRIPTION":"IPHONE 14 PRO MAX ","DEAL LOCATION":"","INTERNAL NOTE":"","NAME OF BUYER":"DENIS4WARD TECHNOLOGY","EXPENSE AMOUNT":"","NAME OF SELLER":"OFFICIALYUNG (SWAP)","PRODUCT STATUS":"SOLD","STATUS OF DEVICE":"UNLOCKED","CALCULATED PROFIT":"","EXPENSE DESCRIPTION":"","PHONE NUMBER OF BUYER":"08038551439","AVAILABILITY/DATE SOLD":"11/15/2024","PHONE NUMBER OF SELLER":"07083395113","RECEIPT & EVIDIENCE LINK":""} | N33: 2026-05-11T22:00:10.014056+01:00 | O33: 2026-05-11T22:00:10.014056+01:00
... A40: fa5bd1f181234283a486c7cda8478153 | B40: fa5bd1f181234283a486c7cda8478153 | C40: 844f843382e6934e663610bbf6697e9a106a94ae32ad48657eed70d125502268 | D40: 42 | E40: 352657197746218 | F40: AYANFE DENIS | G40: SOLD | J40: 0 | L40: 0 | M40: {"S/N":"39","IMEI":"352657197746218","TIME":"","COLOUR":"GOLD (DESERT)","DEVICE":"IPHONE","STORAGE":"128GB","Column 17":"","Column 24":"","Column 25":"","Column 26":"","Column 27":"","Column 28":"","Column 29":"","Column 30":"","Column 31":"","Column 36":"","Column 37":"","Column 38":"","Column 39":"","Column 40":"","Column 41":"","Column 42":"","Column 43":"","Column 44":"","Column 45":"","Column 46":"","Column 47":"","PAID DATE":"","RECORD_ID":"fa5bd1f181234283a486c7cda8478153","BATTERY. H":"100%","CONDITIONS":"","COST PRICE":"","DATE BOUGHT":"11/20/2024","DESCRIPTION":"IPHONE 16 PRO","DEAL LOCATION":"","INTERNAL NOTE":"","NAME OF BUYER":"AYANFE DENIS","EXPENSE AMOUNT":"","NAME OF SELLER":"YUSUF","PRODUCT STATUS":"SOLD","STATUS OF DEVICE":"LOCKED","CALCULATED PROFIT":"","EXPENSE DESCRIPTION":"","PHONE NUMBER OF BUYER":"08138108648","AVAILABILITY/DATE SOLD":"11/22/2024","PHONE NUMBER OF SELLER":"09076229406","RECEIPT & EVIDIENCE LINK":""} | N40: 2026-05-11T22:00:10.014056+01:00 | O40: 2026-05-11T22:00:10.014056+01:00
A41: 76ff941391e046ab8ab636a75a0a371b | B41: 76ff941391e046ab8ab636a75a0a371b | C41: 00c412cc166dbc649c19512d76fbcedcf11d767eb4623293fd43eccbaf538b7d | D41: 43 | F41: ALEX GADGET | G41: SOLD | J41: 0 | L41: 0 | M41: {"S/N":"40","IMEI":"","TIME":"","COLOUR":"BLUE","DEVICE":"IPHONE","STORAGE":"128GB","Column 17":"","Column 24":"","Column 25":"","Column 26":"","Column 27":"","Column 28":"","Column 29":"","Column 30":"","Column 31":"","Column 36":"","Column 37":"","Column 38":"","Column 39":"","Column 40":"","Column 41":"","Column 42":"","Column 43":"","Column 44":"","Column 45":"","Column 46":"","Column 47":"","PAID DATE":"","RECORD_ID":"76ff941391e046ab8ab636a75a0a371b","BATTERY. H":"76%(89%)","CONDITIONS":"NONE","COST PRICE":"","DATE BOUGHT":"11/15/2024","DESCRIPTION":"IPHONE 13","DEAL LOCATION":"","INTERNAL NOTE":"","NAME OF BUYER":"ALEX GADGET","EXPENSE AMOUNT":"","NAME OF SELLER":"TOLULOPE ADIO MEE","PRODUCT STATUS":"SOLD","STATUS OF DEVICE":"UNLOCKED","CALCULATED PROFIT":"","EXPENSE DESCRIPTION":"","PHONE NUMBER OF BUYER":"07025451690","AVAILABILITY/DATE SOLD":"11/20/2024","PHONE NUMBER OF SELLER":"09015069889","RECEIPT & EVIDIENCE LINK":""} | N41: 2026-05-11T22:00:10.014056+01:00 | O41: 2026-05-11T22:00:10.014056+01:00
A42: cb9e758ea6dc4f17b3c58cd00d94582f | B42: cb9e758ea6dc4f17b3c58cd00d94582f | C42: 3aefa4f2bdb9d0dd1b9467e91d1bc038d1d23b62176871340a279eca33ec7eff | D42: 44 | E42: 353357351413577 | F42: PHLEMZY | G42: SOLD | J42: 0 | L42: 0 | M42: {"S/N":"41","IMEI":"353357351413577","TIME":"","COLOUR":"DESERT (GOLD)","DEVICE":"IPHONE","STORAGE":"128GB","Column 17":"","Column 24":"","Column 25":"","Column 26":"","Column 27":"","Column 28":"","Column 29":"","Column 30":"","Column 31":"","Column 36":"","Column 37":"","Column 38":"","Column 39":"","Column 40":"","Column 41":"","Column 42":"","Column 43":"","Column 44":"","Column 45":"","Column 46":"","Column 47":"","PAID DATE":"","RECORD_ID":"cb9e758ea6dc4f17b3c58cd00d94582f","BATTERY. H":"100%","CONDITIONS":"NONE","COST PRICE":"","DATE BOUGHT":"11/15/2024","DESCRIPTION":"IPHONE 16 PRO BRAND NEW","DEAL LOCATION":"","INTERNAL NOTE":"","NAME OF BUYER":"PHLEMZY","EXPENSE AMOUNT":"","NAME OF SELLER":"MD GADGETS","PRODUCT STATUS":"SOLD","STATUS OF DEVICE":"LOCKED","CALCULATED PROFIT":"","EXPENSE DESCRIPTION":"","PHONE NUMBER OF BUYER":"09065642565","AVAILABILITY/DATE SOLD":"11/15/2024","PHONE NUMBER OF SELLER":"08166860603","RECEIPT & EVIDIENCE LINK":""} | N42: 2026-05-11T22:00:10.014056+01:00 | O42: 2026-05-11T22:00:10.014056+01:00
A43: a995a8af989d476cb74ae74e0f8d9b94 | B43: a995a8af989d476cb74ae74e0f8d9b94 | C43: 2581d8adf630106dc8b5a21d23b6444a4378a07cd413ef0ecf7f01e7f0959881 | D43: 45 | E43: 356314952615065 | F43: AYANFE DENIS | G43: SOLD | J43: 0 | L43: 0 | M43: {"S/N":"42","IMEI":"356314952615065","TIME":"","COLOUR":"ALPINE GREEN","DEVICE":"IPHONE","STORAGE":"256GB","Column 17":"","Column 24":"","Column 25":"","Column 26":"","Column 27":"","Column 28":"","Column 29":"","Column 30":"","Column 31":"","Column 36":"","Column 37":"","Column 38":"","Column 39":"","Column 40":"","Column 41":"","Column 42":"","Column 43":"","Column 44":"","Column 45":"","Column 46":"","Column 47":"","PAID DATE":"","RECORD_ID":"a995a8af989d476cb74ae74e0f8d9b94","BATTERY. H":"94%","CONDITIONS":"NONE","COST PRICE":"","DATE BOUGHT":"11/19/2024","DESCRIPTION":"IPHONE 13 PRO","DEAL LOCATION":"","INTERNAL NOTE":"","NAME OF BUYER":"AYANFE DENIS","EXPENSE AMOUNT":"","NAME OF SELLER":"JOY(JUMAT)","PRODUCT STATUS":"SOLD","STATUS OF DEVICE":"UNLOCKED","CALCULATED PROFIT":"","EXPENSE DESCRIPTION":"","PHONE NUMBER OF BUYER":"08138108648","AVAILABILITY/DATE SOLD":"11/27/2024","PHONE NUMBER OF SELLER":"08100725239","RECEIPT & EVIDIENCE LINK":""} | N43: 2026-05-11T22:00:10.014056+01:00 | O43: 2026-05-11T22:00:10.014056+01:00
A44: 734c0b3fa85a4fb0b2389c19d1f20d5f | B44: 734c0b3fa85a4fb0b2389c19d1f20d5f | C44: 236c414d46e92249a238d834bd6dc0aa83480f875d26394c67099d9b02e71e82 | D44: 46 | E44: 353237107467616 | F44: MHIDEY FROM BECKZ | G44: SOLD | J44: 0 | L44: 0 | M44: {"S/N":"43","IMEI":"353237107467616","TIME":"","COLOUR":"SPACE GREY","DEVICE":"IPHONE","STORAGE":"64GB","Column 17":"","Column 24":"","Column 25":"","Column 26":"","Column 27":"","Column 28":"","Column 29":"","Column 30":"","Column 31":"","Column 36":"","Column 37":"","Column 38":"","Column 39":"","Column 40":"","Column 41":"","Column 42":"","Column 43":"","Column 44":"","Column 45":"","Column 46":"","Column 47":"","PAID DATE":"","RECORD_ID":"734c0b3fa85a4fb0b2389c19d1f20d5f","BATTERY. H":"71%(92%)","CONDITIONS":"","COST PRICE":"","DATE BOUGHT":"11/19/2024","DESCRIPTION":"IPHONE 11 PRO","DEAL LOCATION":"","INTERNAL NOTE":"","NAME OF BUYER":"MHIDEY FROM BECKZ","EXPENSE AMOUNT":"","NAME OF SELLER":"IYANUOLUWA (WHYTE)","PRODUCT STATUS":"SOLD","STATUS OF DEVICE":"LOCKED","CALCULATED PROFIT":"","EXPENSE DESCRIPTION":"","PHONE NUMBER OF BUYER":"008032783523","AVAILABILITY/DATE SOLD":"","PHONE NUMBER OF SELLER":"08088480573","RECEIPT & EVIDIENCE LINK":""} | N44: 2026-05-11T22:00:10.014056+01:00 | O44: 2026-05-11T22:00:10.014056+01:00
A45: 96f7dd02c3aa4061b05d6c0fd7cec541 | B45: 96f7dd02c3aa4061b05d6c0fd7cec541 | C45: d3e36fb6fd7fede8222c34f943cbabb028bbe559da64f4f5f02c4f3e9d18db13 | D45: 47 | E45: 355591192643863 | F45: BEAUTYHAVEN FROM SEUN | G45: SOLD | J45: 0 | L45: 0 | M45: {"S/N":"44","IMEI":"355591192643863","TIME":"","COLOUR":"GOLD","DEVICE":"IPHONE","STORAGE":"512GB","Column 17":"","Column 24":"","Column 25":"","Column 26":"","Column 27":"","Column 28":"","Column 29":"","Column 30":"","Column 31":"","Column 36":"","Column 37":"","Column 38":"","Column 39":"","Column 40":"","Column 41":"","Column 42":"","Column 43":"","Column 44":"","Column 45":"","Column 46":"","Column 47":"","PAID DATE":"","RECORD_ID":"96f7dd02c3aa4061b05d6c0fd7cec541","BATTERY. H":"80%","CONDITIONS":"SWAPPED WITH 11 PRO MAX","COST PRICE":"","DATE BOUGHT":"11/20/2024","DESCRIPTION":"IPHONE 12 PRO MAX","DEAL LOCATION":"","INTERNAL NOTE":"","NAME OF BUYER":"BEAUTYHAVEN FROM SEUN","EXPENSE AMOUNT":"","NAME OF SELLER":"DENIS4WARD TECHNOLOGY ","PRODUCT STATUS":"SOLD","STATUS OF DEVICE":"UNLOCKED","CALCULATED PROFIT":"","EXPENSE DESCRIPTION":"","PHONE NUMBER OF BUYER":"07046502373","AVAILABILITY/DATE SOLD":"11/20/2024","PHONE NUMBER OF SELLER":"08038551439","RECEIPT & EVIDIENCE LINK":""} | N45: 2026-05-11T22:00:10.014056+01:00 | O45: 2026-05-11T22:00:10.014056+01:00
A46: e378b29fdbba4af8bc44e603c7285a8b | B46: e378b29fdbba4af8bc44e603c7285a8b | C46: dc8c0244d7a7df037cd542d360dcde549f3418c8e1ce42a1af024251c5f705bb | D46: 48 | E46: 35391505816351 | F46: CH4 STORE | G46: SOLD | J46: 0 | L46: 0 | M46: {"S/N":"45","IMEI":"35391505816351","TIME":"","COLOUR":"GOLD","DEVICE":"IPHONE","STORAGE":"256GB","Column 17":"","Column 24":"","Column 25":"","Column 26":"","Column 27":"","Column 28":"","Column 29":"","Column 30":"","Column 31":"","Column 36":"","Column 37":"","Column 38":"","Column 39":"","Column 40":"","Column 41":"","Column 42":"","Column 43":"","Column 44":"","Column 45":"","Column 46":"","Column 47":"","PAID DATE":"","RECORD_ID":"e378b29fdbba4af8bc44e603c7285a8b","BATTERY. H":"76%(89%)","CONDITIONS":"$485,000.00","COST PRICE":"","DATE BOUGHT":"11/20/2024","DESCRIPTION":"IPHONE 11 PRO MAX ","DEAL LOCATION":"","INTERNAL NOTE":"","NAME OF BUYER":"CH4 STORE","EXPENSE AMOUNT":"","NAME OF SELLER":"BEAUTYHAVEN. NG","PRODUCT STATUS":"SOLD","STATUS OF DEVICE":"UNLOCKED","CALCULATED PROFIT":"","EXPENSE DESCRIPTION":"","PHONE NUMBER OF BUYER":"08131941406","AVAILABILITY/DATE SOLD":"11/30/2024","PHONE NUMBER OF SELLER":"07046502373","RECEIPT & EVIDIENCE LINK":""} | N46: 2026-05-11T22:00:10.014056+01:00 | O46: 2026-05-11T22:00:10.014056+01:00
A47: 79016fcb141349ff85e5b2207c157f4c | B47: 79016fcb141349ff85e5b2207c157f4c | C47: a853776fbd2ff7b2cafc327f3f9ab6259bdd9866beeff315d8a5213cf0de58e8 | D47: 49 | E47: 357938432786689 | F47: IYANUOLUWA DEMIGLOBAL | G47: SOLD | J47: 0 | L47: 0 | M47: {"S/N":"46","IMEI":"357938432786689","TIME":"","COLOUR":"PURPLE","DEVICE":"IPHONE","STORAGE":"128GB","Column 17":"","Column 24":"","Column 25":"","Column 26":"","Column 27":"","Column 28":"","Column 29":"","Column 30":"","Column 31":"","Column 36":"","Column 37":"","Column 38":"","Column 39":"","Column 40":"","Column 41":"","Column 42":"","Column 43":"","Column 44":"","Column 45":"","Column 46":"","Column 47":"","PAID DATE":"","RECORD_ID":"79016fcb141349ff85e5b2207c157f4c","BATTERY. H":"92%","CONDITIONS":"$700,000.00","COST PRICE":"","DATE BOUGHT":"11/19/2024","DESCRIPTION":"IPHONE 14 PRO MAX ","DEAL LOCATION":"","INTERNAL NOTE":"","NAME OF BUYER":"IYANUOLUWA DEMIGLOBAL","EXPENSE AMOUNT":"","NAME OF SELLER":"SEYIFUNMI","PRODUCT STATUS":"SOLD","STATUS OF DEVICE":"LOCKED","CALCULATED PROFIT":"","EXPENSE DESCRIPTION":"","PHONE NUMBER OF BUYER":"08088480573","AVAILABILITY/DATE SOLD":"11/30/2024","PHONE NUMBER OF SELLER":"07036446358","RECEIPT & EVIDIENCE LINK":""} | N47: 2026-05-11T22:00:10.014056+01:00 | O47: 2026-05-11T22:00:10.014056+01:00
A48: 59b5ffb464f54257acfe265dc3afcc3f | B48: 59b5ffb464f54257acfe265dc3afcc3f | C48: a7fea1e833807ba875c089b57d3b610345bdedc97d1c3a3fcea90c98252cabc3 | D48: 50 | E48: 353223141615691 | F48: ENNY'S GADGET | G48: SOLD | J48: 0 | L48: 0 | M48: {"S/N":"47","IMEI":"353223141615691","TIME":"","COLOUR":"PURPLE","DEVICE":"IPHONE","STORAGE":"256GB","Column 17":"","Column 24":"","Column 25":"","Column 26":"","Column 27":"","Column 28":"","Column 29":"","Column 30":"","Column 31":"","Column 36":"","Column 37":"","Column 38":"","Column 39":"","Column 40":"","Column 41":"","Column 42":"","Column 43":"","Column 44":"","Column 45":"","Column 46":"","Column 47":"","PAID DATE":"","RECORD_ID":"59b5ffb464f54257acfe265dc3afcc3f","BATTERY. H":"93%","CONDITIONS":"$1,150,000.00","COST PRICE":"","DATE BOUGHT":"11/20/2024","DESCRIPTION":"IPHONE 14 PRO MAX ","DEAL LOCATION":"","INTERNAL NOTE":"","NAME OF BUYER":"ENNY'S GADGET","EXPENSE AMOUNT":"","NAME OF SELLER":"MOBILETRENDS LTD","PRODUCT STATUS":"SOLD","STATUS OF DEVICE":"LOCKED(THEN UNLOCKED)","CALCULATED PROFIT":"","EXPENSE DESCRIPTION":"","PHONE NUMBER OF BUYER":"09023824556","AVAILABILITY/DATE SOLD":"11/21/2024","PHONE NUMBER OF SELLER":"08034378180","RECEIPT & EVIDIENCE LINK":""} | N48: 2026-05-11T22:00:10.014056+01:00 | O48: 2026-05-11T22:00:10.014056+01:00
A49: 80a08bfb1ad8410586745ad44282b5f4 | B49: 80a08bfb1ad8410586745ad44282b5f4 | C49: d20cd91da9c57b5ec100d7fc1806a5e70e7a656cc42a14a35fe6815612fccb80 | D49: 51 | E49: 357084343408616 | F49: SWEET BOY | G49: SOLD | J49: 0 | L49: 0 | M49: {"S/N":"48","IMEI":"357084343408616","TIME":"","COLOUR":"RED","DEVICE":"IPHONE","STORAGE":"128GB","Column 17":"","Column 24":"","Column 25":"","Column 26":"","Column 27":"","Column 28":"","Column 29":"","Column 30":"","Column 31":"","Column 36":"","Column 37":"","Column 38":"","Column 39":"","Column 40":"","Column 41":"","Column 42":"","Column 43":"","Column 44":"","Column 45":"","Column 46":"","Column 47":"","PAID DATE":"","RECORD_ID":"80a08bfb1ad8410586745ad44282b5f4","BATTERY. H":"86%","CONDITIONS":"$465,000.00","COST PRICE":"","DATE BOUGHT":"11/22/2024","DESCRIPTION":"IPHONE 13","DEAL LOCATION":"","INTERNAL NOTE":"","NAME OF BUYER":"SWEET BOY","EXPENSE AMOUNT":"","NAME OF SELLER":"SAMUEL SLAWT","PRODUCT STATUS":"SOLD","STATUS OF DEVICE":"LOCKED","CALCULATED PROFIT":"","EXPENSE DESCRIPTION":"","PHONE NUMBER OF BUYER":"09039519037","AVAILABILITY/DATE SOLD":"11/23/2024","PHONE NUMBER OF SELLER":"09061496515","RECEIPT & EVIDIENCE LINK":""} | N49: 2026-05-11T22:00:10.014056+01:00 | O49: 2026-05-11T22:00:10.014056+01:00
A50: 35697e891b3544928d20cb9fe98c0b6c | B50: 35697e891b3544928d20cb9fe98c0b6c | C50: a6d170c522bf63feec88238bc070bfd66156a7865321487b204f8544f77491a7 | D50: 52 | E50: 353360940914956 | F50: IMOLE DC | G50: SOLD | J50: 0 | L50: 0 | M50: {"S/N":"49","IMEI":"353360940914956","TIME":"","COLOUR":"PURPLE","DEVICE":"IPHONE","STORAGE":"256GB","Column 17":"","Column 24":"","Column 25":"","Column 26":"","Column 27":"","Column 28":"","Column 29":"","Column 30":"","Column 31":"","Column 36":"","Column 37":"","Column 38":"","Column 39":"","Column 40":"","Column 41":"","Column 42":"","Column 43":"","Column 44":"","Column 45":"","Column 46":"","Column 47":"","PAID DATE":"","RECORD_ID":"35697e891b3544928d20cb9fe98c0b6c","BATTERY. H":"85%","CONDITIONS":"$770,000.00","COST PRICE":"","DATE BOUGHT":"11/27/2024","DESCRIPTION":"IPHONE 14 PRO MAX ","DEAL LOCATION":"","INTERNAL NOTE":"","NAME OF BUYER":"IMOLE DC","EXPENSE AMOUNT":"","NAME OF SELLER":"DEMIGLOBAL MULTISERVICE","PRODUCT STATUS":"SOLD","STATUS OF DEVICE":"LOCKED","CALCULATED PROFIT":"","EXPENSE DESCRIPTION":"","PHONE NUMBER OF BUYER":"08101680421","AVAILABILITY/DATE SOLD":"02/10/2025","PHONE NUMBER OF SELLER":"09066720385","RECEIPT & EVIDIENCE LINK":""} | N50: 2026-05-11T22:00:10.014056+01:00 | O50: 2026-05-11T22:00:10.014056+01:00
A51: 7b1194df76484e409180355fa319bf8d | B51: 7b1194df76484e409180355fa319bf8d | C51: 8fd2635d8d03b6f3953de5622a2418df60c1d18e25664cdc6b23780e3bbc14db | D51: 53 | E51: 350636593325274 | F51: DEMIGLOBAL MULTISERVICE | G51: SOLD | J51: 0 | L51: 0 | M51: {"S/N":"50","IMEI":"350636593325274","TIME":"","COLOUR":"PURPLE","DEVICE":"IPHONE","STORAGE":"256GB","Column 17":"","Column 24":"","Column 25":"","Column 26":"","Column 27":"","Column 28":"","Column 29":"","Column 30":"","Column 31":"","Column 36":"","Column 37":"","Column 38":"","Column 39":"","Column 40":"","Column 41":"","Column 42":"","Column 43":"","Column 44":"","Column 45":"","Column 46":"","Column 47":"","PAID DATE":"","RECORD_ID":"7b1194df76484e409180355fa319bf8d","BATTERY. H":"89%","CONDITIONS":"$1,150,000.00","COST PRICE":"","DATE BOUGHT":"11/26/2024","DESCRIPTION":"IPHONE 14 PRO MAX ","DEAL LOCATION":"","INTERNAL NOTE":"","NAME OF BUYER":"DEMIGLOBAL MULTISERVICE","EXPENSE AMOUNT":"","NAME OF SELLER":"SEYIFUNMI","PRODUCT STATUS":"SOLD","STATUS OF DEVICE":"UNLOCKED","CALCULATED PROFIT":"","EXPENSE DESCRIPTION":"","PHONE NUMBER OF BUYER":"09066720385","AVAILABILITY/DATE SOLD":"11/26/2024","PHONE NUMBER OF SELLER":"07065500068","RECEIPT & EVIDIENCE LINK":""} | N51: 2026-05-11T22:00:10.014056+01:00 | O51: 2026-05-11T22:00:10.014056+01:00
A52: d19ba25a660d416c92f7f1920def282f | B52: d19ba25a660d416c92f7f1920def282f | C52: ba2026c101ad2ef999a8c316c8d548961b190029f6b0e1e126789b82837d6953 | D52: 54 | E52: 353429712968993 | F52: KINGZGADGET | G52: SOLD | J52: 0 | L52: 0 | M52: {"S/N":"51","IMEI":"353429712968993","TIME":"","COLOUR":"PURPLE","DEVICE":"IPHONE","STORAGE":"256GB","Column 17":"","Column 24":"","Column 25":"","Column 26":"","Column 27":"","Column 28":"","Column 29":"","Column 30":"","Column 31":"","Column 36":"","Column 37":"","Column 38":"","Column 39":"","Column 40":"","Column 41":"","Column 42":"","Column 43":"","Column 44":"","Column 45":"","Column 46":"","Column 47":"","PAID DATE":"","RECORD_ID":"d19ba25a660d416c92f7f1920def282f","BATTERY. H":"93%","CONDITIONS":"$975,000.00","COST PRICE":"","DATE BOUGHT":"11/27/2024","DESCRIPTION":"IPHONE 14 PRO","DEAL LOCATION":"","INTERNAL NOTE":"","NAME OF BUYER":"KINGZGADGET","EXPENSE AMOUNT":"","NAME OF SELLER":"HAYKINZ TECH","PRODUCT STATUS":"SOLD","STATUS OF DEVICE":"LOCKED","CALCULATED PROFIT":"","EXPENSE DESCRIPTION":"","PHONE NUMBER OF BUYER":"07076133809","AVAILABILITY/DATE SOLD":"12/27/2024","PHONE NUMBER OF SELLER":"07030279101","RECEIPT & EVIDIENCE LINK":""} | N52: 2026-05-11T22:00:10.014056+01:00 | O52: 2026-05-11T22:00:10.014056+01:00
A53: a277dd9ca5c047a68b6f328899ce1b3d | B53: a277dd9ca5c047a68b6f328899ce1b3d | C53: 1a87d6b09183931cb70624f5d6ed28805e3721ae34e1689650cc0539c9d0974e | D53: 55 | E53: 350496301218398 | F53: ADESINA SEIDU | G53: SOLD | J53: 0 | L53: 0 | M53: {"S/N":"52","IMEI":"350496301218398","TIME":"","COLOUR":"WHITE","DEVICE":"IPHONE","STORAGE":"256GB","Column 17":"","Column 24":"","Column 25":"","Column 26":"","Column 27":"","Column 28":"","Column 29":"","Column 30":"","Column 31":"","Column 36":"","Column 37":"","Column 38":"","Column 39":"","Column 40":"","Column 41":"","Column 42":"","Column 43":"","Column 44":"","Column 45":"","Column 46":"","Column 47":"","PAID DATE":"","RECORD_ID":"a277dd9ca5c047a68b6f328899ce1b3d","BATTERY. H":"90%","CONDITIONS":"$1,400,000.00","COST PRICE":"","DATE BOUGHT":"11/27/2024","DESCRIPTION":"IPHONE 15 PRO MAX ","DEAL LOCATION":"","INTERNAL NOTE":"","NAME OF BUYER":"ADESINA SEIDU","EXPENSE AMOUNT":"","NAME OF SELLER":"HAYKINZ TECH","PRODUCT STATUS":"SOLD","STATUS OF DEVICE":"LOCKED(THEN UNLOCKED)","CALCULATED PROFIT":"","EXPENSE DESCRIPTION":"","PHONE NUMBER OF BUYER":"08106081752","AVAILABILITY/DATE SOLD":"11/30/2024","PHONE NUMBER OF SELLER":"07030279101","RECEIPT & EVIDIENCE LINK":""} | N53: 2026-05-11T22:00:10.014056+01:00 | O53: 2026-05-11T22:00:10.014056+01:00
... A58: 3ed4038cd56e45e3b4d18d768c4ada3c | B58: 3ed4038cd56e45e3b4d18d768c4ada3c | C58: 13fd20d2f114ad0648b65a6ade72ca09d3dcc969279dae2443342f588c38fc5e | D58: 60 | E58: 352400474539877 | F58: WIDAD | G58: SOLD | J58: 0 | L58: 0 | M58: {"S/N":"57","IMEI":"352400474539877","TIME":"","COLOUR":"BLACK TITANIUM","DEVICE":"IPHONE","STORAGE":"256GB","Column 17":"","Column 24":"","Column 25":"","Column 26":"","Column 27":"","Column 28":"","Column 29":"","Column 30":"","Column 31":"","Column 36":"","Column 37":"","Column 38":"","Column 39":"","Column 40":"","Column 41":"","Column 42":"","Column 43":"","Column 44":"","Column 45":"","Column 46":"","Column 47":"","PAID DATE":"","RECORD_ID":"3ed4038cd56e45e3b4d18d768c4ada3c","BATTERY. H":"87%","CONDITIONS":"$1,280,000.00","COST PRICE":"","DATE BOUGHT":"12/3/2024","DESCRIPTION":"IPHONE 15 PRO","DEAL LOCATION":"","INTERNAL NOTE":"","NAME OF BUYER":"WIDAD","EXPENSE AMOUNT":"","NAME OF SELLER":"STAR BOX","PRODUCT STATUS":"SOLD","STATUS OF DEVICE":"LOCKED(THEN UNLOCKED)","CALCULATED PROFIT":"","EXPENSE DESCRIPTION":"","PHONE NUMBER OF BUYER":"07062514545","AVAILABILITY/DATE SOLD":"12/21/2024","PHONE NUMBER OF SELLER":"09063620334","RECEIPT & EVIDIENCE LINK":""} | N58: 2026-05-11T22:00:10.014056+01:00 | O58: 2026-05-11T22:00:10.014056+01:00
A59: cf61336f16b644d09c596ac0d8175a8a | B59: cf61336f16b644d09c596ac0d8175a8a | C59: 4a19f979ffe37f0f06daa38827da22f64f73ccde84bc94830fe89b5f264e4f93 | D59: 61 | F59: BLESSING ABILEKO | G59: SOLD | J59: 0 | L59: 0 | M59: {"S/N":"58","IMEI":"","TIME":"","COLOUR":"BLACK","DEVICE":"SAMSUNG","STORAGE":"128GB","Column 17":"","Column 24":"","Column 25":"","Column 26":"","Column 27":"","Column 28":"","Column 29":"","Column 30":"","Column 31":"","Column 36":"","Column 37":"","Column 38":"","Column 39":"","Column 40":"","Column 41":"","Column 42":"","Column 43":"","Column 44":"","Column 45":"","Column 46":"","Column 47":"","PAID DATE":"","RECORD_ID":"cf61336f16b644d09c596ac0d8175a8a","BATTERY. H":"-","CONDITIONS":"$175,000.00","COST PRICE":"","DATE BOUGHT":"12/6/2024","DESCRIPTION":"SAMSUNG S8","DEAL LOCATION":"","INTERNAL NOTE":"","NAME OF BUYER":"BLESSING ABILEKO","EXPENSE AMOUNT":"","NAME OF SELLER":"DENIS4WARD TECHNOLOGY ","PRODUCT STATUS":"SOLD","STATUS OF DEVICE":"UNLOCKED","CALCULATED PROFIT":"","EXPENSE DESCRIPTION":"","PHONE NUMBER OF BUYER":"07010950790","AVAILABILITY/DATE SOLD":"12/6/2024","PHONE NUMBER OF SELLER":"08038551439","RECEIPT & EVIDIENCE LINK":""} | N59: 2026-05-11T22:00:10.014056+01:00 | O59: 2026-05-11T22:00:10.014056+01:00
A60: 605ea4f748854598b5e4fbebbe649af4 | B60: 605ea4f748854598b5e4fbebbe649af4 | C60: 7e7f9f01bafbdb967b59c26616770787b26a26cf32ffc3e6068953035b9418a3 | D60: 62 | F60: BLESSING ABILEKO | G60: SOLD | J60: 0 | L60: 0 | M60: {"S/N":"59","IMEI":"","TIME":"","COLOUR":"GREY","DEVICE":"SAMSUNG","STORAGE":"128GB","Column 17":"","Column 24":"","Column 25":"","Column 26":"","Column 27":"","Column 28":"","Column 29":"","Column 30":"","Column 31":"","Column 36":"","Column 37":"","Column 38":"","Column 39":"","Column 40":"","Column 41":"","Column 42":"","Column 43":"","Column 44":"","Column 45":"","Column 46":"","Column 47":"","PAID DATE":"","RECORD_ID":"605ea4f748854598b5e4fbebbe649af4","BATTERY. H":"-","CONDITIONS":"$175,000.00","COST PRICE":"","DATE BOUGHT":"12/6/2024","DESCRIPTION":"SAMSUNG S8","DEAL LOCATION":"","INTERNAL NOTE":"","NAME OF BUYER":"BLESSING ABILEKO","EXPENSE AMOUNT":"","NAME OF SELLER":"DENIS4WARD TECHNOLOGY ","PRODUCT STATUS":"SOLD","STATUS OF DEVICE":"UNLOCKED","CALCULATED PROFIT":"","EXPENSE DESCRIPTION":"","PHONE NUMBER OF BUYER":"07010950790","AVAILABILITY/DATE SOLD":"12/6/2024","PHONE NUMBER OF SELLER":"08038551439","RECEIPT & EVIDIENCE LINK":""} | N60: 2026-05-11T22:00:10.014056+01:00 | O60: 2026-05-11T22:00:10.014056+01:00
A61: 064bf17c94d043338d4463e5c1ac8072 | B61: 064bf17c94d043338d4463e5c1ac8072 | C61: 7c5c781080905ea13114e87584ee860e6b64bdafbf165fc4cb812d0bfb1be75b | D61: 63 | E61: 352847943200814 | F61: OKIKI GADGET (KAYWISE) | G61: SOLD | J61: 0 | L61: 0 | M61: {"S/N":"60","IMEI":"352847943200814","TIME":"","COLOUR":"WHITE","DEVICE":"IPHONE","STORAGE":"256GB","Column 17":"","Column 24":"","Column 25":"","Column 26":"","Column 27":"","Column 28":"","Column 29":"","Column 30":"","Column 31":"","Column 36":"","Column 37":"","Column 38":"","Column 39":"","Column 40":"","Column 41":"","Column 42":"","Column 43":"","Column 44":"","Column 45":"","Column 46":"","Column 47":"","PAID DATE":"","RECORD_ID":"064bf17c94d043338d4463e5c1ac8072","BATTERY. H":"87%","CONDITIONS":"$1,390,000.00","COST PRICE":"","DATE BOUGHT":"12/5/2024","DESCRIPTION":"IPHONE 15 PRO MAX","DEAL LOCATION":"","INTERNAL NOTE":"","NAME OF BUYER":"OKIKI GADGET (KAYWISE)","EXPENSE AMOUNT":"","NAME OF SELLER":"HAYKINZ TECH","PRODUCT STATUS":"SOLD","STATUS OF DEVICE":"LOCKED(THEN UNLOCKED)","CALCULATED PROFIT":"","EXPENSE DESCRIPTION":"","PHONE NUMBER OF BUYER":"08105344911","AVAILABILITY/DATE SOLD":"04/01/2024","PHONE NUMBER OF SELLER":"07030279101","RECEIPT & EVIDIENCE LINK":""} | N61: 2026-05-11T22:00:10.014056+01:00 | O61: 2026-05-11T22:00:10.014056+01:00
A62: f9739895a7bc42cd8585f2c74591c976 | B62: f9739895a7bc42cd8585f2c74591c976 | C62: 32a96aaa31adb12b108247b4021ea55967662cfff4d96ed79a5a4af722c6fa39 | D62: 64 | E62: 359428791784739 | F62: THANKGOD CONCEPT | G62: SOLD | J62: 0 | L62: 0 | M62: {"S/N":"61","IMEI":"359428791784739","TIME":"","COLOUR":"BLUE TITANIUM","DEVICE":"IPHONE","STORAGE":"256GB","Column 17":"","Column 24":"","Column 25":"","Column 26":"","Column 27":"","Column 28":"","Column 29":"","Column 30":"","Column 31":"","Column 36":"","Column 37":"","Column 38":"","Column 39":"","Column 40":"","Column 41":"","Column 42":"","Column 43":"","Column 44":"","Column 45":"","Column 46":"","Column 47":"","PAID DATE":"","RECORD_ID":"f9739895a7bc42cd8585f2c74591c976","BATTERY. H":"89","CONDITIONS":"","COST PRICE":"","DATE BOUGHT":"12/5/2024","DESCRIPTION":"IPHONE 15 PRO MAX","DEAL LOCATION":"","INTERNAL NOTE":"","NAME OF BUYER":"THANKGOD CONCEPT","EXPENSE AMOUNT":"","NAME OF SELLER":"NURUDEEN","PRODUCT STATUS":"SOLD","STATUS OF DEVICE":"LOCKED(THEN UNLOCKED)","CALCULATED PROFIT":"","EXPENSE DESCRIPTION":"","PHONE NUMBER OF BUYER":"09060695934","AVAILABILITY/DATE SOLD":"5/1/2025","PHONE NUMBER OF SELLER":"07067426927","RECEIPT & EVIDIENCE LINK":""} | N62: 2026-05-11T22:00:10.014056+01:00 | O62: 2026-05-11T22:00:10.014056+01:00
A63: de7b345cb9eb43eb9648a6ea3328a7b9 | B63: de7b345cb9eb43eb9648a6ea3328a7b9 | C63: 31610b35420f4b83260d7fd859ec750fdfa36094b1fc755c312d4d2f5efd0f49 | D63: 65 | E63: GF6WF4RXRQ | F63: FISTECH GADGET | G63: SOLD | J63: 0 | L63: 0 | M63: {"S/N":"62","IMEI":"GF6WF4RXRQ","TIME":"","COLOUR":"BLACK","DEVICE":"IWATCH","STORAGE":"-","Column 17":"","Column 24":"","Column 25":"","Column 26":"","Column 27":"","Column 28":"","Column 29":"","Column 30":"","Column 31":"","Column 36":"","Column 37":"","Column 38":"","Column 39":"","Column 40":"","Column 41":"","Column 42":"","Column 43":"","Column 44":"","Column 45":"","Column 46":"","Column 47":"","PAID DATE":"","RECORD_ID":"de7b345cb9eb43eb9648a6ea3328a7b9","BATTERY. H":"-","CONDITIONS":"$240,000.00","COST PRICE":"","DATE BOUGHT":"11/26/2024","DESCRIPTION":"SERIES 7","DEAL LOCATION":"","INTERNAL NOTE":"","NAME OF BUYER":"FISTECH GADGET","EXPENSE AMOUNT":"","NAME OF SELLER":"DEMIGLOBAL MULTISERVICE","PRODUCT STATUS":"SOLD","STATUS OF DEVICE":"UNLOCKED","CALCULATED PROFIT":"","EXPENSE DESCRIPTION":"","PHONE NUMBER OF BUYER":"09069888050","AVAILABILITY/DATE SOLD":"12/15/2024","PHONE NUMBER OF SELLER":"09066720385","RECEIPT & EVIDIENCE LINK":""} | N63: 2026-05-11T22:00:10.014056+01:00 | O63: 2026-05-11T22:00:10.014056+01:00
A64: 5e5264bc388e4d079347535bc0cf2a13 | B64: 5e5264bc388e4d079347535bc0cf2a13 | C64: 5e2da7c680645b8e544a5cebc55d32c4db6e4d6547c69693a4fc5f9b95f501ff | D64: 66 | E64: 354820297742432 | F64: BAHMS GADGS | G64: SOLD | J64: 0 | L64: 0 | M64: {"S/N":"63","IMEI":"354820297742432","TIME":"","COLOUR":"PINK","DEVICE":"IPHONE","STORAGE":"128GB","Column 17":"","Column 24":"","Column 25":"","Column 26":"","Column 27":"","Column 28":"","Column 29":"","Column 30":"","Column 31":"","Column 36":"","Column 37":"","Column 38":"","Column 39":"","Column 40":"","Column 41":"","Column 42":"","Column 43":"","Column 44":"","Column 45":"","Column 46":"","Column 47":"","PAID DATE":"","RECORD_ID":"5e5264bc388e4d079347535bc0cf2a13","BATTERY. H":"95","CONDITIONS":"$750,000.00","COST PRICE":"","DATE BOUGHT":"12/17/2024","DESCRIPTION":"IPHONE 15 PLUS","DEAL LOCATION":"","INTERNAL NOTE":"","NAME OF BUYER":"BAHMS GADGS","EXPENSE AMOUNT":"","NAME OF SELLER":"MD GADGETS","PRODUCT STATUS":"SOLD","STATUS OF DEVICE":"LOCKED","CALCULATED PROFIT":"","EXPENSE DESCRIPTION":"","PHONE NUMBER OF BUYER":"090669477050","AVAILABILITY/DATE SOLD":"12/22/2024","PHONE NUMBER OF SELLER":"08166860603","RECEIPT & EVIDIENCE LINK":""} | N64: 2026-05-11T22:00:10.014056+01:00 | O64: 2026-05-11T22:00:10.014056+01:00
A65: e228bca8d68c43418961814492df66f7 | B65: e228bca8d68c43418961814492df66f7 | C65: 9f63de49c8e166cc699efb23018b0e63a79829c2efd0194cfd3b74cd18277761 | D65: 67 | E65: 351582377070406 | F65: STARBOX | G65: SOLD | J65: 0 | L65: 0 | M65: {"S/N":"64","IMEI":"351582377070406","TIME":"","COLOUR":"BLACK","DEVICE":"IPHONE","STORAGE":"128GB","Column 17":"","Column 24":"","Column 25":"","Column 26":"","Column 27":"","Column 28":"","Column 29":"","Column 30":"","Column 31":"","Column 36":"","Column 37":"","Column 38":"","Column 39":"","Column 40":"","Column 41":"","Column 42":"","Column 43":"","Column 44":"","Column 45":"","Column 46":"","Column 47":"","PAID DATE":"","RECORD_ID":"e228bca8d68c43418961814492df66f7","BATTERY. H":"100","CONDITIONS":"$910,000.00","COST PRICE":"","DATE BOUGHT":"12/20/2024","DESCRIPTION":"IPHONE 16","DEAL LOCATION":"","INTERNAL NOTE":"","NAME OF BUYER":"STARBOX","EXPENSE AMOUNT":"","NAME OF SELLER":"OZ GADGETS","PRODUCT STATUS":"SOLD","STATUS OF DEVICE":"LOCKED","CALCULATED PROFIT":"","EXPENSE DESCRIPTION":"","PHONE NUMBER OF BUYER":"09063620334","AVAILABILITY/DATE SOLD":"1/14/2025","PHONE NUMBER OF SELLER":"08106293924","RECEIPT & EVIDIENCE LINK":""} | N65: 2026-05-11T22:00:10.014056+01:00 | O65: 2026-05-11T22:00:10.014056+01:00
A66: 33a2fb49b99c4d45be13830376acb480 | B66: 33a2fb49b99c4d45be13830376acb480 | C66: 5178ada44cda7e8858023dee0199e438a872be2e5aa774c22712131cdfa2f4f0 | D66: 68 | E66: 356166896719985 | F66: RETURNED | G66: SOLD | J66: 0 | L66: 0 | M66: {"S/N":"65","IMEI":"356166896719985","TIME":"","COLOUR":"BLACK","DEVICE":"IPHONE","STORAGE":"128GB","Column 17":"","Column 24":"","Column 25":"","Column 26":"","Column 27":"","Column 28":"","Column 29":"","Column 30":"","Column 31":"","Column 36":"","Column 37":"","Column 38":"","Column 39":"","Column 40":"","Column 41":"","Column 42":"","Column 43":"","Column 44":"","Column 45":"","Column 46":"","Column 47":"","PAID DATE":"","RECORD_ID":"33a2fb49b99c4d45be13830376acb480","BATTERY. H":"100","CONDITIONS":"","COST PRICE":"","DATE BOUGHT":"12/21/2024","DESCRIPTION":"IPHONE 16","DEAL LOCATION":"","INTERNAL NOTE":"","NAME OF BUYER":"RETURNED","EXPENSE AMOUNT":"","NAME OF SELLER":"OZ GADGETS","PRODUCT STATUS":"SOLD","STATUS OF DEVICE":"LOCKED","CALCULATED PROFIT":"","EXPENSE DESCRIPTION":"","PHONE NUMBER OF BUYER":"RETURNED","AVAILABILITY/DATE SOLD":"","PHONE NUMBER OF SELLER":"08106293925","RECEIPT & EVIDIENCE LINK":""} | N66: 2026-05-11T22:00:10.014056+01:00 | O66: 2026-05-11T22:00:10.014056+01:00
A67: 958aaf17a8a5466da1f4d07dfd5ca4fa | B67: 958aaf17a8a5466da1f4d07dfd5ca4fa | C67: 9f424c36a09d2bc2d1bdad7df792131acf3df26e81c00e5726a56fd7ba6b2a48 | D67: 69 | E67: 359954318707176 | F67: IYANUOLUWA DEMIGLOBAL | G67: SOLD | J67: 0 | L67: 0 | M67: {"S/N":"66","IMEI":"359954318707176","TIME":"","COLOUR":"BLACK","DEVICE":"IPHONE","STORAGE":"128GB","Column 17":"","Column 24":"","Column 25":"","Column 26":"","Column 27":"","Column 28":"","Column 29":"","Column 30":"","Column 31":"","Column 36":"","Column 37":"","Column 38":"","Column 39":"","Column 40":"","Column 41":"","Column 42":"","Column 43":"","Column 44":"","Column 45":"","Column 46":"","Column 47":"","PAID DATE":"","RECORD_ID":"958aaf17a8a5466da1f4d07dfd5ca4fa","BATTERY. H":"100","CONDITIONS":"$985,000.00","COST PRICE":"","DATE BOUGHT":"12/22/2024","DESCRIPTION":"IPHONE 16","DEAL LOCATION":"","INTERNAL NOTE":"","NAME OF BUYER":"IYANUOLUWA DEMIGLOBAL ","EXPENSE AMOUNT":"","NAME OF SELLER":"OZ GADGETS","PRODUCT STATUS":"SOLD","STATUS OF DEVICE":"LOCKED","CALCULATED PROFIT":"","EXPENSE DESCRIPTION":"","PHONE NUMBER OF BUYER":"08088480573","AVAILABILITY/DATE SOLD":"1/16/2025","PHONE NUMBER OF SELLER":"08106293926","RECEIPT & EVIDIENCE LINK":""} | N67: 2026-05-11T22:00:10.014056+01:00 | O67: 2026-05-11T22:00:10.014056+01:00
A68: c77edb9056ec4aaea8002d9b4173f8ca | B68: c77edb9056ec4aaea8002d9b4173f8ca | C68: 3e6a61b7730878686199512921e0174a8864a3cb743bcdc57c4d1483edb4ae91 | D68: 70 | E68: 352845110550730 | F68: MIDE GADGET | G68: SOLD | J68: 0 | L68: 0 | M68: {"S/N":"67","IMEI":"352845110550730","TIME":"","COLOUR":"SPACE GREY","DEVICE":"IPHONE","STORAGE":"256GB","Column 17":"","Column 24":"","Column 25":"","Column 26":"","Column 27":"","Column 28":"","Column 29":"","Column 30":"","Column 31":"","Column 36":"","Column 37":"","Column 38":"","Column 39":"","Column 40":"","Column 41":"","Column 42":"","Column 43":"","Column 44":"","Column 45":"","Column 46":"","Column 47":"","PAID DATE":"","RECORD_ID":"c77edb9056ec4aaea8002d9b4173f8ca","BATTERY. H":"87%","CONDITIONS":"$480,000.00","COST PRICE":"","DATE BOUGHT":"12/16/2024","DESCRIPTION":"IPHONE 11 PRO MAX ","DEAL LOCATION":"","INTERNAL NOTE":"","NAME OF BUYER":"MIDE GADGET","EXPENSE AMOUNT":"","NAME OF SELLER":"KEMISOLA","PRODUCT STATUS":"SOLD","STATUS OF DEVICE":"UNLOCKED","CALCULATED PROFIT":"","EXPENSE DESCRIPTION":"","PHONE NUMBER OF BUYER":"09066003937","AVAILABILITY/DATE SOLD":"1/13/2025","PHONE NUMBER OF SELLER":"08068736319","RECEIPT & EVIDIENCE LINK":""} | N68: 2026-05-11T22:00:10.014056+01:00 | O68: 2026-05-11T22:00:10.014056+01:00
A69: 4fb8ff281f434810a55f43f64ca40d8b | B69: 4fb8ff281f434810a55f43f64ca40d8b | C69: 5e99e92dc05a45111a63ac5c71d87f3b644048014c8e04dc664422ef67a41212 | D69: 71 | E69: 353468912889807 | F69: TUNDE Babz | G69: SOLD | J69: 0 | L69: 0 | M69: {"S/N":"68","IMEI":"353468912889807","TIME":"","COLOUR":"BLUE TITANIUM","DEVICE":"IPHONE","STORAGE":"128GB","Column 17":"","Column 24":"","Column 25":"","Column 26":"","Column 27":"","Column 28":"","Column 29":"","Column 30":"","Column 31":"","Column 36":"","Column 37":"","Column 38":"","Column 39":"","Column 40":"","Column 41":"","Column 42":"","Column 43":"","Column 44":"","Column 45":"","Column 46":"","Column 47":"","PAID DATE":"","RECORD_ID":"4fb8ff281f434810a55f43f64ca40d8b","BATTERY. H":"95","CONDITIONS":"","COST PRICE":"","DATE BOUGHT":"12/19/2024","DESCRIPTION":"IPHONE 15 PRO","DEAL LOCATION":"","INTERNAL NOTE":"","NAME OF BUYER":"TUNDE Babz","EXPENSE AMOUNT":"","NAME OF SELLER":"DENIS4WARD TECHNOLOGY","PRODUCT STATUS":"SOLD","STATUS OF DEVICE":"UNLOCKED","CALCULATED PROFIT":"","EXPENSE DESCRIPTION":"","PHONE NUMBER OF BUYER":"0813 079 3960","AVAILABILITY/DATE SOLD":"","PHONE NUMBER OF SELLER":"08038551439","RECEIPT & EVIDIENCE LINK":""} | N69: 2026-05-11T22:00:10.014056+01:00 | O69: 2026-05-11T22:00:10.014056+01:00
A70: ac4ad297b0d44c469d2fa53805b2f8c1 | B70: ac4ad297b0d44c469d2fa53805b2f8c1 | C70: a4a57b57a150790cc2626ea09ec41b5d54b5a1688c51337c4b82ddef97a50a69 | D70: 72 | F70: OLUWASEUN | G70: SOLD | J70: 0 | L70: 0 | M70: {"S/N":"69","IMEI":"","TIME":"","COLOUR":"SIERRA BLUE","DEVICE":"IPHONE","STORAGE":"128GB","Column 17":"","Column 24":"","Column 25":"","Column 26":"","Column 27":"","Column 28":"","Column 29":"","Column 30":"","Column 31":"","Column 36":"","Column 37":"","Column 38":"","Column 39":"","Column 40":"","Column 41":"","Column 42":"","Column 43":"","Column 44":"","Column 45":"","Column 46":"","Column 47":"","PAID DATE":"","RECORD_ID":"ac4ad297b0d44c469d2fa53805b2f8c1","BATTERY. H":"87%","CONDITIONS":"","COST PRICE":"","DATE BOUGHT":"12/18/2024","DESCRIPTION":"IPHONE 13 PRO MAX","DEAL LOCATION":"","INTERNAL NOTE":"","NAME OF BUYER":"OLUWASEUN","EXPENSE AMOUNT":"","NAME OF SELLER":"THANKGOD CONCEPT","PRODUCT STATUS":"SOLD","STATUS OF DEVICE":"UNLOCKED","CALCULATED PROFIT":"","EXPENSE DESCRIPTION":"","PHONE NUMBER OF BUYER":"","AVAILABILITY/DATE SOLD":"","PHONE NUMBER OF SELLER":"09060695934","RECEIPT & EVIDIENCE LINK":""} | N70: 2026-05-11T22:00:10.014056+01:00 | O70: 2026-05-11T22:00:10.014056+01:00
A71: e7ab16997ce4485e8cb79a89c69c4070 | B71: e7ab16997ce4485e8cb79a89c69c4070 | C71: 5a0ed4abaa47e3dc44ca9c9a7613b6644b81b45e7e7c85b5e797c3ea4d908ffe | D71: 73 | E71: 356487145927504 | F71: KEMI (FROM SEUN) | G71: SOLD | J71: 0 | L71: 0 | M71: {"S/N":"70","IMEI":"356487145927504","TIME":"","COLOUR":"GRAPHITE","DEVICE":"IPHONE","STORAGE":"256GB","Column 17":"","Column 24":"","Column 25":"","Column 26":"","Column 27":"","Column 28":"","Column 29":"","Column 30":"","Column 31":"","Column 36":"","Column 37":"","Column 38":"","Column 39":"","Column 40":"","Column 41":"","Column 42":"","Column 43":"","Column 44":"","Column 45":"","Column 46":"","Column 47":"","PAID DATE":"","RECORD_ID":"e7ab16997ce4485e8cb79a89c69c4070","BATTERY. H":"100%","CONDITIONS":"","COST PRICE":"","DATE BOUGHT":"12/16/2024","DESCRIPTION":"IPHONE 12 PRO MAX","DEAL LOCATION":"","INTERNAL NOTE":"","NAME OF BUYER":"KEMI (FROM SEUN)","EXPENSE AMOUNT":"","NAME OF SELLER":"DENIS4WARD TECHNOLOGY","PRODUCT STATUS":"SOLD","STATUS OF DEVICE":"UNLOCKED","CALCULATED PROFIT":"","EXPENSE DESCRIPTION":"","PHONE NUMBER OF BUYER":"08068736319","AVAILABILITY/DATE SOLD":"12/16/2024","PHONE NUMBER OF SELLER":"08038551439","RECEIPT & EVIDIENCE LINK":""} | N71: 2026-05-11T22:00:10.014056+01:00 | O71: 2026-05-11T22:00:10.014056+01:00
A72: 3faa08d1ea6a4f8c9ea46af7e3c25c00 | B72: 3faa08d1ea6a4f8c9ea46af7e3c25c00 | C72: ff6d77a5ab174fe9e2cc94227c6065e9032317abcf825f83e7cb4255d8dedc67 | D72: 74 | E72: 353268391218019 | F72: THANKGOD CONCEPT | G72: SOLD | J72: 0 | L72: 0 | M72: {"S/N":"71","IMEI":"353268391218019","TIME":"","COLOUR":"DESERT","DEVICE":"IPHONE","STORAGE":"128GB","Column 17":"","Column 24":"","Column 25":"","Column 26":"","Column 27":"","Column 28":"","Column 29":"","Column 30":"","Column 31":"","Column 36":"","Column 37":"","Column 38":"","Column 39":"","Column 40":"","Column 41":"","Column 42":"","Column 43":"","Column 44":"","Column 45":"","Column 46":"","Column 47":"","PAID DATE":"","RECORD_ID":"3faa08d1ea6a4f8c9ea46af7e3c25c00","BATTERY. H":"100%","CONDITIONS":"$1,600,000.00","COST PRICE":"","DATE BOUGHT":"12/3/2024","DESCRIPTION":"IPHONE 16 PRO","DEAL LOCATION":"","INTERNAL NOTE":"","NAME OF BUYER":"THANKGOD CONCEPT","EXPENSE AMOUNT":"","NAME OF SELLER":"DENIS4WARD TECHNOLOGY","PRODUCT STATUS":"SOLD","STATUS OF DEVICE":"LOCKED(UNLOCKED)","CALCULATED PROFIT":"","EXPENSE DESCRIPTION":"","PHONE NUMBER OF BUYER":"09060695934","AVAILABILITY/DATE SOLD":"1/4/2025","PHONE NUMBER OF SELLER":"08038551439","RECEIPT & EVIDIENCE LINK":""} | N72: 2026-05-11T22:00:10.014056+01:00 | O72: 2026-05-11T22:00:10.014056+01:00
A73: 51eeb4fc85e84a51bc29b5ce4ce27a1e | B73: 51eeb4fc85e84a51bc29b5ce4ce27a1e | C73: c9d7301caecd0b96e753c76124dbb1f7700866051de4ef693c9f6acb7f9f6fd5 | D73: 75 | E73: 357348095438059 | F73: OLA BTC | G73: SOLD | J73: 0 | L73: 0 | M73: {"S/N":"72","IMEI":"357348095438059","TIME":"","COLOUR":"BLACK","DEVICE":"IPHONE","STORAGE":"64GB","Column 17":"","Column 24":"","Column 25":"","Column 26":"","Column 27":"","Column 28":"","Column 29":"","Column 30":"","Column 31":"","Column 36":"","Column 37":"","Column 38":"","Column 39":"","Column 40":"","Column 41":"","Column 42":"","Column 43":"","Column 44":"","Column 45":"","Column 46":"","Column 47":"","PAID DATE":"","RECORD_ID":"51eeb4fc85e84a51bc29b5ce4ce27a1e","BATTERY. H":"76%(87%)","CONDITIONS":"$230,000.00","COST PRICE":"","DATE BOUGHT":"12/20/2024","DESCRIPTION":"IPHONE XR","DEAL LOCATION":"","INTERNAL NOTE":"","NAME OF BUYER":"OLA BTC","EXPENSE AMOUNT":"","NAME OF SELLER":"MHIDE FROM (BECKZ)","PRODUCT STATUS":"SOLD","STATUS OF DEVICE":"UNLOCKED","CALCULATED PROFIT":"","EXPENSE DESCRIPTION":"","PHONE NUMBER OF BUYER":"07061613141","AVAILABILITY/DATE SOLD":"12/26/2024","PHONE NUMBER OF SELLER":"008032783523","RECEIPT & EVIDIENCE LINK":""} | N73: 2026-05-11T22:00:10.014056+01:00 | O73: 2026-05-11T22:00:10.014056+01:00
A74: de263eff9a45471298eb7dd169093909 | B74: de263eff9a45471298eb7dd169093909 | C74: ec72b4b73ff1844d13c6110ac6a6218f64b28f04e269a273b37f672492625b29 | D74: 76 | F74: AZIMUTHAL | G74: SOLD | J74: 0 | L74: 0 | M74: {"S/N":"73","IMEI":"","TIME":"","COLOUR":"GREEN","DEVICE":"IPHONE","STORAGE":"64GB","Column 17":"","Column 24":"","Column 25":"","Column 26":"","Column 27":"","Column 28":"","Column 29":"","Column 30":"","Column 31":"","Column 36":"","Column 37":"","Column 38":"","Column 39":"","Column 40":"","Column 41":"","Column 42":"","Column 43":"","Column 44":"","Column 45":"","Column 46":"","Column 47":"","PAID DATE":"","RECORD_ID":"de263eff9a45471298eb7dd169093909","BATTERY. H":"79%","CONDITIONS":"$450,000.00","COST PRICE":"","DATE BOUGHT":"12/11/2024","DESCRIPTION":"IPHONE 12","DEAL LOCATION":"","INTERNAL NOTE":"","NAME OF BUYER":"AZIMUTHAL","EXPENSE AMOUNT":"","NAME OF SELLER":"GLORY","PRODUCT STATUS":"SOLD","STATUS OF DEVICE":"UNLOCKED","CALCULATED PROFIT":"","EXPENSE DESCRIPTION":"","PHONE NUMBER OF BUYER":"08135659717","AVAILABILITY/DATE SOLD":"12/11/2024","PHONE NUMBER OF SELLER":"09060584225","RECEIPT & EVIDIENCE LINK":""} | N74: 2026-05-11T22:00:10.014056+01:00 | O74: 2026-05-11T22:00:10.014056+01:00
A75: 34f72e529b054dc2b64919acef1ed32d | B75: 34f72e529b054dc2b64919acef1ed32d | C75: ff90a7f7f367d1980954992f454067b0c414fd25548a748b945cd87e985362f2 | D75: 77 | E75: 359271101948523 | F75: STARBOX | G75: SOLD | J75: 0 | L75: 0 | M75: {"S/N":"74","IMEI":"359271101948523","TIME":"","COLOUR":"BLACK","DEVICE":"SAMSUNG","STORAGE":"64GB","Column 17":"","Column 24":"","Column 25":"","Column 26":"","Column 27":"","Column 28":"","Column 29":"","Column 30":"","Column 31":"","Column 36":"","Column 37":"","Column 38":"","Column 39":"","Column 40":"","Column 41":"","Column 42":"","Column 43":"","Column 44":"","Column 45":"","Column 46":"","Column 47":"","PAID DATE":"","RECORD_ID":"34f72e529b054dc2b64919acef1ed32d","BATTERY. H":"-","CONDITIONS":"$345,000.00","COST PRICE":"","DATE BOUGHT":"12/11/2024","DESCRIPTION":"SAMSUNG NOTE 10+","DEAL LOCATION":"","INTERNAL NOTE":"","NAME OF BUYER":"STARBOX","EXPENSE AMOUNT":"","NAME OF SELLER":"AZIMUTHAL","PRODUCT STATUS":"SOLD","STATUS OF DEVICE":"UNLOCKED","CALCULATED PROFIT":"","EXPENSE DESCRIPTION":"","PHONE NUMBER OF BUYER":"09063620334","AVAILABILITY/DATE SOLD":"12/20/2024","PHONE NUMBER OF SELLER":"08135659717","RECEIPT & EVIDIENCE LINK":""} | N75: 2026-05-11T22:00:10.014056+01:00 | O75: 2026-05-11T22:00:10.014056+01:00
A76: f32a6ea785b0409397762e628cf06bad | B76: f32a6ea785b0409397762e628cf06bad | C76: a3a28eaa68654f3187623b1a76a4a608341dfe907b7230e0d13a49d259331cc1 | D76: 78 | E76: 355300183605562 | F76: ARMY MIGHTY | G76: SOLD | J76: 0 | L76: 0 | M76: {"S/N":"75","IMEI":"355300183605562","TIME":"","COLOUR":"WHITE TITANIUM","DEVICE":"IPHONE","STORAGE":"512GB","Column 17":"","Column 24":"","Column 25":"","Column 26":"","Column 27":"","Column 28":"","Column 29":"","Column 30":"","Column 31":"","Column 36":"","Column 37":"","Column 38":"","Column 39":"","Column 40":"","Column 41":"","Column 42":"","Column 43":"","Column 44":"","Column 45":"","Column 46":"","Column 47":"","PAID DATE":"","RECORD_ID":"f32a6ea785b0409397762e628cf06bad","BATTERY. H":"100%","CONDITIONS":"$1,550,000.00","COST PRICE":"\u20a61,550,000.00","DATE BOUGHT":"12/31/2024","DESCRIPTION":"IPHONE 16 PRO MAX BRAND NEW","DEAL LOCATION":"","INTERNAL NOTE":"","NAME OF BUYER":"ARMY MIGHTY ","EXPENSE AMOUNT":"","NAME OF SELLER":"DENIS4WARD TECHNOLOGY","PRODUCT STATUS":"SOLD","STATUS OF DEVICE":"LOCKED","CALCULATED PROFIT":"","EXPENSE DESCRIPTION":"","PHONE NUMBER OF BUYER":"08169094027","AVAILABILITY/DATE SOLD":"4/20/2026","PHONE NUMBER OF SELLER":"08038551439","RECEIPT & EVIDIENCE LINK":""} | N76: 2026-05-11T22:00:10.014056+01:00 | O76: 2026-05-11T22:00:10.014056+01:00
A77: a69653bd5d064160a326f62db36fab4e | B77: a69653bd5d064160a326f62db36fab4e | C77: f95b69c82fe94cc9e03f3052c14f6a77cbf3b97ac8c5de99a18b2d84447df30a | D77: 79 | E77: 350686383077569 | F77: BAHMS GADGS | G77: SOLD | J77: 0 | L77: 0 | M77: {"S/N":"76","IMEI":"350686383077569","TIME":"","COLOUR":"BLACK TITANIUM","DEVICE":"IPHONE","STORAGE":"128GB","Column 17":"","Column 24":"","Column 25":"","Column 26":"","Column 27":"","Column 28":"","Column 29":"","Column 30":"","Column 31":"","Column 36":"","Column 37":"","Column 38":"","Column 39":"","Column 40":"","Column 41":"","Column 42":"","Column 43":"","Column 44":"","Column 45":"","Column 46":"","Column 47":"","PAID DATE":"","RECORD_ID":"a69653bd5d064160a326f62db36fab4e","BATTERY. H":"99%","CONDITIONS":"$980,000.00","COST PRICE":"","DATE BOUGHT":"12/31/2024","DESCRIPTION":"IPHONE 15 PLUS","DEAL LOCATION":"","INTERNAL NOTE":"","NAME OF BUYER":"BAHMS GADGS","EXPENSE AMOUNT":"","NAME OF SELLER":"ARMY MIGHTY","PRODUCT STATUS":"SOLD","STATUS OF DEVICE":"UNLOCKED","CALCULATED PROFIT":"","EXPENSE DESCRIPTION":"","PHONE NUMBER OF BUYER":"09069477050","AVAILABILITY/DATE SOLD":"1/8/2025","PHONE NUMBER OF SELLER":"08169094027","RECEIPT & EVIDIENCE LINK":""} | N77: 2026-05-11T22:00:10.014056+01:00 | O77: 2026-05-11T22:00:10.014056+01:00
A78: 126fbcb7af074f89b094d53618cf12c5 | B78: 126fbcb7af074f89b094d53618cf12c5 | C78: 79608ca5b6c2f765940c1caec9ca91ef3d7e6b9fdd7f793ddcb9bf6e42d0e5f8 | D78: 80 | E78: 356462525826972 | F78: MIDE GADGET | G78: SOLD | J78: 0 | L78: 0 | M78: {"S/N":"77","IMEI":"356462525826972","TIME":"","COLOUR":"GOLD","DEVICE":"IPHONE","STORAGE":"256GB","Column 17":"","Column 24":"","Column 25":"","Column 26":"","Column 27":"","Column 28":"","Column 29":"","Column 30":"","Column 31":"","Column 36":"","Column 37":"","Column 38":"","Column 39":"","Column 40":"","Column 41":"","Column 42":"","Column 43":"","Column 44":"","Column 45":"","Column 46":"","Column 47":"","PAID DATE":"","RECORD_ID":"126fbcb7af074f89b094d53618cf12c5","BATTERY. H":"77%","CONDITIONS":"","COST PRICE":"","DATE BOUGHT":"12/30/2024","DESCRIPTION":"IPHONE 12 PRO","DEAL LOCATION":"","INTERNAL NOTE":"","NAME OF BUYER":"MIDE GADGET","EXPENSE AMOUNT":"","NAME OF SELLER":"MALI GADGET","PRODUCT STATUS":"SOLD","STATUS OF DEVICE":"LOCKED","CALCULATED PROFIT":"","EXPENSE DESCRIPTION":"","PHONE NUMBER OF BUYER":"09066003937","AVAILABILITY/DATE SOLD":"","PHONE NUMBER OF SELLER":"08115570178","RECEIPT & EVIDIENCE LINK":""} | N78: 2026-05-11T22:00:10.014056+01:00 | O78: 2026-05-11T22:00:10.014056+01:00
A79: 32c7e9bef76845f4b712207c77c0cbda | B79: 32c7e9bef76845f4b712207c77c0cbda | C79: 07b24c99c188f4fd990e7b611e33033a3d24845de5500e2c1bb0931da3c1cf9e | D79: 81 | F79: IPRO GADGET | G79: SOLD | J79: 0 | L79: 0 | M79: {"S/N":"78","IMEI":"","TIME":"","COLOUR":"PURPLE","DEVICE":"IPHONE","STORAGE":"64GB","Column 17":"","Column 24":"","Column 25":"","Column 26":"","Column 27":"","Column 28":"","Column 29":"","Column 30":"","Column 31":"","Column 36":"","Column 37":"","Column 38":"","Column 39":"","Column 40":"","Column 41":"","Column 42":"","Column 43":"","Column 44":"","Column 45":"","Column 46":"","Column 47":"","PAID DATE":"","RECORD_ID":"32c7e9bef76845f4b712207c77c0cbda","BATTERY. H":"72%","CONDITIONS":"$280,000.00","COST PRICE":"","DATE BOUGHT":"1/5/2025","DESCRIPTION":"IPHONE 11","DEAL LOCATION":"","INTERNAL NOTE":"","NAME OF BUYER":"IPRO GADGET","EXPENSE AMOUNT":"","NAME OF SELLER":"JAPHET","PRODUCT STATUS":"SOLD","STATUS OF DEVICE":"UNLOCKED","CALCULATED PROFIT":"","EXPENSE DESCRIPTION":"","PHONE NUMBER OF BUYER":"08109344663","AVAILABILITY/DATE SOLD":"05/01/2024","PHONE NUMBER OF SELLER":"09050037923","RECEIPT & EVIDIENCE LINK":""} | N79: 2026-05-11T22:00:10.014056+01:00 | O79: 2026-05-11T22:00:10.014056+01:00
A80: 1158896726bd4fe5bf7d0f906ffa639c | B80: 1158896726bd4fe5bf7d0f906ffa639c | C80: b3b4dac862eafec0e833aabea9b3303bce9cac821e183dbe64348c7195353968 | D80: 82 | E80: 350056592721102 | F80: PANKY GEE | G80: SOLD | J80: 0 | L80: 0 | M80: {"S/N":"79","IMEI":"350056592721102","TIME":"","COLOUR":"GOLD","DEVICE":"IPHONE","STORAGE":"128GB","Column 17":"","Column 24":"","Column 25":"","Column 26":"","Column 27":"","Column 28":"","Column 29":"","Column 30":"","Column 31":"","Column 36":"","Column 37":"","Column 38":"","Column 39":"","Column 40":"","Column 41":"","Column 42":"","Column 43":"","Column 44":"","Column 45":"","Column 46":"","Column 47":"","PAID DATE":"","RECORD_ID":"1158896726bd4fe5bf7d0f906ffa639c","BATTERY. H":"87%","CONDITIONS":"$940,000.00","COST PRICE":"","DATE BOUGHT":"1/3/2025","DESCRIPTION":"IPHONE 14 PRO (P + E)","DEAL LOCATION":"","INTERNAL NOTE":"","NAME OF BUYER":"PANKY GEE","EXPENSE AMOUNT":"","NAME OF SELLER":"THANKGOD CONCEPT","PRODUCT STATUS":"SOLD","STATUS OF DEVICE":"UNLOCKED","CALCULATED PROFIT":"","EXPENSE DESCRIPTION":"","PHONE NUMBER OF BUYER":"07052247397","AVAILABILITY/DATE SOLD":"1/12/2025","PHONE NUMBER OF SELLER":"","RECEIPT & EVIDIENCE LINK":""} | N80: 2026-05-11T22:00:10.014056+01:00 | O80: 2026-05-11T22:00:10.014056+01:00
A81: 30bccf2c9b744fd89788a68d27784f73 | B81: 30bccf2c9b744fd89788a68d27784f73 | C81: 2dca06012b7685f58822a5547b5f3940645d979e00e63c3dd2695005cc95b0dc | D81: 83 | E81: MG997FR63F | F81: DEMIGLOBAL MULTISERVICE | G81: SOLD | J81: 0 | L81: 0 | M81: {"S/N":"80","IMEI":"MG997FR63F","TIME":"","COLOUR":"BLACK","DEVICE":"IWATCH","STORAGE":"-","Column 17":"","Column 24":"","Column 25":"","Column 26":"","Column 27":"","Column 28":"","Column 29":"","Column 30":"","Column 31":"","Column 36":"","Column 37":"","Column 38":"","Column 39":"","Column 40":"","Column 41":"","Column 42":"","Column 43":"","Column 44":"","Column 45":"","Column 46":"","Column 47":"","PAID DATE":"","RECORD_ID":"30bccf2c9b744fd89788a68d27784f73","BATTERY. H":"-","CONDITIONS":"RETURNED","COST PRICE":"","DATE BOUGHT":"1/6/2025","DESCRIPTION":"IWATCH SERIES 7","DEAL LOCATION":"","INTERNAL NOTE":"","NAME OF BUYER":"DEMIGLOBAL MULTISERVICE","EXPENSE AMOUNT":"","NAME OF SELLER":"DEMIGLOBAL MULTISERVICE","PRODUCT STATUS":"SOLD","STATUS OF DEVICE":"UNLOCKED","CALCULATED PROFIT":"","EXPENSE DESCRIPTION":"","PHONE NUMBER OF BUYER":"09066720385","AVAILABILITY/DATE SOLD":"1/7/2025","PHONE NUMBER OF SELLER":"","RECEIPT & EVIDIENCE LINK":""} | N81: 2026-05-11T22:00:10.014056+01:00 | O81: 2026-05-11T22:00:10.014056+01:00
A82: 0001a5968788456482cfdae3e13e753b | B82: 0001a5968788456482cfdae3e13e753b | C82: da6cbccda6a66d32423e91d27435a2d4b4405077eda150c8e001280c3446fb1d | D82: 84 | E82: 355224389539567 | F82: DREY GADGET | G82: SOLD | J82: 0 | L82: 0 | M82: {"S/N":"81","IMEI":"355224389539567","TIME":"","COLOUR":"SIERRA BLUE","DEVICE":"IPHONE","STORAGE":"256GB","Column 17":"","Column 24":"","Column 25":"","Column 26":"","Column 27":"","Column 28":"","Column 29":"","Column 30":"","Column 31":"","Column 36":"","Column 37":"","Column 38":"","Column 39":"","Column 40":"","Column 41":"","Column 42":"","Column 43":"","Column 44":"","Column 45":"","Column 46":"","Column 47":"","PAID DATE":"","RECORD_ID":"0001a5968788456482cfdae3e13e753b","BATTERY. H":"82 (85%)","CONDITIONS":"$720,000.00","COST PRICE":"","DATE BOUGHT":"1/16/2025","DESCRIPTION":"IPHONE 13 PRO","DEAL LOCATION":"","INTERNAL NOTE":"","NAME OF BUYER":"DREY GADGET","EXPENSE AMOUNT":"","NAME OF SELLER":"KHAFE GADGET","PRODUCT STATUS":"SOLD","STATUS OF DEVICE":"UNLOCKED","CALCULATED PROFIT":"","EXPENSE DESCRIPTION":"","PHONE NUMBER OF BUYER":"09135770042","AVAILABILITY/DATE SOLD":"1/17/2025","PHONE NUMBER OF SELLER":"07048121888","RECEIPT & EVIDIENCE LINK":""} | N82: 2026-05-11T22:00:10.014056+01:00 | O82: 2026-05-11T22:00:10.014056+01:00
A83: df1230dc64394ab7b5a963e8f53e2db3 | B83: df1230dc64394ab7b5a963e8f53e2db3 | C83: d49aa247bd4c19c4f49abb85564edfe08c16b6f36ba0e63af0478884d86d1a5f | D83: 85 | E83: 353967815303147 | F83: ZEE TECH | G83: SOLD | J83: 0 | L83: 0 | M83: {"S/N":"82","IMEI":"353967815303147","TIME":"","COLOUR":"GOLD","DEVICE":"IPHONE","STORAGE":"128GB","Column 17":"","Column 24":"","Column 25":"","Column 26":"","Column 27":"","Column 28":"","Column 29":"","Column 30":"","Column 31":"","Column 36":"","Column 37":"","Column 38":"","Column 39":"","Column 40":"","Column 41":"","Column 42":"","Column 43":"","Column 44":"","Column 45":"","Column 46":"","Column 47":"","PAID DATE":"","RECORD_ID":"df1230dc64394ab7b5a963e8f53e2db3","BATTERY. H":"93%","CONDITIONS":"$800,000.00","COST PRICE":"","DATE BOUGHT":"1/13/2025","DESCRIPTION":"IPHONE 13 PRO MAX","DEAL LOCATION":"","INTERNAL NOTE":"","NAME OF BUYER":"ZEE TECH","EXPENSE AMOUNT":"","NAME OF SELLER":"IBRAHIM GADGET","PRODUCT STATUS":"SOLD","STATUS OF DEVICE":"UNLOCKED","CALCULATED PROFIT":"","EXPENSE DESCRIPTION":"","PHONE NUMBER OF BUYER":"09033724061","AVAILABILITY/DATE SOLD":"1/27/2025","PHONE NUMBER OF SELLER":"09060724788","RECEIPT & EVIDIENCE LINK":""} | N83: 2026-05-11T22:00:10.014056+01:00 | O83: 2026-05-11T22:00:10.014056+01:00
A84: 10b59a02ebbd40b7b9039b96a5755885 | B84: 10b59a02ebbd40b7b9039b96a5755885 | C84: 0bc0b1e66cda938b13c3bfa722d065f5681444626f8c0af512bdda053e2bb6f9 | D84: 86 | E84: 352051692366989 | F84: SEYIFUNMI | G84: SOLD | J84: 0 | L84: 0 | M84: {"S/N":"83","IMEI":"352051692366989","TIME":"","COLOUR":"SIERRA BLUE","DEVICE":"IPHONE","STORAGE":"128GB","Column 17":"","Column 24":"","Column 25":"","Column 26":"","Column 27":"","Column 28":"","Column 29":"","Column 30":"","Column 31":"","Column 36":"","Column 37":"","Column 38":"","Column 39":"","Column 40":"","Column 41":"","Column 42":"","Column 43":"","Column 44":"","Column 45":"","Column 46":"","Column 47":"","PAID DATE":"","RECORD_ID":"10b59a02ebbd40b7b9039b96a5755885","BATTERY. H":"86%","CONDITIONS":"$700,000.00","COST PRICE":"","DATE BOUGHT":"1/21/2025","DESCRIPTION":"IPHONE 13 PRO MAX","DEAL LOCATION":"","INTERNAL NOTE":"","NAME OF BUYER":"SEYIFUNMI","EXPENSE AMOUNT":"","NAME OF SELLER":"SEYIFUNMI","PRODUCT STATUS":"SOLD","STATUS OF DEVICE":"LOCKED","CALCULATED PROFIT":"","EXPENSE DESCRIPTION":"","PHONE NUMBER OF BUYER":"07065500068","AVAILABILITY/DATE SOLD":"2/11/2025","PHONE NUMBER OF SELLER":"07065500068","RECEIPT & EVIDIENCE LINK":""} | N84: 2026-05-11T22:00:10.014056+01:00 | O84: 2026-05-11T22:00:10.014056+01:00
